Workbook
Name japan: 'BIS + EDBA Final'!$D$116

Sheet Filtered G500
B1: Company | C1: HQ | D1: Industry | E1: Employees | F1: Emp Count | G1: MSK RISK | H1: BIS | I1: EDBA | J1: CBG | K1: Total Score | L1: Revenues ($M) | M1: Rev % Change | N1: Profits ($M) | O1: Profits % Change | P1: Assets ($M) | Q1: Change in Rank | R1: Years on Global 500 List
B2: United Parcel Service | C2: United States | D2: Logistics | E2: 372180 | F2: {=_xlfn.IFS( E2<=$E$245,0, E2<=$E$246,1, E2<=$E$247,2, E2>=$E$247,3)} -> 3 | G2: {=_xlfn.IFS( OR(D2="Aerospace",D2="Aerospace & Defense",D2="Agricultural Equipment",D2="Airlines",D2="Automotive",D2="Automotive & Energy",D2="Automotive Components",D2="Aviation",D2="Building Materials",D2="Chemicals",D2="Commercial Vehicles",D2="Conglomerate & Defense",D2="Conglomerate & Energy",D2="Construction",D2="Construction & Infrastructure",D2="Construction & Real Estate",D2="Construction & Telecom",D2="Discount Retail",D2="Energy Management",D2="Energy Technology",D2="Engines & Power Systems",D2="Environmental Services",D2="Food Distribution",D2="Food Services",D2="Grocery Retail",D2="Healthcare & Pharmacy",D2="Home Improvement Retail",D2="Industrial Engineering & Electronics",D2="Oilfield Services",D2="Pharmaceuticals",D2="Pharmaceuticals & Chemicals",D2="Pharmaceuticals & Healthcare",D2="Pharmacy Retail",D2="Postal & Logistics",D2="Retail",D2="Retail & Distribution",D2="Retail & Grocery",D2="Retail (IKEA)",D2="Tobacco",D2="Trading & Conglomerate",D2="Utilities",D2="Utilities & Energy",D2="Wholesale Retail"),2, OR(D2="Agribusiness",D2="Automotive & Heavy Vehicles",D2="Chemicals",D2="Commercial Vehicles",D2="Construction",D2="Construction & Infrastructure",D2="Engines & Power Systems",D2="Food Processing",D2="Healthcare",D2="Healthcare & Medical Devices",D2="Heavy Equipment",D2="Heavy Industry",D2="Industrial Gases",D2="Industrial Manufacturing",D2="Logistics",D2="Medical Devices",D2="Mining",D2="Mining & Commodities Trading",D2="Oil & Gas",D2="Oilfield Services",D2="Rail Transport",D2="Shipping & Logistics",D2="Steel"),3, OR(D2="Apparel & Footwear",D2="Beverage",D2="Coffeehouse & Retail",D2="Conglomerate",D2="Consumer Goods",D2="Convenience Retail",D2="Electronics",D2="Electronics & Semiconductors",D2="Electronics Retail",D2="Fashion Retail",D2="Food & Beverage",D2="Food Retail & Consumer Goods",D2="Industrial & Technology",D2="Industrial Automation",D2="Industrial Technology",D2="Postal & Financial Services",D2="Postal Services",D2="Scientific Instruments",D2="Technology Hardware",D2="Trading Company",D2="IT Consulting"),1, OR(D2="Cosmetics",D2="E-commerce & Cloud Computing",D2="Electronics & Entertainment",D2="Entertainment & Media",D2="Luxury Goods",D2="Media & Telecommunications",D2="Networking Technology",D2="Real Estate Services",D2="Technology & Consumer Electronics",D2="Telecommunications",D2="Telecommunications & Investment"),1, OR(D2="Asset Management",D2="Banking",D2="Banking & Asset Services",D2="Banking & Financial Services",D2="Banking & Wealth Management",D2="Cloud Software",D2="Enterprise Software",D2="Financial Services",D2="Information Technology Consulting",D2="Investment Banking",D2="Social Media & Technology",D2="Software & Cloud Computing",D2="Technology & Consulting",D2="Technology & Internet Services",D2="Technology & Software"),1, TRUE,"Unmapped" )} -> 3 | H2: =VLOOKUP(B2,'BIS + EDBA Final'!A:K,2,FALSE) -> 1 | I2: =VLOOKUP(B2,'BIS + EDBA Final'!A:F,6,FALSE) -> 1 | J2: =VLOOKUP(B2,'CBG Final'!A:B,2,FALSE) -> 3 | K2: =0.3*F2+0.2*G2+0.2*H2+I2*0.1+J2*0.2 -> 2.4 | L2: 91,070 | M2: 0.1% | N2: 5,782 | O2: -13.8% | P2: 70,070 | Q2: 1 | R2: 31
B3: FedEx | C3: United States | D3: Logistics | E3: 494824 | F3: {=_xlfn.IFS( E3<=$E$245,0, E3<=$E$246,1, E3<=$E$247,2, E3>=$E$247,3)} -> 3 | G3: {=_xlfn.IFS( OR(D3="Aerospace",D3="Aerospace & Defense",D3="Agricultural Equipment",D3="Airlines",D3="Automotive",D3="Automotive & Energy",D3="Automotive Components",D3="Aviation",D3="Building Materials",D3="Chemicals",D3="Commercial Vehicles",D3="Conglomerate & Defense",D3="Conglomerate & Energy",D3="Construction",D3="Construction & Infrastructure",D3="Construction & Real Estate",D3="Construction & Telecom",D3="Discount Retail",D3="Energy Management",D3="Energy Technology",D3="Engines & Power Systems",D3="Environmental Services",D3="Food Distribution",D3="Food Services",D3="Grocery Retail",D3="Healthcare & Pharmacy",D3="Home Improvement Retail",D3="Industrial Engineering & Electronics",D3="Oilfield Services",D3="Pharmaceuticals",D3="Pharmaceuticals & Chemicals",D3="Pharmaceuticals & Healthcare",D3="Pharmacy Retail",D3="Postal & Logistics",D3="Retail",D3="Retail & Distribution",D3="Retail & Grocery",D3="Retail (IKEA)",D3="Tobacco",D3="Trading & Conglomerate",D3="Utilities",D3="Utilities & Energy",D3="Wholesale Retail"),2, OR(D3="Agribusiness",D3="Automotive & Heavy Vehicles",D3="Chemicals",D3="Commercial Vehicles",D3="Construction",D3="Construction & Infrastructure",D3="Engines & Power Systems",D3="Food Processing",D3="Healthcare",D3="Healthcare & Medical Devices",D3="Heavy Equipment",D3="Heavy Industry",D3="Industrial Gases",D3="Industrial Manufacturing",D3="Logistics",D3="Medical Devices",D3="Mining",D3="Mining & Commodities Trading",D3="Oil & Gas",D3="Oilfield Services",D3="Rail Transport",D3="Shipping & Logistics",D3="Steel"),3, OR(D3="Apparel & Footwear",D3="Beverage",D3="Coffeehouse & Retail",D3="Conglomerate",D3="Consumer Goods",D3="Convenience Retail",D3="Electronics",D3="Electronics & Semiconductors",D3="Electronics Retail",D3="Fashion Retail",D3="Food & Beverage",D3="Food Retail & Consumer Goods",D3="Industrial & Technology",D3="Industrial Automation",D3="Industrial Technology",D3="Postal & Financial Services",D3="Postal Services",D3="Scientific Instruments",D3="Technology Hardware",D3="Trading Company",D3="IT Consulting"),1, OR(D3="Cosmetics",D3="E-commerce & Cloud Computing",D3="Electronics & Entertainment",D3="Entertainment & Media",D3="Luxury Goods",D3="Media & Telecommunications",D3="Networking Technology",D3="Real Estate Services",D3="Technology & Consumer Electronics",D3="Telecommunications",D3="Telecommunications & Investment"),1, OR(D3="Asset Management",D3="Banking",D3="Banking & Asset Services",D3="Banking & Financial Services",D3="Banking & Wealth Management",D3="Cloud Software",D3="Enterprise Software",D3="Financial Services",D3="Information Technology Consulting",D3="Investment Banking",D3="Social Media & Technology",D3="Software & Cloud Computing",D3="Technology & Consulting",D3="Technology & Internet Services",D3="Technology & Software"),1, TRUE,"Unmapped" )} -> 3 | H3: =VLOOKUP(B3,'BIS + EDBA Final'!A:K,2,FALSE) -> 1 | I3: =VLOOKUP(B3,'BIS + EDBA Final'!A:F,6,FALSE) -> 1 | J3: =VLOOKUP(B3,'CBG Final'!A:B,2,FALSE) -> 3 | K3: =0.3*F3+0.2*G3+0.2*H3+I3*0.1+J3*0.2 -> 2.4 | L3: 87,693 | M3: -2.7% | N3: 4,331 | O3: 9% | P3: 87,007 | Q3: -8 | R3: 31
B4: Tesco | C4: United Kingdom | D4: Retail | E4: 229140 | F4: {=_xlfn.IFS( E4<=$E$245,0, E4<=$E$246,1, E4<=$E$247,2, E4>=$E$247,3)} -> 3 | G4: {=_xlfn.IFS( OR(D4="Aerospace",D4="Aerospace & Defense",D4="Agricultural Equipment",D4="Airlines",D4="Automotive",D4="Automotive & Energy",D4="Automotive Components",D4="Aviation",D4="Building Materials",D4="Chemicals",D4="Commercial Vehicles",D4="Conglomerate & Defense",D4="Conglomerate & Energy",D4="Construction",D4="Construction & Infrastructure",D4="Construction & Real Estate",D4="Construction & Telecom",D4="Discount Retail",D4="Energy Management",D4="Energy Technology",D4="Engines & Power Systems",D4="Environmental Services",D4="Food Distribution",D4="Food Services",D4="Grocery Retail",D4="Healthcare & Pharmacy",D4="Home Improvement Retail",D4="Industrial Engineering & Electronics",D4="Oilfield Services",D4="Pharmaceuticals",D4="Pharmaceuticals & Chemicals",D4="Pharmaceuticals & Healthcare",D4="Pharmacy Retail",D4="Postal & Logistics",D4="Retail",D4="Retail & Distribution",D4="Retail & Grocery",D4="Retail (IKEA)",D4="Tobacco",D4="Trading & Conglomerate",D4="Utilities",D4="Utilities & Energy",D4="Wholesale Retail"),2, OR(D4="Agribusiness",D4="Automotive & Heavy Vehicles",D4="Chemicals",D4="Commercial Vehicles",D4="Construction",D4="Construction & Infrastructure",D4="Engines & Power Systems",D4="Food Processing",D4="Healthcare",D4="Healthcare & Medical Devices",D4="Heavy Equipment",D4="Heavy Industry",D4="Industrial Gases",D4="Industrial Manufacturing",D4="Logistics",D4="Medical Devices",D4="Mining",D4="Mining & Commodities Trading",D4="Oil & Gas",D4="Oilfield Services",D4="Rail Transport",D4="Shipping & Logistics",D4="Steel"),3, OR(D4="Apparel & Footwear",D4="Beverage",D4="Coffeehouse & Retail",D4="Conglomerate",D4="Consumer Goods",D4="Convenience Retail",D4="Electronics",D4="Electronics & Semiconductors",D4="Electronics Retail",D4="Fashion Retail",D4="Food & Beverage",D4="Food Retail & Consumer Goods",D4="Industrial & Technology",D4="Industrial Automation",D4="Industrial Technology",D4="Postal & Financial Services",D4="Postal Services",D4="Scientific Instruments",D4="Technology Hardware",D4="Trading Company",D4="IT Consulting"),1, OR(D4="Cosmetics",D4="E-commerce & Cloud Computing",D4="Electronics & Entertainment",D4="Entertainment & Media",D4="Luxury Goods",D4="Media & Telecommunications",D4="Networking Technology",D4="Real Estate Services",D4="Technology & Consumer Electronics",D4="Telecommunications",D4="Telecommunications & Investment"),1, OR(D4="Asset Management",D4="Banking",D4="Banking & Asset Services",D4="Banking & Financial Services",D4="Banking & Wealth Management",D4="Cloud Software",D4="Enterprise Software",D4="Financial Services",D4="Information Technology Consulting",D4="Investment Banking",D4="Social Media & Technology",D4="Software & Cloud Computing",D4="Technology & Consulting",D4="Technology & Internet Services",D4="Technology & Software"),1, TRUE,"Unmapped" )} -> 2 | H4: =VLOOKUP(B4,'BIS + EDBA Final'!A:K,2,FALSE) -> 2 | I4: =VLOOKUP(B4,'BIS + EDBA Final'!A:F,6,FALSE) -> 1 | J4: =VLOOKUP(B4,'CBG Final'!A:B,2,FALSE) -> 3 | K4: =0.3*F4+0.2*G4+0.2*H4+I4*0.1+J4*0.2 -> 2.4 | L4: 89,745.6 | M4: 4.1% | N4: 2,071 | O4: 39.3% | P4: 48,961.4 | Q4: 11 | R4: 31
B5: Walgreens Boots Alliance | C5: United States | D5: Pharmacy Retail | E5: 252500 | F5: {=_xlfn.IFS( E5<=$E$245,0, E5<=$E$246,1, E5<=$E$247,2, E5>=$E$247,3)} -> 3 | G5: {=_xlfn.IFS( OR(D5="Aerospace",D5="Aerospace & Defense",D5="Agricultural Equipment",D5="Airlines",D5="Automotive",D5="Automotive & Energy",D5="Automotive Components",D5="Aviation",D5="Building Materials",D5="Chemicals",D5="Commercial Vehicles",D5="Conglomerate & Defense",D5="Conglomerate & Energy",D5="Construction",D5="Construction & Infrastructure",D5="Construction & Real Estate",D5="Construction & Telecom",D5="Discount Retail",D5="Energy Management",D5="Energy Technology",D5="Engines & Power Systems",D5="Environmental Services",D5="Food Distribution",D5="Food Services",D5="Grocery Retail",D5="Healthcare & Pharmacy",D5="Home Improvement Retail",D5="Industrial Engineering & Electronics",D5="Oilfield Services",D5="Pharmaceuticals",D5="Pharmaceuticals & Chemicals",D5="Pharmaceuticals & Healthcare",D5="Pharmacy Retail",D5="Postal & Logistics",D5="Retail",D5="Retail & Distribution",D5="Retail & Grocery",D5="Retail (IKEA)",D5="Tobacco",D5="Trading & Conglomerate",D5="Utilities",D5="Utilities & Energy",D5="Wholesale Retail"),2, OR(D5="Agribusiness",D5="Automotive & Heavy Vehicles",D5="Chemicals",D5="Commercial Vehicles",D5="Construction",D5="Construction & Infrastructure",D5="Engines & Power Systems",D5="Food Processing",D5="Healthcare",D5="Healthcare & Medical Devices",D5="Heavy Equipment",D5="Heavy Industry",D5="Industrial Gases",D5="Industrial Manufacturing",D5="Logistics",D5="Medical Devices",D5="Mining",D5="Mining & Commodities Trading",D5="Oil & Gas",D5="Oilfield Services",D5="Rail Transport",D5="Shipping & Logistics",D5="Steel"),3, OR(D5="Apparel & Footwear",D5="Beverage",D5="Coffeehouse & Retail",D5="Conglomerate",D5="Consumer Goods",D5="Convenience Retail",D5="Electronics",D5="Electronics & Semiconductors",D5="Electronics Retail",D5="Fashion Retail",D5="Food & Beverage",D5="Food Retail & Consumer Goods",D5="Industrial & Technology",D5="Industrial Automation",D5="Industrial Technology",D5="Postal & Financial Services",D5="Postal Services",D5="Scientific Instruments",D5="Technology Hardware",D5="Trading Company",D5="IT Consulting"),1, OR(D5="Cosmetics",D5="E-commerce & Cloud Computing",D5="Electronics & Entertainment",D5="Entertainment & Media",D5="Luxury Goods",D5="Media & Telecommunications",D5="Networking Technology",D5="Real Estate Services",D5="Technology & Consumer Electronics",D5="Telecommunications",D5="Telecommunications & Investment"),1, OR(D5="Asset Management",D5="Banking",D5="Banking & Asset Services",D5="Banking & Financial Services",D5="Banking & Wealth Management",D5="Cloud Software",D5="Enterprise Software",D5="Financial Services",D5="Information Technology Consulting",D5="Investment Banking",D5="Social Media & Technology",D5="Software & Cloud Computing",D5="Technology & Consulting",D5="Technology & Internet Services",D5="Technology & Software"),1, TRUE,"Unmapped" )} -> 2 | H5: 2 | I5: =VLOOKUP(B5,'BIS + EDBA Final'!A:F,6,FALSE) -> 1 | J5: =VLOOKUP(B5,'CBG Final'!A:B,2,FALSE) -> 3 | K5: =0.3*F5+0.2*G5+0.2*H5+I5*0.1+J5*0.2 -> 2.4 | L5: 147,658 | M5: 6.2% | N5: -8,636 | P5: 81,037 | Q5: 8 | R5: 31
B6: Abbott Laboratories | C6: United States | D6: Healthcare & Medical Devices | E6: 114000 | F6: {=_xlfn.IFS( E6<=$E$245,0, E6<=$E$246,1, E6<=$E$247,2, E6>=$E$247,3)} -> 2 | G6: {=_xlfn.IFS( OR(D6="Aerospace",D6="Aerospace & Defense",D6="Agricultural Equipment",D6="Airlines",D6="Automotive",D6="Automotive & Energy",D6="Automotive Components",D6="Aviation",D6="Building Materials",D6="Chemicals",D6="Commercial Vehicles",D6="Conglomerate & Defense",D6="Conglomerate & Energy",D6="Construction",D6="Construction & Infrastructure",D6="Construction & Real Estate",D6="Construction & Telecom",D6="Discount Retail",D6="Energy Management",D6="Energy Technology",D6="Engines & Power Systems",D6="Environmental Services",D6="Food Distribution",D6="Food Services",D6="Grocery Retail",D6="Healthcare & Pharmacy",D6="Home Improvement Retail",D6="Industrial Engineering & Electronics",D6="Oilfield Services",D6="Pharmaceuticals",D6="Pharmaceuticals & Chemicals",D6="Pharmaceuticals & Healthcare",D6="Pharmacy Retail",D6="Postal & Logistics",D6="Retail",D6="Retail & Distribution",D6="Retail & Grocery",D6="Retail (IKEA)",D6="Tobacco",D6="Trading & Conglomerate",D6="Utilities",D6="Utilities & Energy",D6="Wholesale Retail"),2, OR(D6="Agribusiness",D6="Automotive & Heavy Vehicles",D6="Chemicals",D6="Commercial Vehicles",D6="Construction",D6="Construction & Infrastructure",D6="Engines & Power Systems",D6="Food Processing",D6="Healthcare",D6="Healthcare & Medical Devices",D6="Heavy Equipment",D6="Heavy Industry",D6="Industrial Gases",D6="Industrial Manufacturing",D6="Logistics",D6="Medical Devices",D6="Mining",D6="Mining & Commodities Trading",D6="Oil & Gas",D6="Oilfield Services",D6="Rail Transport",D6="Shipping & Logistics",D6="Steel"),3, OR(D6="Apparel & Footwear",D6="Beverage",D6="Coffeehouse & Retail",D6="Conglomerate",D6="Consumer Goods",D6="Convenience Retail",D6="Electronics",D6="Electronics & Semiconductors",D6="Electronics Retail",D6="Fashion Retail",D6="Food & Beverage",D6="Food Retail & Consumer Goods",D6="Industrial & Technology",D6="Industrial Automation",D6="Industrial Technology",D6="Postal & Financial Services",D6="Postal Services",D6="Scientific Instruments",D6="Technology Hardware",D6="Trading Company",D6="IT Consulting"),1, OR(D6="Cosmetics",D6="E-commerce & Cloud Computing",D6="Electronics & Entertainment",D6="Entertainment & Media",D6="Luxury Goods",D6="Media & Telecommunications",D6="Networking Technology",D6="Real Estate Services",D6="Technology & Consumer Electronics",D6="Telecommunications",D6="Telecommunications & Investment"),1, OR(D6="Asset Management",D6="Banking",D6="Banking & Asset Services",D6="Banking & Financial Services",D6="Banking & Wealth Management",D6="Cloud Software",D6="Enterprise Software",D6="Financial Services",D6="Information Technology Consulting",D6="Investment Banking",D6="Social Media & Technology",D6="Software & Cloud Computing",D6="Technology & Consulting",D6="Technology & Internet Services",D6="Technology & Software"),1, TRUE,"Unmapped" )} -> 3 | H6: 2 | I6: =VLOOKUP(B6,'BIS + EDBA Final'!A:F,6,FALSE) -> 1 | J6: =VLOOKUP(B6,'CBG Final'!A:B,2,FALSE) -> 3 | K6: =0.3*F6+0.2*G6+0.2*H6+I6*0.1+J6*0.2 -> 2.3 | L6: 41,950 | M6: 4.6% | N6: 13,402 | O6: 134.2% | P6: 81,414 | Q6: 4 | R6: 27
B7: Caterpillar | C7: United States | D7: Heavy Equipment | E7: 112900 | F7: {=_xlfn.IFS( E7<=$E$245,0, E7<=$E$246,1, E7<=$E$247,2, E7>=$E$247,3)} -> 2 | G7: {=_xlfn.IFS( OR(D7="Aerospace",D7="Aerospace & Defense",D7="Agricultural Equipment",D7="Airlines",D7="Automotive",D7="Automotive & Energy",D7="Automotive Components",D7="Aviation",D7="Building Materials",D7="Chemicals",D7="Commercial Vehicles",D7="Conglomerate & Defense",D7="Conglomerate & Energy",D7="Construction",D7="Construction & Infrastructure",D7="Construction & Real Estate",D7="Construction & Telecom",D7="Discount Retail",D7="Energy Management",D7="Energy Technology",D7="Engines & Power Systems",D7="Environmental Services",D7="Food Distribution",D7="Food Services",D7="Grocery Retail",D7="Healthcare & Pharmacy",D7="Home Improvement Retail",D7="Industrial Engineering & Electronics",D7="Oilfield Services",D7="Pharmaceuticals",D7="Pharmaceuticals & Chemicals",D7="Pharmaceuticals & Healthcare",D7="Pharmacy Retail",D7="Postal & Logistics",D7="Retail",D7="Retail & Distribution",D7="Retail & Grocery",D7="Retail (IKEA)",D7="Tobacco",D7="Trading & Conglomerate",D7="Utilities",D7="Utilities & Energy",D7="Wholesale Retail"),2, OR(D7="Agribusiness",D7="Automotive & Heavy Vehicles",D7="Chemicals",D7="Commercial Vehicles",D7="Construction",D7="Construction & Infrastructure",D7="Engines & Power Systems",D7="Food Processing",D7="Healthcare",D7="Healthcare & Medical Devices",D7="Heavy Equipment",D7="Heavy Industry",D7="Industrial Gases",D7="Industrial Manufacturing",D7="Logistics",D7="Medical Devices",D7="Mining",D7="Mining & Commodities Trading",D7="Oil & Gas",D7="Oilfield Services",D7="Rail Transport",D7="Shipping & Logistics",D7="Steel"),3, OR(D7="Apparel & Footwear",D7="Beverage",D7="Coffeehouse & Retail",D7="Conglomerate",D7="Consumer Goods",D7="Convenience Retail",D7="Electronics",D7="Electronics & Semiconductors",D7="Electronics Retail",D7="Fashion Retail",D7="Food & Beverage",D7="Food Retail & Consumer Goods",D7="Industrial & Technology",D7="Industrial Automation",D7="Industrial Technology",D7="Postal & Financial Services",D7="Postal Services",D7="Scientific Instruments",D7="Technology Hardware",D7="Trading Company",D7="IT Consulting"),1, OR(D7="Cosmetics",D7="E-commerce & Cloud Computing",D7="Electronics & Entertainment",D7="Entertainment & Media",D7="Luxury Goods",D7="Media & Telecommunications",D7="Networking Technology",D7="Real Estate Services",D7="Technology & Consumer Electronics",D7="Telecommunications",D7="Telecommunications & Investment"),1, OR(D7="Asset Management",D7="Banking",D7="Banking & Asset Services",D7="Banking & Financial Services",D7="Banking & Wealth Management",D7="Cloud Software",D7="Enterprise Software",D7="Financial Services",D7="Information Technology Consulting",D7="Investment Banking",D7="Social Media & Technology",D7="Software & Cloud Computing",D7="Technology & Consulting",D7="Technology & Internet Services",D7="Technology & Software"),1, TRUE,"Unmapped" )} -> 3 | H7: 2 | I7: =VLOOKUP(B7,'BIS + EDBA Final'!A:F,6,FALSE) -> 1 | J7: =VLOOKUP(B7,'CBG Final'!A:B,2,FALSE) -> 3 | K7: =0.3*F7+0.2*G7+0.2*H7+I7*0.1+J7*0.2 -> 2.3 | L7: 64,809 | M7: -3.4% | N7: 10,792 | O7: 4.4% | P7: 87,764 | Q7: -14 | R7: 31
B8: Siemens | C8: Germany | D8: Industrial Manufacturing | E8: 327000 | F8: {=_xlfn.IFS( E8<=$E$245,0, E8<=$E$246,1, E8<=$E$247,2, E8>=$E$247,3)} -> 3 | G8: {=_xlfn.IFS( OR(D8="Aerospace",D8="Aerospace & Defense",D8="Agricultural Equipment",D8="Airlines",D8="Automotive",D8="Automotive & Energy",D8="Automotive Components",D8="Aviation",D8="Building Materials",D8="Chemicals",D8="Commercial Vehicles",D8="Conglomerate & Defense",D8="Conglomerate & Energy",D8="Construction",D8="Construction & Infrastructure",D8="Construction & Real Estate",D8="Construction & Telecom",D8="Discount Retail",D8="Energy Management",D8="Energy Technology",D8="Engines & Power Systems",D8="Environmental Services",D8="Food Distribution",D8="Food Services",D8="Grocery Retail",D8="Healthcare & Pharmacy",D8="Home Improvement Retail",D8="Industrial Engineering & Electronics",D8="Oilfield Services",D8="Pharmaceuticals",D8="Pharmaceuticals & Chemicals",D8="Pharmaceuticals & Healthcare",D8="Pharmacy Retail",D8="Postal & Logistics",D8="Retail",D8="Retail & Distribution",D8="Retail & Grocery",D8="Retail (IKEA)",D8="Tobacco",D8="Trading & Conglomerate",D8="Utilities",D8="Utilities & Energy",D8="Wholesale Retail"),2, OR(D8="Agribusiness",D8="Automotive & Heavy Vehicles",D8="Chemicals",D8="Commercial Vehicles",D8="Construction",D8="Construction & Infrastructure",D8="Engines & Power Systems",D8="Food Processing",D8="Healthcare",D8="Healthcare & Medical Devices",D8="Heavy Equipment",D8="Heavy Industry",D8="Industrial Gases",D8="Industrial Manufacturing",D8="Logistics",D8="Medical Devices",D8="Mining",D8="Mining & Commodities Trading",D8="Oil & Gas",D8="Oilfield Services",D8="Rail Transport",D8="Shipping & Logistics",D8="Steel"),3, OR(D8="Apparel & Footwear",D8="Beverage",D8="Coffeehouse & Retail",D8="Conglomerate",D8="Consumer Goods",D8="Convenience Retail",D8="Electronics",D8="Electronics & Semiconductors",D8="Electronics Retail",D8="Fashion Retail",D8="Food & Beverage",D8="Food Retail & Consumer Goods",D8="Industrial & Technology",D8="Industrial Automation",D8="Industrial Technology",D8="Postal & Financial Services",D8="Postal Services",D8="Scientific Instruments",D8="Technology Hardware",D8="Trading Company",D8="IT Consulting"),1, OR(D8="Cosmetics",D8="E-commerce & Cloud Computing",D8="Electronics & Entertainment",D8="Entertainment & Media",D8="Luxury Goods",D8="Media & Telecommunications",D8="Networking Technology",D8="Real Estate Services",D8="Technology & Consumer Electronics",D8="Telecommunications",D8="Telecommunications & Investment"),1, OR(D8="Asset Management",D8="Banking",D8="Banking & Asset Services",D8="Banking & Financial Services",D8="Banking & Wealth Management",D8="Cloud Software",D8="Enterprise Software",D8="Financial Services",D8="Information Technology Consulting",D8="Investment Banking",D8="Social Media & Technology",D8="Software & Cloud Computing",D8="Technology & Consulting",D8="Technology & Internet Services",D8="Technology & Software"),1, TRUE,"Unmapped" )} -> 3 | H8: =VLOOKUP(B8,'BIS + EDBA Final'!A:K,2,FALSE) -> 1 | I8: =VLOOKUP(B8,'BIS + EDBA Final'!A:F,6,FALSE) -> 0 | J8: =VLOOKUP(B8,'CBG Final'!A:B,2,FALSE) -> 3 | K8: =0.3*F8+0.2*G8+0.2*H8+I8*0.1+J8*0.2 -> 2.3 | L8: 85,432.8 | M8: 3% | N8: 8,998.5 | O8: 6.2% | P8: 164,729.7 | Q8: 1 | R8: 31
B9: DHL Group | C9: Germany | D9: Logistics | E9: 559051 | F9: {=_xlfn.IFS( E9<=$E$245,0, E9<=$E$246,1, E9<=$E$247,2, E9>=$E$247,3)} -> 3 | G9: {=_xlfn.IFS( OR(D9="Aerospace",D9="Aerospace & Defense",D9="Agricultural Equipment",D9="Airlines",D9="Automotive",D9="Automotive & Energy",D9="Automotive Components",D9="Aviation",D9="Building Materials",D9="Chemicals",D9="Commercial Vehicles",D9="Conglomerate & Defense",D9="Conglomerate & Energy",D9="Construction",D9="Construction & Infrastructure",D9="Construction & Real Estate",D9="Construction & Telecom",D9="Discount Retail",D9="Energy Management",D9="Energy Technology",D9="Engines & Power Systems",D9="Environmental Services",D9="Food Distribution",D9="Food Services",D9="Grocery Retail",D9="Healthcare & Pharmacy",D9="Home Improvement Retail",D9="Industrial Engineering & Electronics",D9="Oilfield Services",D9="Pharmaceuticals",D9="Pharmaceuticals & Chemicals",D9="Pharmaceuticals & Healthcare",D9="Pharmacy Retail",D9="Postal & Logistics",D9="Retail",D9="Retail & Distribution",D9="Retail & Grocery",D9="Retail (IKEA)",D9="Tobacco",D9="Trading & Conglomerate",D9="Utilities",D9="Utilities & Energy",D9="Wholesale Retail"),2, OR(D9="Agribusiness",D9="Automotive & Heavy Vehicles",D9="Chemicals",D9="Commercial Vehicles",D9="Construction",D9="Construction & Infrastructure",D9="Engines & Power Systems",D9="Food Processing",D9="Healthcare",D9="Healthcare & Medical Devices",D9="Heavy Equipment",D9="Heavy Industry",D9="Industrial Gases",D9="Industrial Manufacturing",D9="Logistics",D9="Medical Devices",D9="Mining",D9="Mining & Commodities Trading",D9="Oil & Gas",D9="Oilfield Services",D9="Rail Transport",D9="Shipping & Logistics",D9="Steel"),3, OR(D9="Apparel & Footwear",D9="Beverage",D9="Coffeehouse & Retail",D9="Conglomerate",D9="Consumer Goods",D9="Convenience Retail",D9="Electronics",D9="Electronics & Semiconductors",D9="Electronics Retail",D9="Fashion Retail",D9="Food & Beverage",D9="Food Retail & Consumer Goods",D9="Industrial & Technology",D9="Industrial Automation",D9="Industrial Technology",D9="Postal & Financial Services",D9="Postal Services",D9="Scientific Instruments",D9="Technology Hardware",D9="Trading Company",D9="IT Consulting"),1, OR(D9="Cosmetics",D9="E-commerce & Cloud Computing",D9="Electronics & Entertainment",D9="Entertainment & Media",D9="Luxury Goods",D9="Media & Telecommunications",D9="Networking Technology",D9="Real Estate Services",D9="Technology & Consumer Electronics",D9="Telecommunications",D9="Telecommunications & Investment"),1, OR(D9="Asset Management",D9="Banking",D9="Banking & Asset Services",D9="Banking & Financial Services",D9="Banking & Wealth Management",D9="Cloud Software",D9="Enterprise Software",D9="Financial Services",D9="Information Technology Consulting",D9="Investment Banking",D9="Social Media & Technology",D9="Software & Cloud Computing",D9="Technology & Consulting",D9="Technology & Internet Services",D9="Technology & Software"),1, TRUE,"Unmapped" )} -> 3 | H9: =VLOOKUP(B9,'BIS + EDBA Final'!A:K,2,FALSE) -> 2 | I9: =VLOOKUP(B9,'BIS + EDBA Final'!A:F,6,FALSE) -> 0 | J9: =VLOOKUP(B9,'CBG Final'!A:B,2,FALSE) -> 2 | K9: =0.3*F9+0.2*G9+0.2*H9+I9*0.1+J9*0.2 -> 2.3 | L9: 91,041.4 | M9: 3% | N9: 3,603.3 | O9: -9.4% | P9: 72,349.4 | Q9: 10 | R9: 31
B10: Deutsche Bahn | C10: Germany | D10: Rail Transport | E10: 296662 | F10: {=_xlfn.IFS( E10<=$E$245,0, E10<=$E$246,1, E10<=$E$247,2, E10>=$E$247,3)} -> 3 | G10: {=_xlfn.IFS( OR(D10="Aerospace",D10="Aerospace & Defense",D10="Agricultural Equipment",D10="Airlines",D10="Automotive",D10="Automotive & Energy",D10="Automotive Components",D10="Aviation",D10="Building Materials",D10="Chemicals",D10="Commercial Vehicles",D10="Conglomerate & Defense",D10="Conglomerate & Energy",D10="Construction",D10="Construction & Infrastructure",D10="Construction & Real Estate",D10="Construction & Telecom",D10="Discount Retail",D10="Energy Management",D10="Energy Technology",D10="Engines & Power Systems",D10="Environmental Services",D10="Food Distribution",D10="Food Services",D10="Grocery Retail",D10="Healthcare & Pharmacy",D10="Home Improvement Retail",D10="Industrial Engineering & Electronics",D10="Oilfield Services",D10="Pharmaceuticals",D10="Pharmaceuticals & Chemicals",D10="Pharmaceuticals & Healthcare",D10="Pharmacy Retail",D10="Postal & Logistics",D10="Retail",D10="Retail & Distribution",D10="Retail & Grocery",D10="Retail (IKEA)",D10="Tobacco",D10="Trading & Conglomerate",D10="Utilities",D10="Utilities & Energy",D10="Wholesale Retail"),2, OR(D10="Agribusiness",D10="Automotive & Heavy Vehicles",D10="Chemicals",D10="Commercial Vehicles",D10="Construction",D10="Construction & Infrastructure",D10="Engines & Power Systems",D10="Food Processing",D10="Healthcare",D10="Healthcare & Medical Devices",D10="Heavy Equipment",D10="Heavy Industry",D10="Industrial Gases",D10="Industrial Manufacturing",D10="Logistics",D10="Medical Devices",D10="Mining",D10="Mining & Commodities Trading",D10="Oil & Gas",D10="Oilfield Services",D10="Rail Transport",D10="Shipping & Logistics",D10="Steel"),3, OR(D10="Apparel & Footwear",D10="Beverage",D10="Coffeehouse & Retail",D10="Conglomerate",D10="Consumer Goods",D10="Convenience Retail",D10="Electronics",D10="Electronics & Semiconductors",D10="Electronics Retail",D10="Fashion Retail",D10="Food & Beverage",D10="Food Retail & Consumer Goods",D10="Industrial & Technology",D10="Industrial Automation",D10="Industrial Technology",D10="Postal & Financial Services",D10="Postal Services",D10="Scientific Instruments",D10="Technology Hardware",D10="Trading Company",D10="IT Consulting"),1, OR(D10="Cosmetics",D10="E-commerce & Cloud Computing",D10="Electronics & Entertainment",D10="Entertainment & Media",D10="Luxury Goods",D10="Media & Telecommunications",D10="Networking Technology",D10="Real Estate Services",D10="Technology & Consumer Electronics",D10="Telecommunications",D10="Telecommunications & Investment"),1, OR(D10="Asset Management",D10="Banking",D10="Banking & Asset Services",D10="Banking & Financial Services",D10="Banking & Wealth Management",D10="Cloud Software",D10="Enterprise Software",D10="Financial Services",D10="Information Technology Consulting",D10="Investment Banking",D10="Social Media & Technology",D10="Software & Cloud Computing",D10="Technology & Consulting",D10="Technology & Internet Services",D10="Technology & Software"),1, TRUE,"Unmapped" )} -> 3 | H10: =VLOOKUP(B10,'BIS + EDBA Final'!A:K,2,FALSE) -> 2 | I10: =VLOOKUP(B10,'BIS + EDBA Final'!A:F,6,FALSE) -> 0 | J10: =VLOOKUP(B10,'CBG Final'!A:B,2,FALSE) -> 2 | K10: =0.3*F10+0.2*G10+0.2*H10+I10*0.1+J10*0.2 -> 2.3 | L10: 50,972.2 | M10: -4.2% | N10: -844.6 | P10: 86,868.9 | Q10: -22 | R10: 31
B11: Accenture | C11: Ireland | D11: IT Consulting | E11: 774303 | F11: {=_xlfn.IFS( E11<=$E$245,0, E11<=$E$246,1, E11<=$E$247,2, E11>=$E$247,3)} -> 3 | G11: {=_xlfn.IFS( OR(D11="Aerospace",D11="Aerospace & Defense",D11="Agricultural Equipment",D11="Airlines",D11="Automotive",D11="Automotive & Energy",D11="Automotive Components",D11="Aviation",D11="Building Materials",D11="Chemicals",D11="Commercial Vehicles",D11="Conglomerate & Defense",D11="Conglomerate & Energy",D11="Construction",D11="Construction & Infrastructure",D11="Construction & Real Estate",D11="Construction & Telecom",D11="Discount Retail",D11="Energy Management",D11="Energy Technology",D11="Engines & Power Systems",D11="Environmental Services",D11="Food Distribution",D11="Food Services",D11="Grocery Retail",D11="Healthcare & Pharmacy",D11="Home Improvement Retail",D11="Industrial Engineering & Electronics",D11="Oilfield Services",D11="Pharmaceuticals",D11="Pharmaceuticals & Chemicals",D11="Pharmaceuticals & Healthcare",D11="Pharmacy Retail",D11="Postal & Logistics",D11="Retail",D11="Retail & Distribution",D11="Retail & Grocery",D11="Retail (IKEA)",D11="Tobacco",D11="Trading & Conglomerate",D11="Utilities",D11="Utilities & Energy",D11="Wholesale Retail"),2, OR(D11="Agribusiness",D11="Automotive & Heavy Vehicles",D11="Chemicals",D11="Commercial Vehicles",D11="Construction",D11="Construction & Infrastructure",D11="Engines & Power Systems",D11="Food Processing",D11="Healthcare",D11="Healthcare & Medical Devices",D11="Heavy Equipment",D11="Heavy Industry",D11="Industrial Gases",D11="Industrial Manufacturing",D11="Logistics",D11="Medical Devices",D11="Mining",D11="Mining & Commodities Trading",D11="Oil & Gas",D11="Oilfield Services",D11="Rail Transport",D11="Shipping & Logistics",D11="Steel"),3, OR(D11="Apparel & Footwear",D11="Beverage",D11="Coffeehouse & Retail",D11="Conglomerate",D11="Consumer Goods",D11="Convenience Retail",D11="Electronics",D11="Electronics & Semiconductors",D11="Electronics Retail",D11="Fashion Retail",D11="Food & Beverage",D11="Food Retail & Consumer Goods",D11="Industrial & Technology",D11="Industrial Automation",D11="Industrial Technology",D11="Postal & Financial Services",D11="Postal Services",D11="Scientific Instruments",D11="Technology Hardware",D11="Trading Company",D11="IT Consulting"),1, OR(D11="Cosmetics",D11="E-commerce & Cloud Computing",D11="Electronics & Entertainment",D11="Entertainment & Media",D11="Luxury Goods",D11="Media & Telecommunications",D11="Networking Technology",D11="Real Estate Services",D11="Technology & Consumer Electronics",D11="Telecommunications",D11="Telecommunications & Investment"),1, OR(D11="Asset Management",D11="Banking",D11="Banking & Asset Services",D11="Banking & Financial Services",D11="Banking & Wealth Management",D11="Cloud Software",D11="Enterprise Software",D11="Financial Services",D11="Information Technology Consulting",D11="Investment Banking",D11="Social Media & Technology",D11="Software & Cloud Computing",D11="Technology & Consulting",D11="Technology & Internet Services",D11="Technology & Software"),1, TRUE,"Unmapped" )} -> 1 | H11: 3 | I11: =VLOOKUP(B11,'BIS + EDBA Final'!A:F,6,FALSE) -> 0 | J11: =VLOOKUP(B11,'CBG Final'!A:B,2,FALSE) -> 3 | K11: =0.3*F11+0.2*G11+0.2*H11+I11*0.1+J11*0.2 -> 2.3 | L11: 64,896.5 | M11: 1.2% | N11: 7,264.8 | O11: 5.7% | P11: 55,932.4 | Q11: - | R11: 24
B12: CVS Health | C12: United States | D12: Healthcare & Pharmacy | E12: 259500 | F12: {=_xlfn.IFS( E12<=$E$245,0, E12<=$E$246,1, E12<=$E$247,2, E12>=$E$247,3)} -> 3 | G12: {=_xlfn.IFS( OR(D12="Aerospace",D12="Aerospace & Defense",D12="Agricultural Equipment",D12="Airlines",D12="Automotive",D12="Automotive & Energy",D12="Automotive Components",D12="Aviation",D12="Building Materials",D12="Chemicals",D12="Commercial Vehicles",D12="Conglomerate & Defense",D12="Conglomerate & Energy",D12="Construction",D12="Construction & Infrastructure",D12="Construction & Real Estate",D12="Construction & Telecom",D12="Discount Retail",D12="Energy Management",D12="Energy Technology",D12="Engines & Power Systems",D12="Environmental Services",D12="Food Distribution",D12="Food Services",D12="Grocery Retail",D12="Healthcare & Pharmacy",D12="Home Improvement Retail",D12="Industrial Engineering & Electronics",D12="Oilfield Services",D12="Pharmaceuticals",D12="Pharmaceuticals & Chemicals",D12="Pharmaceuticals & Healthcare",D12="Pharmacy Retail",D12="Postal & Logistics",D12="Retail",D12="Retail & Distribution",D12="Retail & Grocery",D12="Retail (IKEA)",D12="Tobacco",D12="Trading & Conglomerate",D12="Utilities",D12="Utilities & Energy",D12="Wholesale Retail"),2, OR(D12="Agribusiness",D12="Automotive & Heavy Vehicles",D12="Chemicals",D12="Commercial Vehicles",D12="Construction",D12="Construction & Infrastructure",D12="Engines & Power Systems",D12="Food Processing",D12="Healthcare",D12="Healthcare & Medical Devices",D12="Heavy Equipment",D12="Heavy Industry",D12="Industrial Gases",D12="Industrial Manufacturing",D12="Logistics",D12="Medical Devices",D12="Mining",D12="Mining & Commodities Trading",D12="Oil & Gas",D12="Oilfield Services",D12="Rail Transport",D12="Shipping & Logistics",D12="Steel"),3, OR(D12="Apparel & Footwear",D12="Beverage",D12="Coffeehouse & Retail",D12="Conglomerate",D12="Consumer Goods",D12="Convenience Retail",D12="Electronics",D12="Electronics & Semiconductors",D12="Electronics Retail",D12="Fashion Retail",D12="Food & Beverage",D12="Food Retail & Consumer Goods",D12="Industrial & Technology",D12="Industrial Automation",D12="Industrial Technology",D12="Postal & Financial Services",D12="Postal Services",D12="Scientific Instruments",D12="Technology Hardware",D12="Trading Company",D12="IT Consulting"),1, OR(D12="Cosmetics",D12="E-commerce & Cloud Computing",D12="Electronics & Entertainment",D12="Entertainment & Media",D12="Luxury Goods",D12="Media & Telecommunications",D12="Networking Technology",D12="Real Estate Services",D12="Technology & Consumer Electronics",D12="Telecommunications",D12="Telecommunications & Investment"),1, OR(D12="Asset Management",D12="Banking",D12="Banking & Asset Services",D12="Banking & Financial Services",D12="Banking & Wealth Management",D12="Cloud Software",D12="Enterprise Software",D12="Financial Services",D12="Information Technology Consulting",D12="Investment Banking",D12="Social Media & Technology",D12="Software & Cloud Computing",D12="Technology & Consulting",D12="Technology & Internet Services",D12="Technology & Software"),1, TRUE,"Unmapped" )} -> 2 | H12: 2 | I12: =VLOOKUP(B12,'BIS + EDBA Final'!A:F,6,FALSE) -> 0 | J12: =VLOOKUP(B12,'CBG Final'!A:B,2,FALSE) -> 3 | K12: =0.3*F12+0.2*G12+0.2*H12+I12*0.1+J12*0.2 -> 2.3 | L12: 372,809 | M12: 4.2% | N12: 4,614 | O12: -44.7% | P12: 253,215 | Q12: 1 | R12: 30
B13: Nestlé | C13: Switzerland | D13: Food & Beverage | E13: 277000 | F13: {=_xlfn.IFS( E13<=$E$245,0, E13<=$E$246,1, E13<=$E$247,2, E13>=$E$247,3)} -> 3 | G13: {=_xlfn.IFS( OR(D13="Aerospace",D13="Aerospace & Defense",D13="Agricultural Equipment",D13="Airlines",D13="Automotive",D13="Automotive & Energy",D13="Automotive Components",D13="Aviation",D13="Building Materials",D13="Chemicals",D13="Commercial Vehicles",D13="Conglomerate & Defense",D13="Conglomerate & Energy",D13="Construction",D13="Construction & Infrastructure",D13="Construction & Real Estate",D13="Construction & Telecom",D13="Discount Retail",D13="Energy Management",D13="Energy Technology",D13="Engines & Power Systems",D13="Environmental Services",D13="Food Distribution",D13="Food Services",D13="Grocery Retail",D13="Healthcare & Pharmacy",D13="Home Improvement Retail",D13="Industrial Engineering & Electronics",D13="Oilfield Services",D13="Pharmaceuticals",D13="Pharmaceuticals & Chemicals",D13="Pharmaceuticals & Healthcare",D13="Pharmacy Retail",D13="Postal & Logistics",D13="Retail",D13="Retail & Distribution",D13="Retail & Grocery",D13="Retail (IKEA)",D13="Tobacco",D13="Trading & Conglomerate",D13="Utilities",D13="Utilities & Energy",D13="Wholesale Retail"),2, OR(D13="Agribusiness",D13="Automotive & Heavy Vehicles",D13="Chemicals",D13="Commercial Vehicles",D13="Construction",D13="Construction & Infrastructure",D13="Engines & Power Systems",D13="Food Processing",D13="Healthcare",D13="Healthcare & Medical Devices",D13="Heavy Equipment",D13="Heavy Industry",D13="Industrial Gases",D13="Industrial Manufacturing",D13="Logistics",D13="Medical Devices",D13="Mining",D13="Mining & Commodities Trading",D13="Oil & Gas",D13="Oilfield Services",D13="Rail Transport",D13="Shipping & Logistics",D13="Steel"),3, OR(D13="Apparel & Footwear",D13="Beverage",D13="Coffeehouse & Retail",D13="Conglomerate",D13="Consumer Goods",D13="Convenience Retail",D13="Electronics",D13="Electronics & Semiconductors",D13="Electronics Retail",D13="Fashion Retail",D13="Food & Beverage",D13="Food Retail & Consumer Goods",D13="Industrial & Technology",D13="Industrial Automation",D13="Industrial Technology",D13="Postal & Financial Services",D13="Postal Services",D13="Scientific Instruments",D13="Technology Hardware",D13="Trading Company",D13="IT Consulting"),1, OR(D13="Cosmetics",D13="E-commerce & Cloud Computing",D13="Electronics & Entertainment",D13="Entertainment & Media",D13="Luxury Goods",D13="Media & Telecommunications",D13="Networking Technology",D13="Real Estate Services",D13="Technology & Consumer Electronics",D13="Telecommunications",D13="Telecommunications & Investment"),1, OR(D13="Asset Management",D13="Banking",D13="Banking & Asset Services",D13="Banking & Financial Services",D13="Banking & Wealth Management",D13="Cloud Software",D13="Enterprise Software",D13="Financial Services",D13="Information Technology Consulting",D13="Investment Banking",D13="Social Media & Technology",D13="Software & Cloud Computing",D13="Technology & Consulting",D13="Technology & Internet Services",D13="Technology & Software"),1, TRUE,"Unmapped" )} -> 1 | H13: =VLOOKUP(B13,'BIS + EDBA Final'!A:K,2,FALSE) -> 2 | I13: =VLOOKUP(B13,'BIS + EDBA Final'!A:F,6,FALSE) -> 1 | J13: =VLOOKUP(B13,'CBG Final'!A:B,2,FALSE) -> 3 | K13: =0.3*F13+0.2*G13+0.2*H13+I13*0.1+J13*0.2 -> 2.2 | L13: 103,749.5 | M13: 0.2% | N13: 12,360.8 | O13: -0.9% | P13: 153,713 | Q13: -1 | R13: 31 | AD13: =_xlfn.PERCENTILE.INC($E$2:$E$231,0.75) -> 201189.25
B14: TJX | C14: United States | D14: Retail | E14: 364000 | F14: {=_xlfn.IFS( E14<=$E$245,0, E14<=$E$246,1, E14<=$E$247,2, E14>=$E$247,3)} -> 3 | G14: {=_xlfn.IFS( OR(D14="Aerospace",D14="Aerospace & Defense",D14="Agricultural Equipment",D14="Airlines",D14="Automotive",D14="Automotive & Energy",D14="Automotive Components",D14="Aviation",D14="Building Materials",D14="Chemicals",D14="Commercial Vehicles",D14="Conglomerate & Defense",D14="Conglomerate & Energy",D14="Construction",D14="Construction & Infrastructure",D14="Construction & Real Estate",D14="Construction & Telecom",D14="Discount Retail",D14="Energy Management",D14="Energy Technology",D14="Engines & Power Systems",D14="Environmental Services",D14="Food Distribution",D14="Food Services",D14="Grocery Retail",D14="Healthcare & Pharmacy",D14="Home Improvement Retail",D14="Industrial Engineering & Electronics",D14="Oilfield Services",D14="Pharmaceuticals",D14="Pharmaceuticals & Chemicals",D14="Pharmaceuticals & Healthcare",D14="Pharmacy Retail",D14="Postal & Logistics",D14="Retail",D14="Retail & Distribution",D14="Retail & Grocery",D14="Retail (IKEA)",D14="Tobacco",D14="Trading & Conglomerate",D14="Utilities",D14="Utilities & Energy",D14="Wholesale Retail"),2, OR(D14="Agribusiness",D14="Automotive & Heavy Vehicles",D14="Chemicals",D14="Commercial Vehicles",D14="Construction",D14="Construction & Infrastructure",D14="Engines & Power Systems",D14="Food Processing",D14="Healthcare",D14="Healthcare & Medical Devices",D14="Heavy Equipment",D14="Heavy Industry",D14="Industrial Gases",D14="Industrial Manufacturing",D14="Logistics",D14="Medical Devices",D14="Mining",D14="Mining & Commodities Trading",D14="Oil & Gas",D14="Oilfield Services",D14="Rail Transport",D14="Shipping & Logistics",D14="Steel"),3, OR(D14="Apparel & Footwear",D14="Beverage",D14="Coffeehouse & Retail",D14="Conglomerate",D14="Consumer Goods",D14="Convenience Retail",D14="Electronics",D14="Electronics & Semiconductors",D14="Electronics Retail",D14="Fashion Retail",D14="Food & Beverage",D14="Food Retail & Consumer Goods",D14="Industrial & Technology",D14="Industrial Automation",D14="Industrial Technology",D14="Postal & Financial Services",D14="Postal Services",D14="Scientific Instruments",D14="Technology Hardware",D14="Trading Company",D14="IT Consulting"),1, OR(D14="Cosmetics",D14="E-commerce & Cloud Computing",D14="Electronics & Entertainment",D14="Entertainment & Media",D14="Luxury Goods",D14="Media & Telecommunications",D14="Networking Technology",D14="Real Estate Services",D14="Technology & Consumer Electronics",D14="Telecommunications",D14="Telecommunications & Investment"),1, OR(D14="Asset Management",D14="Banking",D14="Banking & Asset Services",D14="Banking & Financial Services",D14="Banking & Wealth Management",D14="Cloud Software",D14="Enterprise Software",D14="Financial Services",D14="Information Technology Consulting",D14="Investment Banking",D14="Social Media & Technology",D14="Software & Cloud Computing",D14="Technology & Consulting",D14="Technology & Internet Services",D14="Technology & Software"),1, TRUE,"Unmapped" )} -> 2 | H14: 1 | I14: =VLOOKUP(B14,'BIS + EDBA Final'!A:F,6,FALSE) -> 1 | J14: =VLOOKUP(B14,'CBG Final'!A:B,2,FALSE) -> 3 | K14: =0.3*F14+0.2*G14+0.2*H14+I14*0.1+J14*0.2 -> 2.2 | L14: 56,360 | M14: 4% | N14: 4,864 | O14: 8.7% | P14: 31,749 | Q14: 14 | R14: 24
B15: PepsiCo | C15: United States | D15: Food & Beverage | E15: 319000 | F15: {=_xlfn.IFS( E15<=$E$245,0, E15<=$E$246,1, E15<=$E$247,2, E15>=$E$247,3)} -> 3 | G15: {=_xlfn.IFS( OR(D15="Aerospace",D15="Aerospace & Defense",D15="Agricultural Equipment",D15="Airlines",D15="Automotive",D15="Automotive & Energy",D15="Automotive Components",D15="Aviation",D15="Building Materials",D15="Chemicals",D15="Commercial Vehicles",D15="Conglomerate & Defense",D15="Conglomerate & Energy",D15="Construction",D15="Construction & Infrastructure",D15="Construction & Real Estate",D15="Construction & Telecom",D15="Discount Retail",D15="Energy Management",D15="Energy Technology",D15="Engines & Power Systems",D15="Environmental Services",D15="Food Distribution",D15="Food Services",D15="Grocery Retail",D15="Healthcare & Pharmacy",D15="Home Improvement Retail",D15="Industrial Engineering & Electronics",D15="Oilfield Services",D15="Pharmaceuticals",D15="Pharmaceuticals & Chemicals",D15="Pharmaceuticals & Healthcare",D15="Pharmacy Retail",D15="Postal & Logistics",D15="Retail",D15="Retail & Distribution",D15="Retail & Grocery",D15="Retail (IKEA)",D15="Tobacco",D15="Trading & Conglomerate",D15="Utilities",D15="Utilities & Energy",D15="Wholesale Retail"),2, OR(D15="Agribusiness",D15="Automotive & Heavy Vehicles",D15="Chemicals",D15="Commercial Vehicles",D15="Construction",D15="Construction & Infrastructure",D15="Engines & Power Systems",D15="Food Processing",D15="Healthcare",D15="Healthcare & Medical Devices",D15="Heavy Equipment",D15="Heavy Industry",D15="Industrial Gases",D15="Industrial Manufacturing",D15="Logistics",D15="Medical Devices",D15="Mining",D15="Mining & Commodities Trading",D15="Oil & Gas",D15="Oilfield Services",D15="Rail Transport",D15="Shipping & Logistics",D15="Steel"),3, OR(D15="Apparel & Footwear",D15="Beverage",D15="Coffeehouse & Retail",D15="Conglomerate",D15="Consumer Goods",D15="Convenience Retail",D15="Electronics",D15="Electronics & Semiconductors",D15="Electronics Retail",D15="Fashion Retail",D15="Food & Beverage",D15="Food Retail & Consumer Goods",D15="Industrial & Technology",D15="Industrial Automation",D15="Industrial Technology",D15="Postal & Financial Services",D15="Postal Services",D15="Scientific Instruments",D15="Technology Hardware",D15="Trading Company",D15="IT Consulting"),1, OR(D15="Cosmetics",D15="E-commerce & Cloud Computing",D15="Electronics & Entertainment",D15="Entertainment & Media",D15="Luxury Goods",D15="Media & Telecommunications",D15="Networking Technology",D15="Real Estate Services",D15="Technology & Consumer Electronics",D15="Telecommunications",D15="Telecommunications & Investment"),1, OR(D15="Asset Management",D15="Banking",D15="Banking & Asset Services",D15="Banking & Financial Services",D15="Banking & Wealth Management",D15="Cloud Software",D15="Enterprise Software",D15="Financial Services",D15="Information Technology Consulting",D15="Investment Banking",D15="Social Media & Technology",D15="Software & Cloud Computing",D15="Technology & Consulting",D15="Technology & Internet Services",D15="Technology & Software"),1, TRUE,"Unmapped" )} -> 1 | H15: 2 | I15: =VLOOKUP(B15,'BIS + EDBA Final'!A:F,6,FALSE) -> 1 | J15: =VLOOKUP(B15,'CBG Final'!A:B,2,FALSE) -> 3 | K15: =0.3*F15+0.2*G15+0.2*H15+I15*0.1+J15*0.2 -> 2.2 | L15: 91,854 | M15: 0.4% | N15: 9,578 | O15: 5.6% | P15: 99,467 | Q15: 8 | R15: 31
B16: Walt Disney | C16: United States | D16: Entertainment & Media | E16: 205040 | F16: {=_xlfn.IFS( E16<=$E$245,0, E16<=$E$246,1, E16<=$E$247,2, E16>=$E$247,3)} -> 3 | G16: {=_xlfn.IFS( OR(D16="Aerospace",D16="Aerospace & Defense",D16="Agricultural Equipment",D16="Airlines",D16="Automotive",D16="Automotive & Energy",D16="Automotive Components",D16="Aviation",D16="Building Materials",D16="Chemicals",D16="Commercial Vehicles",D16="Conglomerate & Defense",D16="Conglomerate & Energy",D16="Construction",D16="Construction & Infrastructure",D16="Construction & Real Estate",D16="Construction & Telecom",D16="Discount Retail",D16="Energy Management",D16="Energy Technology",D16="Engines & Power Systems",D16="Environmental Services",D16="Food Distribution",D16="Food Services",D16="Grocery Retail",D16="Healthcare & Pharmacy",D16="Home Improvement Retail",D16="Industrial Engineering & Electronics",D16="Oilfield Services",D16="Pharmaceuticals",D16="Pharmaceuticals & Chemicals",D16="Pharmaceuticals & Healthcare",D16="Pharmacy Retail",D16="Postal & Logistics",D16="Retail",D16="Retail & Distribution",D16="Retail & Grocery",D16="Retail (IKEA)",D16="Tobacco",D16="Trading & Conglomerate",D16="Utilities",D16="Utilities & Energy",D16="Wholesale Retail"),2, OR(D16="Agribusiness",D16="Automotive & Heavy Vehicles",D16="Chemicals",D16="Commercial Vehicles",D16="Construction",D16="Construction & Infrastructure",D16="Engines & Power Systems",D16="Food Processing",D16="Healthcare",D16="Healthcare & Medical Devices",D16="Heavy Equipment",D16="Heavy Industry",D16="Industrial Gases",D16="Industrial Manufacturing",D16="Logistics",D16="Medical Devices",D16="Mining",D16="Mining & Commodities Trading",D16="Oil & Gas",D16="Oilfield Services",D16="Rail Transport",D16="Shipping & Logistics",D16="Steel"),3, OR(D16="Apparel & Footwear",D16="Beverage",D16="Coffeehouse & Retail",D16="Conglomerate",D16="Consumer Goods",D16="Convenience Retail",D16="Electronics",D16="Electronics & Semiconductors",D16="Electronics Retail",D16="Fashion Retail",D16="Food & Beverage",D16="Food Retail & Consumer Goods",D16="Industrial & Technology",D16="Industrial Automation",D16="Industrial Technology",D16="Postal & Financial Services",D16="Postal Services",D16="Scientific Instruments",D16="Technology Hardware",D16="Trading Company",D16="IT Consulting"),1, OR(D16="Cosmetics",D16="E-commerce & Cloud Computing",D16="Electronics & Entertainment",D16="Entertainment & Media",D16="Luxury Goods",D16="Media & Telecommunications",D16="Networking Technology",D16="Real Estate Services",D16="Technology & Consumer Electronics",D16="Telecommunications",D16="Telecommunications & Investment"),1, OR(D16="Asset Management",D16="Banking",D16="Banking & Asset Services",D16="Banking & Financial Services",D16="Banking & Wealth Management",D16="Cloud Software",D16="Enterprise Software",D16="Financial Services",D16="Information Technology Consulting",D16="Investment Banking",D16="Social Media & Technology",D16="Software & Cloud Computing",D16="Technology & Consulting",D16="Technology & Internet Services",D16="Technology & Software"),1, TRUE,"Unmapped" )} -> 1 | H16: 2 | I16: =VLOOKUP(B16,'BIS + EDBA Final'!A:F,6,FALSE) -> 1 | J16: =VLOOKUP(B16,'CBG Final'!A:B,2,FALSE) -> 3 | K16: =0.3*F16+0.2*G16+0.2*H16+I16*0.1+J16*0.2 -> 2.2 | L16: 91,361 | M16: 2.8% | N16: 4,972 | O16: 111.2% | P16: 196,219 | Q16: 9 | R16: 31
B17: Citigroup | C17: United States | D17: Banking | E17: 227855 | F17: {=_xlfn.IFS( E17<=$E$245,0, E17<=$E$246,1, E17<=$E$247,2, E17>=$E$247,3)} -> 3 | G17: {=_xlfn.IFS( OR(D17="Aerospace",D17="Aerospace & Defense",D17="Agricultural Equipment",D17="Airlines",D17="Automotive",D17="Automotive & Energy",D17="Automotive Components",D17="Aviation",D17="Building Materials",D17="Chemicals",D17="Commercial Vehicles",D17="Conglomerate & Defense",D17="Conglomerate & Energy",D17="Construction",D17="Construction & Infrastructure",D17="Construction & Real Estate",D17="Construction & Telecom",D17="Discount Retail",D17="Energy Management",D17="Energy Technology",D17="Engines & Power Systems",D17="Environmental Services",D17="Food Distribution",D17="Food Services",D17="Grocery Retail",D17="Healthcare & Pharmacy",D17="Home Improvement Retail",D17="Industrial Engineering & Electronics",D17="Oilfield Services",D17="Pharmaceuticals",D17="Pharmaceuticals & Chemicals",D17="Pharmaceuticals & Healthcare",D17="Pharmacy Retail",D17="Postal & Logistics",D17="Retail",D17="Retail & Distribution",D17="Retail & Grocery",D17="Retail (IKEA)",D17="Tobacco",D17="Trading & Conglomerate",D17="Utilities",D17="Utilities & Energy",D17="Wholesale Retail"),2, OR(D17="Agribusiness",D17="Automotive & Heavy Vehicles",D17="Chemicals",D17="Commercial Vehicles",D17="Construction",D17="Construction & Infrastructure",D17="Engines & Power Systems",D17="Food Processing",D17="Healthcare",D17="Healthcare & Medical Devices",D17="Heavy Equipment",D17="Heavy Industry",D17="Industrial Gases",D17="Industrial Manufacturing",D17="Logistics",D17="Medical Devices",D17="Mining",D17="Mining & Commodities Trading",D17="Oil & Gas",D17="Oilfield Services",D17="Rail Transport",D17="Shipping & Logistics",D17="Steel"),3, OR(D17="Apparel & Footwear",D17="Beverage",D17="Coffeehouse & Retail",D17="Conglomerate",D17="Consumer Goods",D17="Convenience Retail",D17="Electronics",D17="Electronics & Semiconductors",D17="Electronics Retail",D17="Fashion Retail",D17="Food & Beverage",D17="Food Retail & Consumer Goods",D17="Industrial & Technology",D17="Industrial Automation",D17="Industrial Technology",D17="Postal & Financial Services",D17="Postal Services",D17="Scientific Instruments",D17="Technology Hardware",D17="Trading Company",D17="IT Consulting"),1, OR(D17="Cosmetics",D17="E-commerce & Cloud Computing",D17="Electronics & Entertainment",D17="Entertainment & Media",D17="Luxury Goods",D17="Media & Telecommunications",D17="Networking Technology",D17="Real Estate Services",D17="Technology & Consumer Electronics",D17="Telecommunications",D17="Telecommunications & Investment"),1, OR(D17="Asset Management",D17="Banking",D17="Banking & Asset Services",D17="Banking & Financial Services",D17="Banking & Wealth Management",D17="Cloud Software",D17="Enterprise Software",D17="Financial Services",D17="Information Technology Consulting",D17="Investment Banking",D17="Social Media & Technology",D17="Software & Cloud Computing",D17="Technology & Consulting",D17="Technology & Internet Services",D17="Technology & Software"),1, TRUE,"Unmapped" )} -> 1 | H17: 2 | I17: =VLOOKUP(B17,'BIS + EDBA Final'!A:F,6,FALSE) -> 1 | J17: =VLOOKUP(B17,'CBG Final'!A:B,2,FALSE) -> 3 | K17: =0.3*F17+0.2*G17+0.2*H17+I17*0.1+J17*0.2 -> 2.2 | L17: 170,757 | M17: 8.9% | N17: 12,682 | O17: 37.4% | P17: 2,352,945 | Q17: 6 | R17: 31
B18: Microsoft | C18: United States | D18: Technology & Software | E18: 228000 | F18: {=_xlfn.IFS( E18<=$E$245,0, E18<=$E$246,1, E18<=$E$247,2, E18>=$E$247,3)} -> 3 | G18: {=_xlfn.IFS( OR(D18="Aerospace",D18="Aerospace & Defense",D18="Agricultural Equipment",D18="Airlines",D18="Automotive",D18="Automotive & Energy",D18="Automotive Components",D18="Aviation",D18="Building Materials",D18="Chemicals",D18="Commercial Vehicles",D18="Conglomerate & Defense",D18="Conglomerate & Energy",D18="Construction",D18="Construction & Infrastructure",D18="Construction & Real Estate",D18="Construction & Telecom",D18="Discount Retail",D18="Energy Management",D18="Energy Technology",D18="Engines & Power Systems",D18="Environmental Services",D18="Food Distribution",D18="Food Services",D18="Grocery Retail",D18="Healthcare & Pharmacy",D18="Home Improvement Retail",D18="Industrial Engineering & Electronics",D18="Oilfield Services",D18="Pharmaceuticals",D18="Pharmaceuticals & Chemicals",D18="Pharmaceuticals & Healthcare",D18="Pharmacy Retail",D18="Postal & Logistics",D18="Retail",D18="Retail & Distribution",D18="Retail & Grocery",D18="Retail (IKEA)",D18="Tobacco",D18="Trading & Conglomerate",D18="Utilities",D18="Utilities & Energy",D18="Wholesale Retail"),2, OR(D18="Agribusiness",D18="Automotive & Heavy Vehicles",D18="Chemicals",D18="Commercial Vehicles",D18="Construction",D18="Construction & Infrastructure",D18="Engines & Power Systems",D18="Food Processing",D18="Healthcare",D18="Healthcare & Medical Devices",D18="Heavy Equipment",D18="Heavy Industry",D18="Industrial Gases",D18="Industrial Manufacturing",D18="Logistics",D18="Medical Devices",D18="Mining",D18="Mining & Commodities Trading",D18="Oil & Gas",D18="Oilfield Services",D18="Rail Transport",D18="Shipping & Logistics",D18="Steel"),3, OR(D18="Apparel & Footwear",D18="Beverage",D18="Coffeehouse & Retail",D18="Conglomerate",D18="Consumer Goods",D18="Convenience Retail",D18="Electronics",D18="Electronics & Semiconductors",D18="Electronics Retail",D18="Fashion Retail",D18="Food & Beverage",D18="Food Retail & Consumer Goods",D18="Industrial & Technology",D18="Industrial Automation",D18="Industrial Technology",D18="Postal & Financial Services",D18="Postal Services",D18="Scientific Instruments",D18="Technology Hardware",D18="Trading Company",D18="IT Consulting"),1, OR(D18="Cosmetics",D18="E-commerce & Cloud Computing",D18="Electronics & Entertainment",D18="Entertainment & Media",D18="Luxury Goods",D18="Media & Telecommunications",D18="Networking Technology",D18="Real Estate Services",D18="Technology & Consumer Electronics",D18="Telecommunications",D18="Telecommunications & Investment"),1, OR(D18="Asset Management",D18="Banking",D18="Banking & Asset Services",D18="Banking & Financial Services",D18="Banking & Wealth Management",D18="Cloud Software",D18="Enterprise Software",D18="Financial Services",D18="Information Technology Consulting",D18="Investment Banking",D18="Social Media & Technology",D18="Software & Cloud Computing",D18="Technology & Consulting",D18="Technology & Internet Services",D18="Technology & Software"),1, TRUE,"Unmapped" )} -> 1 | H18: 3 | I18: =VLOOKUP(B18,'BIS + EDBA Final'!A:F,6,FALSE) -> -1 | J18: =VLOOKUP(B18,'CBG Final'!A:B,2,FALSE) -> 3 | K18: =0.3*F18+0.2*G18+0.2*H18+I18*0.1+J18*0.2 -> 2.2 | L18: 245,122 | M18: 15.7% | N18: 88,136 | O18: 21.8% | P18: 512,163 | Q18: 4 | R18: 28
B19: Bank of America | C19: United States | D19: Banking | E19: 213193 | F19: {=_xlfn.IFS( E19<=$E$245,0, E19<=$E$246,1, E19<=$E$247,2, E19>=$E$247,3)} -> 3 | G19: {=_xlfn.IFS( OR(D19="Aerospace",D19="Aerospace & Defense",D19="Agricultural Equipment",D19="Airlines",D19="Automotive",D19="Automotive & Energy",D19="Automotive Components",D19="Aviation",D19="Building Materials",D19="Chemicals",D19="Commercial Vehicles",D19="Conglomerate & Defense",D19="Conglomerate & Energy",D19="Construction",D19="Construction & Infrastructure",D19="Construction & Real Estate",D19="Construction & Telecom",D19="Discount Retail",D19="Energy Management",D19="Energy Technology",D19="Engines & Power Systems",D19="Environmental Services",D19="Food Distribution",D19="Food Services",D19="Grocery Retail",D19="Healthcare & Pharmacy",D19="Home Improvement Retail",D19="Industrial Engineering & Electronics",D19="Oilfield Services",D19="Pharmaceuticals",D19="Pharmaceuticals & Chemicals",D19="Pharmaceuticals & Healthcare",D19="Pharmacy Retail",D19="Postal & Logistics",D19="Retail",D19="Retail & Distribution",D19="Retail & Grocery",D19="Retail (IKEA)",D19="Tobacco",D19="Trading & Conglomerate",D19="Utilities",D19="Utilities & Energy",D19="Wholesale Retail"),2, OR(D19="Agribusiness",D19="Automotive & Heavy Vehicles",D19="Chemicals",D19="Commercial Vehicles",D19="Construction",D19="Construction & Infrastructure",D19="Engines & Power Systems",D19="Food Processing",D19="Healthcare",D19="Healthcare & Medical Devices",D19="Heavy Equipment",D19="Heavy Industry",D19="Industrial Gases",D19="Industrial Manufacturing",D19="Logistics",D19="Medical Devices",D19="Mining",D19="Mining & Commodities Trading",D19="Oil & Gas",D19="Oilfield Services",D19="Rail Transport",D19="Shipping & Logistics",D19="Steel"),3, OR(D19="Apparel & Footwear",D19="Beverage",D19="Coffeehouse & Retail",D19="Conglomerate",D19="Consumer Goods",D19="Convenience Retail",D19="Electronics",D19="Electronics & Semiconductors",D19="Electronics Retail",D19="Fashion Retail",D19="Food & Beverage",D19="Food Retail & Consumer Goods",D19="Industrial & Technology",D19="Industrial Automation",D19="Industrial Technology",D19="Postal & Financial Services",D19="Postal Services",D19="Scientific Instruments",D19="Technology Hardware",D19="Trading Company",D19="IT Consulting"),1, OR(D19="Cosmetics",D19="E-commerce & Cloud Computing",D19="Electronics & Entertainment",D19="Entertainment & Media",D19="Luxury Goods",D19="Media & Telecommunications",D19="Networking Technology",D19="Real Estate Services",D19="Technology & Consumer Electronics",D19="Telecommunications",D19="Telecommunications & Investment"),1, OR(D19="Asset Management",D19="Banking",D19="Banking & Asset Services",D19="Banking & Financial Services",D19="Banking & Wealth Management",D19="Cloud Software",D19="Enterprise Software",D19="Financial Services",D19="Information Technology Consulting",D19="Investment Banking",D19="Social Media & Technology",D19="Software & Cloud Computing",D19="Technology & Consulting",D19="Technology & Internet Services",D19="Technology & Software"),1, TRUE,"Unmapped" )} -> 1 | H19: 2 | I19: =VLOOKUP(B19,'BIS + EDBA Final'!A:F,6,FALSE) -> 1 | J19: =VLOOKUP(B19,'CBG Final'!A:B,2,FALSE) -> 3 | K19: =0.3*F19+0.2*G19+0.2*H19+I19*0.1+J19*0.2 -> 2.2 | L19: 192,434 | M19: 11.9% | N19: 27,132 | O19: 2.3% | P19: 3,261,519 | Q19: 4 | R19: 31
B20: Lowe's | C20: United States | D20: Home Improvement Retail | E20: 215500 | F20: {=_xlfn.IFS( E20<=$E$245,0, E20<=$E$246,1, E20<=$E$247,2, E20>=$E$247,3)} -> 3 | G20: {=_xlfn.IFS( OR(D20="Aerospace",D20="Aerospace & Defense",D20="Agricultural Equipment",D20="Airlines",D20="Automotive",D20="Automotive & Energy",D20="Automotive Components",D20="Aviation",D20="Building Materials",D20="Chemicals",D20="Commercial Vehicles",D20="Conglomerate & Defense",D20="Conglomerate & Energy",D20="Construction",D20="Construction & Infrastructure",D20="Construction & Real Estate",D20="Construction & Telecom",D20="Discount Retail",D20="Energy Management",D20="Energy Technology",D20="Engines & Power Systems",D20="Environmental Services",D20="Food Distribution",D20="Food Services",D20="Grocery Retail",D20="Healthcare & Pharmacy",D20="Home Improvement Retail",D20="Industrial Engineering & Electronics",D20="Oilfield Services",D20="Pharmaceuticals",D20="Pharmaceuticals & Chemicals",D20="Pharmaceuticals & Healthcare",D20="Pharmacy Retail",D20="Postal & Logistics",D20="Retail",D20="Retail & Distribution",D20="Retail & Grocery",D20="Retail (IKEA)",D20="Tobacco",D20="Trading & Conglomerate",D20="Utilities",D20="Utilities & Energy",D20="Wholesale Retail"),2, OR(D20="Agribusiness",D20="Automotive & Heavy Vehicles",D20="Chemicals",D20="Commercial Vehicles",D20="Construction",D20="Construction & Infrastructure",D20="Engines & Power Systems",D20="Food Processing",D20="Healthcare",D20="Healthcare & Medical Devices",D20="Heavy Equipment",D20="Heavy Industry",D20="Industrial Gases",D20="Industrial Manufacturing",D20="Logistics",D20="Medical Devices",D20="Mining",D20="Mining & Commodities Trading",D20="Oil & Gas",D20="Oilfield Services",D20="Rail Transport",D20="Shipping & Logistics",D20="Steel"),3, OR(D20="Apparel & Footwear",D20="Beverage",D20="Coffeehouse & Retail",D20="Conglomerate",D20="Consumer Goods",D20="Convenience Retail",D20="Electronics",D20="Electronics & Semiconductors",D20="Electronics Retail",D20="Fashion Retail",D20="Food & Beverage",D20="Food Retail & Consumer Goods",D20="Industrial & Technology",D20="Industrial Automation",D20="Industrial Technology",D20="Postal & Financial Services",D20="Postal Services",D20="Scientific Instruments",D20="Technology Hardware",D20="Trading Company",D20="IT Consulting"),1, OR(D20="Cosmetics",D20="E-commerce & Cloud Computing",D20="Electronics & Entertainment",D20="Entertainment & Media",D20="Luxury Goods",D20="Media & Telecommunications",D20="Networking Technology",D20="Real Estate Services",D20="Technology & Consumer Electronics",D20="Telecommunications",D20="Telecommunications & Investment"),1, OR(D20="Asset Management",D20="Banking",D20="Banking & Asset Services",D20="Banking & Financial Services",D20="Banking & Wealth Management",D20="Cloud Software",D20="Enterprise Software",D20="Financial Services",D20="Information Technology Consulting",D20="Investment Banking",D20="Social Media & Technology",D20="Software & Cloud Computing",D20="Technology & Consulting",D20="Technology & Internet Services",D20="Technology & Software"),1, TRUE,"Unmapped" )} -> 2 | H20: 1 | I20: =VLOOKUP(B20,'BIS + EDBA Final'!A:F,6,FALSE) -> 1 | J20: =VLOOKUP(B20,'CBG Final'!A:B,2,FALSE) -> 3 | K20: =0.3*F20+0.2*G20+0.2*H20+I20*0.1+J20*0.2 -> 2.2 | L20: 83,674 | M20: -3.1% | N20: 6,957 | O20: -10% | P20: 43,102 | Q20: -9 | R20: 28
B21: Publix Super Markets | C21: United States | D21: Grocery Retail | E21: 255000 | F21: {=_xlfn.IFS( E21<=$E$245,0, E21<=$E$246,1, E21<=$E$247,2, E21>=$E$247,3)} -> 3 | G21: {=_xlfn.IFS( OR(D21="Aerospace",D21="Aerospace & Defense",D21="Agricultural Equipment",D21="Airlines",D21="Automotive",D21="Automotive & Energy",D21="Automotive Components",D21="Aviation",D21="Building Materials",D21="Chemicals",D21="Commercial Vehicles",D21="Conglomerate & Defense",D21="Conglomerate & Energy",D21="Construction",D21="Construction & Infrastructure",D21="Construction & Real Estate",D21="Construction & Telecom",D21="Discount Retail",D21="Energy Management",D21="Energy Technology",D21="Engines & Power Systems",D21="Environmental Services",D21="Food Distribution",D21="Food Services",D21="Grocery Retail",D21="Healthcare & Pharmacy",D21="Home Improvement Retail",D21="Industrial Engineering & Electronics",D21="Oilfield Services",D21="Pharmaceuticals",D21="Pharmaceuticals & Chemicals",D21="Pharmaceuticals & Healthcare",D21="Pharmacy Retail",D21="Postal & Logistics",D21="Retail",D21="Retail & Distribution",D21="Retail & Grocery",D21="Retail (IKEA)",D21="Tobacco",D21="Trading & Conglomerate",D21="Utilities",D21="Utilities & Energy",D21="Wholesale Retail"),2, OR(D21="Agribusiness",D21="Automotive & Heavy Vehicles",D21="Chemicals",D21="Commercial Vehicles",D21="Construction",D21="Construction & Infrastructure",D21="Engines & Power Systems",D21="Food Processing",D21="Healthcare",D21="Healthcare & Medical Devices",D21="Heavy Equipment",D21="Heavy Industry",D21="Industrial Gases",D21="Industrial Manufacturing",D21="Logistics",D21="Medical Devices",D21="Mining",D21="Mining & Commodities Trading",D21="Oil & Gas",D21="Oilfield Services",D21="Rail Transport",D21="Shipping & Logistics",D21="Steel"),3, OR(D21="Apparel & Footwear",D21="Beverage",D21="Coffeehouse & Retail",D21="Conglomerate",D21="Consumer Goods",D21="Convenience Retail",D21="Electronics",D21="Electronics & Semiconductors",D21="Electronics Retail",D21="Fashion Retail",D21="Food & Beverage",D21="Food Retail & Consumer Goods",D21="Industrial & Technology",D21="Industrial Automation",D21="Industrial Technology",D21="Postal & Financial Services",D21="Postal Services",D21="Scientific Instruments",D21="Technology Hardware",D21="Trading Company",D21="IT Consulting"),1, OR(D21="Cosmetics",D21="E-commerce & Cloud Computing",D21="Electronics & Entertainment",D21="Entertainment & Media",D21="Luxury Goods",D21="Media & Telecommunications",D21="Networking Technology",D21="Real Estate Services",D21="Technology & Consumer Electronics",D21="Telecommunications",D21="Telecommunications & Investment"),1, OR(D21="Asset Management",D21="Banking",D21="Banking & Asset Services",D21="Banking & Financial Services",D21="Banking & Wealth Management",D21="Cloud Software",D21="Enterprise Software",D21="Financial Services",D21="Information Technology Consulting",D21="Investment Banking",D21="Social Media & Technology",D21="Software & Cloud Computing",D21="Technology & Consulting",D21="Technology & Internet Services",D21="Technology & Software"),1, TRUE,"Unmapped" )} -> 2 | H21: 1 | I21: =VLOOKUP(B21,'BIS + EDBA Final'!A:F,6,FALSE) -> 1 | J21: =VLOOKUP(B21,'CBG Final'!A:B,2,FALSE) -> 3 | K21: =0.3*F21+0.2*G21+0.2*H21+I21*0.1+J21*0.2 -> 2.2 | L21: 60,177 | M21: 4.6% | N21: 4,635 | O21: 6.6% | P21: 37,601 | Q21: 11 | R21: 31
B22: Woolworths Group | C22: Australia | D22: Retail | E22: 201413 | F22: {=_xlfn.IFS( E22<=$E$245,0, E22<=$E$246,1, E22<=$E$247,2, E22>=$E$247,3)} -> 3 | G22: {=_xlfn.IFS( OR(D22="Aerospace",D22="Aerospace & Defense",D22="Agricultural Equipment",D22="Airlines",D22="Automotive",D22="Automotive & Energy",D22="Automotive Components",D22="Aviation",D22="Building Materials",D22="Chemicals",D22="Commercial Vehicles",D22="Conglomerate & Defense",D22="Conglomerate & Energy",D22="Construction",D22="Construction & Infrastructure",D22="Construction & Real Estate",D22="Construction & Telecom",D22="Discount Retail",D22="Energy Management",D22="Energy Technology",D22="Engines & Power Systems",D22="Environmental Services",D22="Food Distribution",D22="Food Services",D22="Grocery Retail",D22="Healthcare & Pharmacy",D22="Home Improvement Retail",D22="Industrial Engineering & Electronics",D22="Oilfield Services",D22="Pharmaceuticals",D22="Pharmaceuticals & Chemicals",D22="Pharmaceuticals & Healthcare",D22="Pharmacy Retail",D22="Postal & Logistics",D22="Retail",D22="Retail & Distribution",D22="Retail & Grocery",D22="Retail (IKEA)",D22="Tobacco",D22="Trading & Conglomerate",D22="Utilities",D22="Utilities & Energy",D22="Wholesale Retail"),2, OR(D22="Agribusiness",D22="Automotive & Heavy Vehicles",D22="Chemicals",D22="Commercial Vehicles",D22="Construction",D22="Construction & Infrastructure",D22="Engines & Power Systems",D22="Food Processing",D22="Healthcare",D22="Healthcare & Medical Devices",D22="Heavy Equipment",D22="Heavy Industry",D22="Industrial Gases",D22="Industrial Manufacturing",D22="Logistics",D22="Medical Devices",D22="Mining",D22="Mining & Commodities Trading",D22="Oil & Gas",D22="Oilfield Services",D22="Rail Transport",D22="Shipping & Logistics",D22="Steel"),3, OR(D22="Apparel & Footwear",D22="Beverage",D22="Coffeehouse & Retail",D22="Conglomerate",D22="Consumer Goods",D22="Convenience Retail",D22="Electronics",D22="Electronics & Semiconductors",D22="Electronics Retail",D22="Fashion Retail",D22="Food & Beverage",D22="Food Retail & Consumer Goods",D22="Industrial & Technology",D22="Industrial Automation",D22="Industrial Technology",D22="Postal & Financial Services",D22="Postal Services",D22="Scientific Instruments",D22="Technology Hardware",D22="Trading Company",D22="IT Consulting"),1, OR(D22="Cosmetics",D22="E-commerce & Cloud Computing",D22="Electronics & Entertainment",D22="Entertainment & Media",D22="Luxury Goods",D22="Media & Telecommunications",D22="Networking Technology",D22="Real Estate Services",D22="Technology & Consumer Electronics",D22="Telecommunications",D22="Telecommunications & Investment"),1, OR(D22="Asset Management",D22="Banking",D22="Banking & Asset Services",D22="Banking & Financial Services",D22="Banking & Wealth Management",D22="Cloud Software",D22="Enterprise Software",D22="Financial Services",D22="Information Technology Consulting",D22="Investment Banking",D22="Social Media & Technology",D22="Software & Cloud Computing",D22="Technology & Consulting",D22="Technology & Internet Services",D22="Technology & Software"),1, TRUE,"Unmapped" )} -> 2 | H22: =VLOOKUP(B22,'BIS + EDBA Final'!A:K,2,FALSE) -> 2 | I22: =VLOOKUP(B22,'BIS + EDBA Final'!A:F,6,FALSE) -> 1 | J22: =VLOOKUP(B22,'CBG Final'!A:B,2,FALSE) -> 2 | K22: =0.3*F22+0.2*G22+0.2*H22+I22*0.1+J22*0.2 -> 2.2 | L22: 44,521.5 | M22: 2.9% | N22: 70.8 | O22: -93.5% | P22: 22,645.1 | Q22: 8 | R22: 29
B23: HCA Healthcare | C23: United States | D23: Healthcare | E23: 271000 | F23: {=_xlfn.IFS( E23<=$E$245,0, E23<=$E$246,1, E23<=$E$247,2, E23>=$E$247,3)} -> 3 | G23: {=_xlfn.IFS( OR(D23="Aerospace",D23="Aerospace & Defense",D23="Agricultural Equipment",D23="Airlines",D23="Automotive",D23="Automotive & Energy",D23="Automotive Components",D23="Aviation",D23="Building Materials",D23="Chemicals",D23="Commercial Vehicles",D23="Conglomerate & Defense",D23="Conglomerate & Energy",D23="Construction",D23="Construction & Infrastructure",D23="Construction & Real Estate",D23="Construction & Telecom",D23="Discount Retail",D23="Energy Management",D23="Energy Technology",D23="Engines & Power Systems",D23="Environmental Services",D23="Food Distribution",D23="Food Services",D23="Grocery Retail",D23="Healthcare & Pharmacy",D23="Home Improvement Retail",D23="Industrial Engineering & Electronics",D23="Oilfield Services",D23="Pharmaceuticals",D23="Pharmaceuticals & Chemicals",D23="Pharmaceuticals & Healthcare",D23="Pharmacy Retail",D23="Postal & Logistics",D23="Retail",D23="Retail & Distribution",D23="Retail & Grocery",D23="Retail (IKEA)",D23="Tobacco",D23="Trading & Conglomerate",D23="Utilities",D23="Utilities & Energy",D23="Wholesale Retail"),2, OR(D23="Agribusiness",D23="Automotive & Heavy Vehicles",D23="Chemicals",D23="Commercial Vehicles",D23="Construction",D23="Construction & Infrastructure",D23="Engines & Power Systems",D23="Food Processing",D23="Healthcare",D23="Healthcare & Medical Devices",D23="Heavy Equipment",D23="Heavy Industry",D23="Industrial Gases",D23="Industrial Manufacturing",D23="Logistics",D23="Medical Devices",D23="Mining",D23="Mining & Commodities Trading",D23="Oil & Gas",D23="Oilfield Services",D23="Rail Transport",D23="Shipping & Logistics",D23="Steel"),3, OR(D23="Apparel & Footwear",D23="Beverage",D23="Coffeehouse & Retail",D23="Conglomerate",D23="Consumer Goods",D23="Convenience Retail",D23="Electronics",D23="Electronics & Semiconductors",D23="Electronics Retail",D23="Fashion Retail",D23="Food & Beverage",D23="Food Retail & Consumer Goods",D23="Industrial & Technology",D23="Industrial Automation",D23="Industrial Technology",D23="Postal & Financial Services",D23="Postal Services",D23="Scientific Instruments",D23="Technology Hardware",D23="Trading Company",D23="IT Consulting"),1, OR(D23="Cosmetics",D23="E-commerce & Cloud Computing",D23="Electronics & Entertainment",D23="Entertainment & Media",D23="Luxury Goods",D23="Media & Telecommunications",D23="Networking Technology",D23="Real Estate Services",D23="Technology & Consumer Electronics",D23="Telecommunications",D23="Telecommunications & Investment"),1, OR(D23="Asset Management",D23="Banking",D23="Banking & Asset Services",D23="Banking & Financial Services",D23="Banking & Wealth Management",D23="Cloud Software",D23="Enterprise Software",D23="Financial Services",D23="Information Technology Consulting",D23="Investment Banking",D23="Social Media & Technology",D23="Software & Cloud Computing",D23="Technology & Consulting",D23="Technology & Internet Services",D23="Technology & Software"),1, TRUE,"Unmapped" )} -> 3 | H23: =VLOOKUP(B23,'BIS + EDBA Final'!A:K,2,FALSE) -> 2 | I23: =VLOOKUP(B23,'BIS + EDBA Final'!A:F,6,FALSE) -> -1 | J23: =VLOOKUP(B23,'CBG Final'!A:B,2,FALSE) -> 2 | K23: =0.3*F23+0.2*G23+0.2*H23+I23*0.1+J23*0.2 -> 2.2 | L23: 70,603 | M23: 8.7% | N23: 5,760 | O23: 9.9% | P23: 59,513 | Q23: 18 | R23: 31
B24: Stellantis | C24: Netherlands | D24: Automotive | E24: 248243 | F24: {=_xlfn.IFS( E24<=$E$245,0, E24<=$E$246,1, E24<=$E$247,2, E24>=$E$247,3)} -> 3 | G24: {=_xlfn.IFS( OR(D24="Aerospace",D24="Aerospace & Defense",D24="Agricultural Equipment",D24="Airlines",D24="Automotive",D24="Automotive & Energy",D24="Automotive Components",D24="Aviation",D24="Building Materials",D24="Chemicals",D24="Commercial Vehicles",D24="Conglomerate & Defense",D24="Conglomerate & Energy",D24="Construction",D24="Construction & Infrastructure",D24="Construction & Real Estate",D24="Construction & Telecom",D24="Discount Retail",D24="Energy Management",D24="Energy Technology",D24="Engines & Power Systems",D24="Environmental Services",D24="Food Distribution",D24="Food Services",D24="Grocery Retail",D24="Healthcare & Pharmacy",D24="Home Improvement Retail",D24="Industrial Engineering & Electronics",D24="Oilfield Services",D24="Pharmaceuticals",D24="Pharmaceuticals & Chemicals",D24="Pharmaceuticals & Healthcare",D24="Pharmacy Retail",D24="Postal & Logistics",D24="Retail",D24="Retail & Distribution",D24="Retail & Grocery",D24="Retail (IKEA)",D24="Tobacco",D24="Trading & Conglomerate",D24="Utilities",D24="Utilities & Energy",D24="Wholesale Retail"),2, OR(D24="Agribusiness",D24="Automotive & Heavy Vehicles",D24="Chemicals",D24="Commercial Vehicles",D24="Construction",D24="Construction & Infrastructure",D24="Engines & Power Systems",D24="Food Processing",D24="Healthcare",D24="Healthcare & Medical Devices",D24="Heavy Equipment",D24="Heavy Industry",D24="Industrial Gases",D24="Industrial Manufacturing",D24="Logistics",D24="Medical Devices",D24="Mining",D24="Mining & Commodities Trading",D24="Oil & Gas",D24="Oilfield Services",D24="Rail Transport",D24="Shipping & Logistics",D24="Steel"),3, OR(D24="Apparel & Footwear",D24="Beverage",D24="Coffeehouse & Retail",D24="Conglomerate",D24="Consumer Goods",D24="Convenience Retail",D24="Electronics",D24="Electronics & Semiconductors",D24="Electronics Retail",D24="Fashion Retail",D24="Food & Beverage",D24="Food Retail & Consumer Goods",D24="Industrial & Technology",D24="Industrial Automation",D24="Industrial Technology",D24="Postal & Financial Services",D24="Postal Services",D24="Scientific Instruments",D24="Technology Hardware",D24="Trading Company",D24="IT Consulting"),1, OR(D24="Cosmetics",D24="E-commerce & Cloud Computing",D24="Electronics & Entertainment",D24="Entertainment & Media",D24="Luxury Goods",D24="Media & Telecommunications",D24="Networking Technology",D24="Real Estate Services",D24="Technology & Consumer Electronics",D24="Telecommunications",D24="Telecommunications & Investment"),1, OR(D24="Asset Management",D24="Banking",D24="Banking & Asset Services",D24="Banking & Financial Services",D24="Banking & Wealth Management",D24="Cloud Software",D24="Enterprise Software",D24="Financial Services",D24="Information Technology Consulting",D24="Investment Banking",D24="Social Media & Technology",D24="Software & Cloud Computing",D24="Technology & Consulting",D24="Technology & Internet Services",D24="Technology & Software"),1, TRUE,"Unmapped" )} -> 2 | H24: 2 | I24: =VLOOKUP(B24,'BIS + EDBA Final'!A:F,6,FALSE) -> 1 | J24: =VLOOKUP(B24,'CBG Final'!A:B,2,FALSE) -> 2 | K24: =0.3*F24+0.2*G24+0.2*H24+I24*0.1+J24*0.2 -> 2.2 | L24: 169,652.9 | M24: -17.2% | N24: 5,918.7 | O24: -70.6% | P24: 214,958.6 | Q24: -12 | R24: 20
B25: Toyota Motor | C25: Japan | D25: Automotive | E25: 383853 | F25: {=_xlfn.IFS( E25<=$E$245,0, E25<=$E$246,1, E25<=$E$247,2, E25>=$E$247,3)} -> 3 | G25: {=_xlfn.IFS( OR(D25="Aerospace",D25="Aerospace & Defense",D25="Agricultural Equipment",D25="Airlines",D25="Automotive",D25="Automotive & Energy",D25="Automotive Components",D25="Aviation",D25="Building Materials",D25="Chemicals",D25="Commercial Vehicles",D25="Conglomerate & Defense",D25="Conglomerate & Energy",D25="Construction",D25="Construction & Infrastructure",D25="Construction & Real Estate",D25="Construction & Telecom",D25="Discount Retail",D25="Energy Management",D25="Energy Technology",D25="Engines & Power Systems",D25="Environmental Services",D25="Food Distribution",D25="Food Services",D25="Grocery Retail",D25="Healthcare & Pharmacy",D25="Home Improvement Retail",D25="Industrial Engineering & Electronics",D25="Oilfield Services",D25="Pharmaceuticals",D25="Pharmaceuticals & Chemicals",D25="Pharmaceuticals & Healthcare",D25="Pharmacy Retail",D25="Postal & Logistics",D25="Retail",D25="Retail & Distribution",D25="Retail & Grocery",D25="Retail (IKEA)",D25="Tobacco",D25="Trading & Conglomerate",D25="Utilities",D25="Utilities & Energy",D25="Wholesale Retail"),2, OR(D25="Agribusiness",D25="Automotive & Heavy Vehicles",D25="Chemicals",D25="Commercial Vehicles",D25="Construction",D25="Construction & Infrastructure",D25="Engines & Power Systems",D25="Food Processing",D25="Healthcare",D25="Healthcare & Medical Devices",D25="Heavy Equipment",D25="Heavy Industry",D25="Industrial Gases",D25="Industrial Manufacturing",D25="Logistics",D25="Medical Devices",D25="Mining",D25="Mining & Commodities Trading",D25="Oil & Gas",D25="Oilfield Services",D25="Rail Transport",D25="Shipping & Logistics",D25="Steel"),3, OR(D25="Apparel & Footwear",D25="Beverage",D25="Coffeehouse & Retail",D25="Conglomerate",D25="Consumer Goods",D25="Convenience Retail",D25="Electronics",D25="Electronics & Semiconductors",D25="Electronics Retail",D25="Fashion Retail",D25="Food & Beverage",D25="Food Retail & Consumer Goods",D25="Industrial & Technology",D25="Industrial Automation",D25="Industrial Technology",D25="Postal & Financial Services",D25="Postal Services",D25="Scientific Instruments",D25="Technology Hardware",D25="Trading Company",D25="IT Consulting"),1, OR(D25="Cosmetics",D25="E-commerce & Cloud Computing",D25="Electronics & Entertainment",D25="Entertainment & Media",D25="Luxury Goods",D25="Media & Telecommunications",D25="Networking Technology",D25="Real Estate Services",D25="Technology & Consumer Electronics",D25="Telecommunications",D25="Telecommunications & Investment"),1, OR(D25="Asset Management",D25="Banking",D25="Banking & Asset Services",D25="Banking & Financial Services",D25="Banking & Wealth Management",D25="Cloud Software",D25="Enterprise Software",D25="Financial Services",D25="Information Technology Consulting",D25="Investment Banking",D25="Social Media & Technology",D25="Software & Cloud Computing",D25="Technology & Consulting",D25="Technology & Internet Services",D25="Technology & Software"),1, TRUE,"Unmapped" )} -> 2 | H25: 2 | I25: =VLOOKUP(B25,'BIS + EDBA Final'!A:F,6,FALSE) -> 1 | J25: =VLOOKUP(B25,'CBG Final'!A:B,2,FALSE) -> 2 | K25: =0.3*F25+0.2*G25+0.2*H25+I25*0.1+J25*0.2 -> 2.2 | L25: 315,110.2 | M25: 1% | N25: 31,257.9 | O25: -8.6% | P25: 624,466.9 | Q25: - | R25: 31
B26: Target | C26: United States | D26: Retail | E26: 440000 | F26: {=_xlfn.IFS( E26<=$E$245,0, E26<=$E$246,1, E26<=$E$247,2, E26>=$E$247,3)} -> 3 | G26: {=_xlfn.IFS( OR(D26="Aerospace",D26="Aerospace & Defense",D26="Agricultural Equipment",D26="Airlines",D26="Automotive",D26="Automotive & Energy",D26="Automotive Components",D26="Aviation",D26="Building Materials",D26="Chemicals",D26="Commercial Vehicles",D26="Conglomerate & Defense",D26="Conglomerate & Energy",D26="Construction",D26="Construction & Infrastructure",D26="Construction & Real Estate",D26="Construction & Telecom",D26="Discount Retail",D26="Energy Management",D26="Energy Technology",D26="Engines & Power Systems",D26="Environmental Services",D26="Food Distribution",D26="Food Services",D26="Grocery Retail",D26="Healthcare & Pharmacy",D26="Home Improvement Retail",D26="Industrial Engineering & Electronics",D26="Oilfield Services",D26="Pharmaceuticals",D26="Pharmaceuticals & Chemicals",D26="Pharmaceuticals & Healthcare",D26="Pharmacy Retail",D26="Postal & Logistics",D26="Retail",D26="Retail & Distribution",D26="Retail & Grocery",D26="Retail (IKEA)",D26="Tobacco",D26="Trading & Conglomerate",D26="Utilities",D26="Utilities & Energy",D26="Wholesale Retail"),2, OR(D26="Agribusiness",D26="Automotive & Heavy Vehicles",D26="Chemicals",D26="Commercial Vehicles",D26="Construction",D26="Construction & Infrastructure",D26="Engines & Power Systems",D26="Food Processing",D26="Healthcare",D26="Healthcare & Medical Devices",D26="Heavy Equipment",D26="Heavy Industry",D26="Industrial Gases",D26="Industrial Manufacturing",D26="Logistics",D26="Medical Devices",D26="Mining",D26="Mining & Commodities Trading",D26="Oil & Gas",D26="Oilfield Services",D26="Rail Transport",D26="Shipping & Logistics",D26="Steel"),3, OR(D26="Apparel & Footwear",D26="Beverage",D26="Coffeehouse & Retail",D26="Conglomerate",D26="Consumer Goods",D26="Convenience Retail",D26="Electronics",D26="Electronics & Semiconductors",D26="Electronics Retail",D26="Fashion Retail",D26="Food & Beverage",D26="Food Retail & Consumer Goods",D26="Industrial & Technology",D26="Industrial Automation",D26="Industrial Technology",D26="Postal & Financial Services",D26="Postal Services",D26="Scientific Instruments",D26="Technology Hardware",D26="Trading Company",D26="IT Consulting"),1, OR(D26="Cosmetics",D26="E-commerce & Cloud Computing",D26="Electronics & Entertainment",D26="Entertainment & Media",D26="Luxury Goods",D26="Media & Telecommunications",D26="Networking Technology",D26="Real Estate Services",D26="Technology & Consumer Electronics",D26="Telecommunications",D26="Telecommunications & Investment"),1, OR(D26="Asset Management",D26="Banking",D26="Banking & Asset Services",D26="Banking & Financial Services",D26="Banking & Wealth Management",D26="Cloud Software",D26="Enterprise Software",D26="Financial Services",D26="Information Technology Consulting",D26="Investment Banking",D26="Social Media & Technology",D26="Software & Cloud Computing",D26="Technology & Consulting",D26="Technology & Internet Services",D26="Technology & Software"),1, TRUE,"Unmapped" )} -> 2 | H26: 2 | I26: =VLOOKUP(B26,'BIS + EDBA Final'!A:F,6,FALSE) -> 1 | J26: =VLOOKUP(B26,'CBG Final'!A:B,2,FALSE) -> 2 | K26: =0.3*F26+0.2*G26+0.2*H26+I26*0.1+J26*0.2 -> 2.2 | L26: 106,566 | M26: -0.8% | N26: 4,091 | O26: -1.1% | P26: 57,769 | Q26: -4 | R26: 31
B27: Walmart | C27: United States | D27: Retail | E27: 2100000 | F27: {=_xlfn.IFS( E27<=$E$245,0, E27<=$E$246,1, E27<=$E$247,2, E27>=$E$247,3)} -> 3 | G27: {=_xlfn.IFS( OR(D27="Aerospace",D27="Aerospace & Defense",D27="Agricultural Equipment",D27="Airlines",D27="Automotive",D27="Automotive & Energy",D27="Automotive Components",D27="Aviation",D27="Building Materials",D27="Chemicals",D27="Commercial Vehicles",D27="Conglomerate & Defense",D27="Conglomerate & Energy",D27="Construction",D27="Construction & Infrastructure",D27="Construction & Real Estate",D27="Construction & Telecom",D27="Discount Retail",D27="Energy Management",D27="Energy Technology",D27="Engines & Power Systems",D27="Environmental Services",D27="Food Distribution",D27="Food Services",D27="Grocery Retail",D27="Healthcare & Pharmacy",D27="Home Improvement Retail",D27="Industrial Engineering & Electronics",D27="Oilfield Services",D27="Pharmaceuticals",D27="Pharmaceuticals & Chemicals",D27="Pharmaceuticals & Healthcare",D27="Pharmacy Retail",D27="Postal & Logistics",D27="Retail",D27="Retail & Distribution",D27="Retail & Grocery",D27="Retail (IKEA)",D27="Tobacco",D27="Trading & Conglomerate",D27="Utilities",D27="Utilities & Energy",D27="Wholesale Retail"),2, OR(D27="Agribusiness",D27="Automotive & Heavy Vehicles",D27="Chemicals",D27="Commercial Vehicles",D27="Construction",D27="Construction & Infrastructure",D27="Engines & Power Systems",D27="Food Processing",D27="Healthcare",D27="Healthcare & Medical Devices",D27="Heavy Equipment",D27="Heavy Industry",D27="Industrial Gases",D27="Industrial Manufacturing",D27="Logistics",D27="Medical Devices",D27="Mining",D27="Mining & Commodities Trading",D27="Oil & Gas",D27="Oilfield Services",D27="Rail Transport",D27="Shipping & Logistics",D27="Steel"),3, OR(D27="Apparel & Footwear",D27="Beverage",D27="Coffeehouse & Retail",D27="Conglomerate",D27="Consumer Goods",D27="Convenience Retail",D27="Electronics",D27="Electronics & Semiconductors",D27="Electronics Retail",D27="Fashion Retail",D27="Food & Beverage",D27="Food Retail & Consumer Goods",D27="Industrial & Technology",D27="Industrial Automation",D27="Industrial Technology",D27="Postal & Financial Services",D27="Postal Services",D27="Scientific Instruments",D27="Technology Hardware",D27="Trading Company",D27="IT Consulting"),1, OR(D27="Cosmetics",D27="E-commerce & Cloud Computing",D27="Electronics & Entertainment",D27="Entertainment & Media",D27="Luxury Goods",D27="Media & Telecommunications",D27="Networking Technology",D27="Real Estate Services",D27="Technology & Consumer Electronics",D27="Telecommunications",D27="Telecommunications & Investment"),1, OR(D27="Asset Management",D27="Banking",D27="Banking & Asset Services",D27="Banking & Financial Services",D27="Banking & Wealth Management",D27="Cloud Software",D27="Enterprise Software",D27="Financial Services",D27="Information Technology Consulting",D27="Investment Banking",D27="Social Media & Technology",D27="Software & Cloud Computing",D27="Technology & Consulting",D27="Technology & Internet Services",D27="Technology & Software"),1, TRUE,"Unmapped" )} -> 2 | H27: 2 | I27: =VLOOKUP(B27,'BIS + EDBA Final'!A:F,6,FALSE) -> -1 | J27: =VLOOKUP(B27,'CBG Final'!A:B,2,FALSE) -> 3 | K27: =0.3*F27+0.2*G27+0.2*H27+I27*0.1+J27*0.2 -> 2.2 | L27: 680,985 | M27: 5.1% | N27: 19,436 | O27: 25.3% | P27: 260,823 | Q27: - | R27: 31
B28: Kroger | C28: United States | D28: Grocery Retail | E28: 409000 | F28: {=_xlfn.IFS( E28<=$E$245,0, E28<=$E$246,1, E28<=$E$247,2, E28>=$E$247,3)} -> 3 | G28: {=_xlfn.IFS( OR(D28="Aerospace",D28="Aerospace & Defense",D28="Agricultural Equipment",D28="Airlines",D28="Automotive",D28="Automotive & Energy",D28="Automotive Components",D28="Aviation",D28="Building Materials",D28="Chemicals",D28="Commercial Vehicles",D28="Conglomerate & Defense",D28="Conglomerate & Energy",D28="Construction",D28="Construction & Infrastructure",D28="Construction & Real Estate",D28="Construction & Telecom",D28="Discount Retail",D28="Energy Management",D28="Energy Technology",D28="Engines & Power Systems",D28="Environmental Services",D28="Food Distribution",D28="Food Services",D28="Grocery Retail",D28="Healthcare & Pharmacy",D28="Home Improvement Retail",D28="Industrial Engineering & Electronics",D28="Oilfield Services",D28="Pharmaceuticals",D28="Pharmaceuticals & Chemicals",D28="Pharmaceuticals & Healthcare",D28="Pharmacy Retail",D28="Postal & Logistics",D28="Retail",D28="Retail & Distribution",D28="Retail & Grocery",D28="Retail (IKEA)",D28="Tobacco",D28="Trading & Conglomerate",D28="Utilities",D28="Utilities & Energy",D28="Wholesale Retail"),2, OR(D28="Agribusiness",D28="Automotive & Heavy Vehicles",D28="Chemicals",D28="Commercial Vehicles",D28="Construction",D28="Construction & Infrastructure",D28="Engines & Power Systems",D28="Food Processing",D28="Healthcare",D28="Healthcare & Medical Devices",D28="Heavy Equipment",D28="Heavy Industry",D28="Industrial Gases",D28="Industrial Manufacturing",D28="Logistics",D28="Medical Devices",D28="Mining",D28="Mining & Commodities Trading",D28="Oil & Gas",D28="Oilfield Services",D28="Rail Transport",D28="Shipping & Logistics",D28="Steel"),3, OR(D28="Apparel & Footwear",D28="Beverage",D28="Coffeehouse & Retail",D28="Conglomerate",D28="Consumer Goods",D28="Convenience Retail",D28="Electronics",D28="Electronics & Semiconductors",D28="Electronics Retail",D28="Fashion Retail",D28="Food & Beverage",D28="Food Retail & Consumer Goods",D28="Industrial & Technology",D28="Industrial Automation",D28="Industrial Technology",D28="Postal & Financial Services",D28="Postal Services",D28="Scientific Instruments",D28="Technology Hardware",D28="Trading Company",D28="IT Consulting"),1, OR(D28="Cosmetics",D28="E-commerce & Cloud Computing",D28="Electronics & Entertainment",D28="Entertainment & Media",D28="Luxury Goods",D28="Media & Telecommunications",D28="Networking Technology",D28="Real Estate Services",D28="Technology & Consumer Electronics",D28="Telecommunications",D28="Telecommunications & Investment"),1, OR(D28="Asset Management",D28="Banking",D28="Banking & Asset Services",D28="Banking & Financial Services",D28="Banking & Wealth Management",D28="Cloud Software",D28="Enterprise Software",D28="Financial Services",D28="Information Technology Consulting",D28="Investment Banking",D28="Social Media & Technology",D28="Software & Cloud Computing",D28="Technology & Consulting",D28="Technology & Internet Services",D28="Technology & Software"),1, TRUE,"Unmapped" )} -> 2 | H28: 2 | I28: =VLOOKUP(B28,'BIS + EDBA Final'!A:F,6,FALSE) -> -1 | J28: =VLOOKUP(B28,'CBG Final'!A:B,2,FALSE) -> 3 | K28: =0.3*F28+0.2*G28+0.2*H28+I28*0.1+J28*0.2 -> 2.2 | L28: 147,123 | M28: -1.9% | N28: 2,665 | O28: 23.2% | P28: 52,616 | Q28: -2 | R28: 31
B29: Reliance Industries | C29: India | D29: Conglomerate & Energy | E29: 381876 | F29: {=_xlfn.IFS( E29<=$E$245,0, E29<=$E$246,1, E29<=$E$247,2, E29>=$E$247,3)} -> 3 | G29: {=_xlfn.IFS( OR(D29="Aerospace",D29="Aerospace & Defense",D29="Agricultural Equipment",D29="Airlines",D29="Automotive",D29="Automotive & Energy",D29="Automotive Components",D29="Aviation",D29="Building Materials",D29="Chemicals",D29="Commercial Vehicles",D29="Conglomerate & Defense",D29="Conglomerate & Energy",D29="Construction",D29="Construction & Infrastructure",D29="Construction & Real Estate",D29="Construction & Telecom",D29="Discount Retail",D29="Energy Management",D29="Energy Technology",D29="Engines & Power Systems",D29="Environmental Services",D29="Food Distribution",D29="Food Services",D29="Grocery Retail",D29="Healthcare & Pharmacy",D29="Home Improvement Retail",D29="Industrial Engineering & Electronics",D29="Oilfield Services",D29="Pharmaceuticals",D29="Pharmaceuticals & Chemicals",D29="Pharmaceuticals & Healthcare",D29="Pharmacy Retail",D29="Postal & Logistics",D29="Retail",D29="Retail & Distribution",D29="Retail & Grocery",D29="Retail (IKEA)",D29="Tobacco",D29="Trading & Conglomerate",D29="Utilities",D29="Utilities & Energy",D29="Wholesale Retail"),2, OR(D29="Agribusiness",D29="Automotive & Heavy Vehicles",D29="Chemicals",D29="Commercial Vehicles",D29="Construction",D29="Construction & Infrastructure",D29="Engines & Power Systems",D29="Food Processing",D29="Healthcare",D29="Healthcare & Medical Devices",D29="Heavy Equipment",D29="Heavy Industry",D29="Industrial Gases",D29="Industrial Manufacturing",D29="Logistics",D29="Medical Devices",D29="Mining",D29="Mining & Commodities Trading",D29="Oil & Gas",D29="Oilfield Services",D29="Rail Transport",D29="Shipping & Logistics",D29="Steel"),3, OR(D29="Apparel & Footwear",D29="Beverage",D29="Coffeehouse & Retail",D29="Conglomerate",D29="Consumer Goods",D29="Convenience Retail",D29="Electronics",D29="Electronics & Semiconductors",D29="Electronics Retail",D29="Fashion Retail",D29="Food & Beverage",D29="Food Retail & Consumer Goods",D29="Industrial & Technology",D29="Industrial Automation",D29="Industrial Technology",D29="Postal & Financial Services",D29="Postal Services",D29="Scientific Instruments",D29="Technology Hardware",D29="Trading Company",D29="IT Consulting"),1, OR(D29="Cosmetics",D29="E-commerce & Cloud Computing",D29="Electronics & Entertainment",D29="Entertainment & Media",D29="Luxury Goods",D29="Media & Telecommunications",D29="Networking Technology",D29="Real Estate Services",D29="Technology & Consumer Electronics",D29="Telecommunications",D29="Telecommunications & Investment"),1, OR(D29="Asset Management",D29="Banking",D29="Banking & Asset Services",D29="Banking & Financial Services",D29="Banking & Wealth Management",D29="Cloud Software",D29="Enterprise Software",D29="Financial Services",D29="Information Technology Consulting",D29="Investment Banking",D29="Social Media & Technology",D29="Software & Cloud Computing",D29="Technology & Consulting",D29="Technology & Internet Services",D29="Technology & Software"),1, TRUE,"Unmapped" )} -> 2 | H29: =VLOOKUP(B29,'BIS + EDBA Final'!A:K,2,FALSE) -> 3 | I29: =VLOOKUP(B29,'BIS + EDBA Final'!A:F,6,FALSE) -> 0 | J29: =VLOOKUP(B29,'CBG Final'!A:B,2,FALSE) -> 1 | K29: =0.3*F29+0.2*G29+0.2*H29+I29*0.1+J29*0.2 -> 2.1 | L29: 114,121.6 | M29: 4.8% | N29: 8,239.3 | O29: -2.1% | P29: 228,260.5 | Q29: -2 | R29: 22 | AD29: =_xlfn.PERCENTILE.INC($E$2:$E$231,0.25) -> 83151.75
B30: Tyson Foods | C30: United States | D30: Food Processing | E30: 138000 | F30: {=_xlfn.IFS( E30<=$E$245,0, E30<=$E$246,1, E30<=$E$247,2, E30>=$E$247,3)} -> 2 | G30: {=_xlfn.IFS( OR(D30="Aerospace",D30="Aerospace & Defense",D30="Agricultural Equipment",D30="Airlines",D30="Automotive",D30="Automotive & Energy",D30="Automotive Components",D30="Aviation",D30="Building Materials",D30="Chemicals",D30="Commercial Vehicles",D30="Conglomerate & Defense",D30="Conglomerate & Energy",D30="Construction",D30="Construction & Infrastructure",D30="Construction & Real Estate",D30="Construction & Telecom",D30="Discount Retail",D30="Energy Management",D30="Energy Technology",D30="Engines & Power Systems",D30="Environmental Services",D30="Food Distribution",D30="Food Services",D30="Grocery Retail",D30="Healthcare & Pharmacy",D30="Home Improvement Retail",D30="Industrial Engineering & Electronics",D30="Oilfield Services",D30="Pharmaceuticals",D30="Pharmaceuticals & Chemicals",D30="Pharmaceuticals & Healthcare",D30="Pharmacy Retail",D30="Postal & Logistics",D30="Retail",D30="Retail & Distribution",D30="Retail & Grocery",D30="Retail (IKEA)",D30="Tobacco",D30="Trading & Conglomerate",D30="Utilities",D30="Utilities & Energy",D30="Wholesale Retail"),2, OR(D30="Agribusiness",D30="Automotive & Heavy Vehicles",D30="Chemicals",D30="Commercial Vehicles",D30="Construction",D30="Construction & Infrastructure",D30="Engines & Power Systems",D30="Food Processing",D30="Healthcare",D30="Healthcare & Medical Devices",D30="Heavy Equipment",D30="Heavy Industry",D30="Industrial Gases",D30="Industrial Manufacturing",D30="Logistics",D30="Medical Devices",D30="Mining",D30="Mining & Commodities Trading",D30="Oil & Gas",D30="Oilfield Services",D30="Rail Transport",D30="Shipping & Logistics",D30="Steel"),3, OR(D30="Apparel & Footwear",D30="Beverage",D30="Coffeehouse & Retail",D30="Conglomerate",D30="Consumer Goods",D30="Convenience Retail",D30="Electronics",D30="Electronics & Semiconductors",D30="Electronics Retail",D30="Fashion Retail",D30="Food & Beverage",D30="Food Retail & Consumer Goods",D30="Industrial & Technology",D30="Industrial Automation",D30="Industrial Technology",D30="Postal & Financial Services",D30="Postal Services",D30="Scientific Instruments",D30="Technology Hardware",D30="Trading Company",D30="IT Consulting"),1, OR(D30="Cosmetics",D30="E-commerce & Cloud Computing",D30="Electronics & Entertainment",D30="Entertainment & Media",D30="Luxury Goods",D30="Media & Telecommunications",D30="Networking Technology",D30="Real Estate Services",D30="Technology & Consumer Electronics",D30="Telecommunications",D30="Telecommunications & Investment"),1, OR(D30="Asset Management",D30="Banking",D30="Banking & Asset Services",D30="Banking & Financial Services",D30="Banking & Wealth Management",D30="Cloud Software",D30="Enterprise Software",D30="Financial Services",D30="Information Technology Consulting",D30="Investment Banking",D30="Social Media & Technology",D30="Software & Cloud Computing",D30="Technology & Consulting",D30="Technology & Internet Services",D30="Technology & Software"),1, TRUE,"Unmapped" )} -> 3 | H30: 2 | I30: =VLOOKUP(B30,'BIS + EDBA Final'!A:F,6,FALSE) -> 1 | J30: =VLOOKUP(B30,'CBG Final'!A:B,2,FALSE) -> 2 | K30: =0.3*F30+0.2*G30+0.2*H30+I30*0.1+J30*0.2 -> 2.1 | L30: 53,309 | M30: 0.8% | N30: 800 | P30: 37,100 | Q30: -2 | R30: 24
B31: Lockheed Martin | C31: United States | D31: Aerospace & Defense | E31: 121000 | F31: {=_xlfn.IFS( E31<=$E$245,0, E31<=$E$246,1, E31<=$E$247,2, E31>=$E$247,3)} -> 2 | G31: {=_xlfn.IFS( OR(D31="Aerospace",D31="Aerospace & Defense",D31="Agricultural Equipment",D31="Airlines",D31="Automotive",D31="Automotive & Energy",D31="Automotive Components",D31="Aviation",D31="Building Materials",D31="Chemicals",D31="Commercial Vehicles",D31="Conglomerate & Defense",D31="Conglomerate & Energy",D31="Construction",D31="Construction & Infrastructure",D31="Construction & Real Estate",D31="Construction & Telecom",D31="Discount Retail",D31="Energy Management",D31="Energy Technology",D31="Engines & Power Systems",D31="Environmental Services",D31="Food Distribution",D31="Food Services",D31="Grocery Retail",D31="Healthcare & Pharmacy",D31="Home Improvement Retail",D31="Industrial Engineering & Electronics",D31="Oilfield Services",D31="Pharmaceuticals",D31="Pharmaceuticals & Chemicals",D31="Pharmaceuticals & Healthcare",D31="Pharmacy Retail",D31="Postal & Logistics",D31="Retail",D31="Retail & Distribution",D31="Retail & Grocery",D31="Retail (IKEA)",D31="Tobacco",D31="Trading & Conglomerate",D31="Utilities",D31="Utilities & Energy",D31="Wholesale Retail"),2, OR(D31="Agribusiness",D31="Automotive & Heavy Vehicles",D31="Chemicals",D31="Commercial Vehicles",D31="Construction",D31="Construction & Infrastructure",D31="Engines & Power Systems",D31="Food Processing",D31="Healthcare",D31="Healthcare & Medical Devices",D31="Heavy Equipment",D31="Heavy Industry",D31="Industrial Gases",D31="Industrial Manufacturing",D31="Logistics",D31="Medical Devices",D31="Mining",D31="Mining & Commodities Trading",D31="Oil & Gas",D31="Oilfield Services",D31="Rail Transport",D31="Shipping & Logistics",D31="Steel"),3, OR(D31="Apparel & Footwear",D31="Beverage",D31="Coffeehouse & Retail",D31="Conglomerate",D31="Consumer Goods",D31="Convenience Retail",D31="Electronics",D31="Electronics & Semiconductors",D31="Electronics Retail",D31="Fashion Retail",D31="Food & Beverage",D31="Food Retail & Consumer Goods",D31="Industrial & Technology",D31="Industrial Automation",D31="Industrial Technology",D31="Postal & Financial Services",D31="Postal Services",D31="Scientific Instruments",D31="Technology Hardware",D31="Trading Company",D31="IT Consulting"),1, OR(D31="Cosmetics",D31="E-commerce & Cloud Computing",D31="Electronics & Entertainment",D31="Entertainment & Media",D31="Luxury Goods",D31="Media & Telecommunications",D31="Networking Technology",D31="Real Estate Services",D31="Technology & Consumer Electronics",D31="Telecommunications",D31="Telecommunications & Investment"),1, OR(D31="Asset Management",D31="Banking",D31="Banking & Asset Services",D31="Banking & Financial Services",D31="Banking & Wealth Management",D31="Cloud Software",D31="Enterprise Software",D31="Financial Services",D31="Information Technology Consulting",D31="Investment Banking",D31="Social Media & Technology",D31="Software & Cloud Computing",D31="Technology & Consulting",D31="Technology & Internet Services",D31="Technology & Software"),1, TRUE,"Unmapped" )} -> 2 | H31: 2 | I31: =VLOOKUP(B31,'BIS + EDBA Final'!A:F,6,FALSE) -> 1 | J31: =VLOOKUP(B31,'CBG Final'!A:B,2,FALSE) -> 3 | K31: =0.3*F31+0.2*G31+0.2*H31+I31*0.1+J31*0.2 -> 2.1 | L31: 71,043 | M31: 5.1% | N31: 5,336 | O31: -22.9% | P31: 55,617 | Q31: 7 | R31: 31
B32: Johnson & Johnson | C32: United States | D32: Pharmaceuticals & Healthcare | E32: 138100 | F32: {=_xlfn.IFS( E32<=$E$245,0, E32<=$E$246,1, E32<=$E$247,2, E32>=$E$247,3)} -> 2 | G32: {=_xlfn.IFS( OR(D32="Aerospace",D32="Aerospace & Defense",D32="Agricultural Equipment",D32="Airlines",D32="Automotive",D32="Automotive & Energy",D32="Automotive Components",D32="Aviation",D32="Building Materials",D32="Chemicals",D32="Commercial Vehicles",D32="Conglomerate & Defense",D32="Conglomerate & Energy",D32="Construction",D32="Construction & Infrastructure",D32="Construction & Real Estate",D32="Construction & Telecom",D32="Discount Retail",D32="Energy Management",D32="Energy Technology",D32="Engines & Power Systems",D32="Environmental Services",D32="Food Distribution",D32="Food Services",D32="Grocery Retail",D32="Healthcare & Pharmacy",D32="Home Improvement Retail",D32="Industrial Engineering & Electronics",D32="Oilfield Services",D32="Pharmaceuticals",D32="Pharmaceuticals & Chemicals",D32="Pharmaceuticals & Healthcare",D32="Pharmacy Retail",D32="Postal & Logistics",D32="Retail",D32="Retail & Distribution",D32="Retail & Grocery",D32="Retail (IKEA)",D32="Tobacco",D32="Trading & Conglomerate",D32="Utilities",D32="Utilities & Energy",D32="Wholesale Retail"),2, OR(D32="Agribusiness",D32="Automotive & Heavy Vehicles",D32="Chemicals",D32="Commercial Vehicles",D32="Construction",D32="Construction & Infrastructure",D32="Engines & Power Systems",D32="Food Processing",D32="Healthcare",D32="Healthcare & Medical Devices",D32="Heavy Equipment",D32="Heavy Industry",D32="Industrial Gases",D32="Industrial Manufacturing",D32="Logistics",D32="Medical Devices",D32="Mining",D32="Mining & Commodities Trading",D32="Oil & Gas",D32="Oilfield Services",D32="Rail Transport",D32="Shipping & Logistics",D32="Steel"),3, OR(D32="Apparel & Footwear",D32="Beverage",D32="Coffeehouse & Retail",D32="Conglomerate",D32="Consumer Goods",D32="Convenience Retail",D32="Electronics",D32="Electronics & Semiconductors",D32="Electronics Retail",D32="Fashion Retail",D32="Food & Beverage",D32="Food Retail & Consumer Goods",D32="Industrial & Technology",D32="Industrial Automation",D32="Industrial Technology",D32="Postal & Financial Services",D32="Postal Services",D32="Scientific Instruments",D32="Technology Hardware",D32="Trading Company",D32="IT Consulting"),1, OR(D32="Cosmetics",D32="E-commerce & Cloud Computing",D32="Electronics & Entertainment",D32="Entertainment & Media",D32="Luxury Goods",D32="Media & Telecommunications",D32="Networking Technology",D32="Real Estate Services",D32="Technology & Consumer Electronics",D32="Telecommunications",D32="Telecommunications & Investment"),1, OR(D32="Asset Management",D32="Banking",D32="Banking & Asset Services",D32="Banking & Financial Services",D32="Banking & Wealth Management",D32="Cloud Software",D32="Enterprise Software",D32="Financial Services",D32="Information Technology Consulting",D32="Investment Banking",D32="Social Media & Technology",D32="Software & Cloud Computing",D32="Technology & Consulting",D32="Technology & Internet Services",D32="Technology & Software"),1, TRUE,"Unmapped" )} -> 2 | H32: 2 | I32: =VLOOKUP(B32,'BIS + EDBA Final'!A:F,6,FALSE) -> 1 | J32: =VLOOKUP(B32,'CBG Final'!A:B,2,FALSE) -> 3 | K32: =0.3*F32+0.2*G32+0.2*H32+I32*0.1+J32*0.2 -> 2.1 | L32: 88,821 | M32: -6.7% | N32: 14,066 | O32: -60% | P32: 180,104 | Q32: -16 | R32: 25
B33: Ingka Group | C33: Netherlands | D33: Retail (IKEA) | E33: 162293 | F33: {=_xlfn.IFS( E33<=$E$245,0, E33<=$E$246,1, E33<=$E$247,2, E33>=$E$247,3)} -> 2 | G33: {=_xlfn.IFS( OR(D33="Aerospace",D33="Aerospace & Defense",D33="Agricultural Equipment",D33="Airlines",D33="Automotive",D33="Automotive & Energy",D33="Automotive Components",D33="Aviation",D33="Building Materials",D33="Chemicals",D33="Commercial Vehicles",D33="Conglomerate & Defense",D33="Conglomerate & Energy",D33="Construction",D33="Construction & Infrastructure",D33="Construction & Real Estate",D33="Construction & Telecom",D33="Discount Retail",D33="Energy Management",D33="Energy Technology",D33="Engines & Power Systems",D33="Environmental Services",D33="Food Distribution",D33="Food Services",D33="Grocery Retail",D33="Healthcare & Pharmacy",D33="Home Improvement Retail",D33="Industrial Engineering & Electronics",D33="Oilfield Services",D33="Pharmaceuticals",D33="Pharmaceuticals & Chemicals",D33="Pharmaceuticals & Healthcare",D33="Pharmacy Retail",D33="Postal & Logistics",D33="Retail",D33="Retail & Distribution",D33="Retail & Grocery",D33="Retail (IKEA)",D33="Tobacco",D33="Trading & Conglomerate",D33="Utilities",D33="Utilities & Energy",D33="Wholesale Retail"),2, OR(D33="Agribusiness",D33="Automotive & Heavy Vehicles",D33="Chemicals",D33="Commercial Vehicles",D33="Construction",D33="Construction & Infrastructure",D33="Engines & Power Systems",D33="Food Processing",D33="Healthcare",D33="Healthcare & Medical Devices",D33="Heavy Equipment",D33="Heavy Industry",D33="Industrial Gases",D33="Industrial Manufacturing",D33="Logistics",D33="Medical Devices",D33="Mining",D33="Mining & Commodities Trading",D33="Oil & Gas",D33="Oilfield Services",D33="Rail Transport",D33="Shipping & Logistics",D33="Steel"),3, OR(D33="Apparel & Footwear",D33="Beverage",D33="Coffeehouse & Retail",D33="Conglomerate",D33="Consumer Goods",D33="Convenience Retail",D33="Electronics",D33="Electronics & Semiconductors",D33="Electronics Retail",D33="Fashion Retail",D33="Food & Beverage",D33="Food Retail & Consumer Goods",D33="Industrial & Technology",D33="Industrial Automation",D33="Industrial Technology",D33="Postal & Financial Services",D33="Postal Services",D33="Scientific Instruments",D33="Technology Hardware",D33="Trading Company",D33="IT Consulting"),1, OR(D33="Cosmetics",D33="E-commerce & Cloud Computing",D33="Electronics & Entertainment",D33="Entertainment & Media",D33="Luxury Goods",D33="Media & Telecommunications",D33="Networking Technology",D33="Real Estate Services",D33="Technology & Consumer Electronics",D33="Telecommunications",D33="Telecommunications & Investment"),1, OR(D33="Asset Management",D33="Banking",D33="Banking & Asset Services",D33="Banking & Financial Services",D33="Banking & Wealth Management",D33="Cloud Software",D33="Enterprise Software",D33="Financial Services",D33="Information Technology Consulting",D33="Investment Banking",D33="Social Media & Technology",D33="Software & Cloud Computing",D33="Technology & Consulting",D33="Technology & Internet Services",D33="Technology & Software"),1, TRUE,"Unmapped" )} -> 2 | H33: 2 | I33: =VLOOKUP(B33,'BIS + EDBA Final'!A:F,6,FALSE) -> 1 | J33: =VLOOKUP(B33,'CBG Final'!A:B,2,FALSE) -> 3 | K33: =0.3*F33+0.2*G33+0.2*H33+I33*0.1+J33*0.2 -> 2.1 | L33: 45,215.7 | M33: -3.7% | N33: 870.9 | O33: -45.5% | P33: 63,700.5 | Q33: -13 | R33: 5
B34: Carrefour | C34: France | D34: Retail | E34: 324750 | F34: {=_xlfn.IFS( E34<=$E$245,0, E34<=$E$246,1, E34<=$E$247,2, E34>=$E$247,3)} -> 3 | G34: {=_xlfn.IFS( OR(D34="Aerospace",D34="Aerospace & Defense",D34="Agricultural Equipment",D34="Airlines",D34="Automotive",D34="Automotive & Energy",D34="Automotive Components",D34="Aviation",D34="Building Materials",D34="Chemicals",D34="Commercial Vehicles",D34="Conglomerate & Defense",D34="Conglomerate & Energy",D34="Construction",D34="Construction & Infrastructure",D34="Construction & Real Estate",D34="Construction & Telecom",D34="Discount Retail",D34="Energy Management",D34="Energy Technology",D34="Engines & Power Systems",D34="Environmental Services",D34="Food Distribution",D34="Food Services",D34="Grocery Retail",D34="Healthcare & Pharmacy",D34="Home Improvement Retail",D34="Industrial Engineering & Electronics",D34="Oilfield Services",D34="Pharmaceuticals",D34="Pharmaceuticals & Chemicals",D34="Pharmaceuticals & Healthcare",D34="Pharmacy Retail",D34="Postal & Logistics",D34="Retail",D34="Retail & Distribution",D34="Retail & Grocery",D34="Retail (IKEA)",D34="Tobacco",D34="Trading & Conglomerate",D34="Utilities",D34="Utilities & Energy",D34="Wholesale Retail"),2, OR(D34="Agribusiness",D34="Automotive & Heavy Vehicles",D34="Chemicals",D34="Commercial Vehicles",D34="Construction",D34="Construction & Infrastructure",D34="Engines & Power Systems",D34="Food Processing",D34="Healthcare",D34="Healthcare & Medical Devices",D34="Heavy Equipment",D34="Heavy Industry",D34="Industrial Gases",D34="Industrial Manufacturing",D34="Logistics",D34="Medical Devices",D34="Mining",D34="Mining & Commodities Trading",D34="Oil & Gas",D34="Oilfield Services",D34="Rail Transport",D34="Shipping & Logistics",D34="Steel"),3, OR(D34="Apparel & Footwear",D34="Beverage",D34="Coffeehouse & Retail",D34="Conglomerate",D34="Consumer Goods",D34="Convenience Retail",D34="Electronics",D34="Electronics & Semiconductors",D34="Electronics Retail",D34="Fashion Retail",D34="Food & Beverage",D34="Food Retail & Consumer Goods",D34="Industrial & Technology",D34="Industrial Automation",D34="Industrial Technology",D34="Postal & Financial Services",D34="Postal Services",D34="Scientific Instruments",D34="Technology Hardware",D34="Trading Company",D34="IT Consulting"),1, OR(D34="Cosmetics",D34="E-commerce & Cloud Computing",D34="Electronics & Entertainment",D34="Entertainment & Media",D34="Luxury Goods",D34="Media & Telecommunications",D34="Networking Technology",D34="Real Estate Services",D34="Technology & Consumer Electronics",D34="Telecommunications",D34="Telecommunications & Investment"),1, OR(D34="Asset Management",D34="Banking",D34="Banking & Asset Services",D34="Banking & Financial Services",D34="Banking & Wealth Management",D34="Cloud Software",D34="Enterprise Software",D34="Financial Services",D34="Information Technology Consulting",D34="Investment Banking",D34="Social Media & Technology",D34="Software & Cloud Computing",D34="Technology & Consulting",D34="Technology & Internet Services",D34="Technology & Software"),1, TRUE,"Unmapped" )} -> 2 | H34: =VLOOKUP(B34,'BIS + EDBA Final'!A:K,2,FALSE) -> 2 | I34: =VLOOKUP(B34,'BIS + EDBA Final'!A:F,6,FALSE) -> 0 | J34: =VLOOKUP(B34,'CBG Final'!A:B,2,FALSE) -> 2 | K34: =0.3*F34+0.2*G34+0.2*H34+I34*0.1+J34*0.2 -> 2.1 | L34: 94,376.6 | M34: 2.8% | N34: 781.9 | O34: -56.4% | P34: 59,394.3 | Q34: 9 | R34: 31
B35: Veolia Environnement | C35: France | D35: Environmental Services | E35: 214041 | F35: {=_xlfn.IFS( E35<=$E$245,0, E35<=$E$246,1, E35<=$E$247,2, E35>=$E$247,3)} -> 3 | G35: {=_xlfn.IFS( OR(D35="Aerospace",D35="Aerospace & Defense",D35="Agricultural Equipment",D35="Airlines",D35="Automotive",D35="Automotive & Energy",D35="Automotive Components",D35="Aviation",D35="Building Materials",D35="Chemicals",D35="Commercial Vehicles",D35="Conglomerate & Defense",D35="Conglomerate & Energy",D35="Construction",D35="Construction & Infrastructure",D35="Construction & Real Estate",D35="Construction & Telecom",D35="Discount Retail",D35="Energy Management",D35="Energy Technology",D35="Engines & Power Systems",D35="Environmental Services",D35="Food Distribution",D35="Food Services",D35="Grocery Retail",D35="Healthcare & Pharmacy",D35="Home Improvement Retail",D35="Industrial Engineering & Electronics",D35="Oilfield Services",D35="Pharmaceuticals",D35="Pharmaceuticals & Chemicals",D35="Pharmaceuticals & Healthcare",D35="Pharmacy Retail",D35="Postal & Logistics",D35="Retail",D35="Retail & Distribution",D35="Retail & Grocery",D35="Retail (IKEA)",D35="Tobacco",D35="Trading & Conglomerate",D35="Utilities",D35="Utilities & Energy",D35="Wholesale Retail"),2, OR(D35="Agribusiness",D35="Automotive & Heavy Vehicles",D35="Chemicals",D35="Commercial Vehicles",D35="Construction",D35="Construction & Infrastructure",D35="Engines & Power Systems",D35="Food Processing",D35="Healthcare",D35="Healthcare & Medical Devices",D35="Heavy Equipment",D35="Heavy Industry",D35="Industrial Gases",D35="Industrial Manufacturing",D35="Logistics",D35="Medical Devices",D35="Mining",D35="Mining & Commodities Trading",D35="Oil & Gas",D35="Oilfield Services",D35="Rail Transport",D35="Shipping & Logistics",D35="Steel"),3, OR(D35="Apparel & Footwear",D35="Beverage",D35="Coffeehouse & Retail",D35="Conglomerate",D35="Consumer Goods",D35="Convenience Retail",D35="Electronics",D35="Electronics & Semiconductors",D35="Electronics Retail",D35="Fashion Retail",D35="Food & Beverage",D35="Food Retail & Consumer Goods",D35="Industrial & Technology",D35="Industrial Automation",D35="Industrial Technology",D35="Postal & Financial Services",D35="Postal Services",D35="Scientific Instruments",D35="Technology Hardware",D35="Trading Company",D35="IT Consulting"),1, OR(D35="Cosmetics",D35="E-commerce & Cloud Computing",D35="Electronics & Entertainment",D35="Entertainment & Media",D35="Luxury Goods",D35="Media & Telecommunications",D35="Networking Technology",D35="Real Estate Services",D35="Technology & Consumer Electronics",D35="Telecommunications",D35="Telecommunications & Investment"),1, OR(D35="Asset Management",D35="Banking",D35="Banking & Asset Services",D35="Banking & Financial Services",D35="Banking & Wealth Management",D35="Cloud Software",D35="Enterprise Software",D35="Financial Services",D35="Information Technology Consulting",D35="Investment Banking",D35="Social Media & Technology",D35="Software & Cloud Computing",D35="Technology & Consulting",D35="Technology & Internet Services",D35="Technology & Software"),1, TRUE,"Unmapped" )} -> 2 | H35: =VLOOKUP(B35,'BIS + EDBA Final'!A:K,2,FALSE) -> 1 | I35: =VLOOKUP(B35,'BIS + EDBA Final'!A:F,6,FALSE) -> 0 | J35: =VLOOKUP(B35,'CBG Final'!A:B,2,FALSE) -> 3 | K35: =0.3*F35+0.2*G35+0.2*H35+I35*0.1+J35*0.2 -> 2.1 | L35: 48,331.4 | M35: -1.4% | N35: 1,187.4 | O35: 17.2% | P35: 75,542.6 | Q35: -5 | R35: 23
B36: Bosch Group | C36: Germany | D36: Industrial Engineering & Electronics | E36: 417859 | F36: {=_xlfn.IFS( E36<=$E$245,0, E36<=$E$246,1, E36<=$E$247,2, E36>=$E$247,3)} -> 3 | G36: {=_xlfn.IFS( OR(D36="Aerospace",D36="Aerospace & Defense",D36="Agricultural Equipment",D36="Airlines",D36="Automotive",D36="Automotive & Energy",D36="Automotive Components",D36="Aviation",D36="Building Materials",D36="Chemicals",D36="Commercial Vehicles",D36="Conglomerate & Defense",D36="Conglomerate & Energy",D36="Construction",D36="Construction & Infrastructure",D36="Construction & Real Estate",D36="Construction & Telecom",D36="Discount Retail",D36="Energy Management",D36="Energy Technology",D36="Engines & Power Systems",D36="Environmental Services",D36="Food Distribution",D36="Food Services",D36="Grocery Retail",D36="Healthcare & Pharmacy",D36="Home Improvement Retail",D36="Industrial Engineering & Electronics",D36="Oilfield Services",D36="Pharmaceuticals",D36="Pharmaceuticals & Chemicals",D36="Pharmaceuticals & Healthcare",D36="Pharmacy Retail",D36="Postal & Logistics",D36="Retail",D36="Retail & Distribution",D36="Retail & Grocery",D36="Retail (IKEA)",D36="Tobacco",D36="Trading & Conglomerate",D36="Utilities",D36="Utilities & Energy",D36="Wholesale Retail"),2, OR(D36="Agribusiness",D36="Automotive & Heavy Vehicles",D36="Chemicals",D36="Commercial Vehicles",D36="Construction",D36="Construction & Infrastructure",D36="Engines & Power Systems",D36="Food Processing",D36="Healthcare",D36="Healthcare & Medical Devices",D36="Heavy Equipment",D36="Heavy Industry",D36="Industrial Gases",D36="Industrial Manufacturing",D36="Logistics",D36="Medical Devices",D36="Mining",D36="Mining & Commodities Trading",D36="Oil & Gas",D36="Oilfield Services",D36="Rail Transport",D36="Shipping & Logistics",D36="Steel"),3, OR(D36="Apparel & Footwear",D36="Beverage",D36="Coffeehouse & Retail",D36="Conglomerate",D36="Consumer Goods",D36="Convenience Retail",D36="Electronics",D36="Electronics & Semiconductors",D36="Electronics Retail",D36="Fashion Retail",D36="Food & Beverage",D36="Food Retail & Consumer Goods",D36="Industrial & Technology",D36="Industrial Automation",D36="Industrial Technology",D36="Postal & Financial Services",D36="Postal Services",D36="Scientific Instruments",D36="Technology Hardware",D36="Trading Company",D36="IT Consulting"),1, OR(D36="Cosmetics",D36="E-commerce & Cloud Computing",D36="Electronics & Entertainment",D36="Entertainment & Media",D36="Luxury Goods",D36="Media & Telecommunications",D36="Networking Technology",D36="Real Estate Services",D36="Technology & Consumer Electronics",D36="Telecommunications",D36="Telecommunications & Investment"),1, OR(D36="Asset Management",D36="Banking",D36="Banking & Asset Services",D36="Banking & Financial Services",D36="Banking & Wealth Management",D36="Cloud Software",D36="Enterprise Software",D36="Financial Services",D36="Information Technology Consulting",D36="Investment Banking",D36="Social Media & Technology",D36="Software & Cloud Computing",D36="Technology & Consulting",D36="Technology & Internet Services",D36="Technology & Software"),1, TRUE,"Unmapped" )} -> 2 | H36: 2 | I36: =VLOOKUP(B36,'BIS + EDBA Final'!A:F,6,FALSE) -> 0 | J36: =VLOOKUP(B36,'CBG Final'!A:B,2,FALSE) -> 2 | K36: =0.3*F36+0.2*G36+0.2*H36+I36*0.1+J36*0.2 -> 2.1 | L36: 97,702 | M36: -1.3% | N36: 850 | O36: -62.6% | P36: 116,759.2 | Q36: - | R36: 31
B37: Volkswagen | C37: Germany | D37: Automotive | E37: 646501 | F37: {=_xlfn.IFS( E37<=$E$245,0, E37<=$E$246,1, E37<=$E$247,2, E37>=$E$247,3)} -> 3 | G37: {=_xlfn.IFS( OR(D37="Aerospace",D37="Aerospace & Defense",D37="Agricultural Equipment",D37="Airlines",D37="Automotive",D37="Automotive & Energy",D37="Automotive Components",D37="Aviation",D37="Building Materials",D37="Chemicals",D37="Commercial Vehicles",D37="Conglomerate & Defense",D37="Conglomerate & Energy",D37="Construction",D37="Construction & Infrastructure",D37="Construction & Real Estate",D37="Construction & Telecom",D37="Discount Retail",D37="Energy Management",D37="Energy Technology",D37="Engines & Power Systems",D37="Environmental Services",D37="Food Distribution",D37="Food Services",D37="Grocery Retail",D37="Healthcare & Pharmacy",D37="Home Improvement Retail",D37="Industrial Engineering & Electronics",D37="Oilfield Services",D37="Pharmaceuticals",D37="Pharmaceuticals & Chemicals",D37="Pharmaceuticals & Healthcare",D37="Pharmacy Retail",D37="Postal & Logistics",D37="Retail",D37="Retail & Distribution",D37="Retail & Grocery",D37="Retail (IKEA)",D37="Tobacco",D37="Trading & Conglomerate",D37="Utilities",D37="Utilities & Energy",D37="Wholesale Retail"),2, OR(D37="Agribusiness",D37="Automotive & Heavy Vehicles",D37="Chemicals",D37="Commercial Vehicles",D37="Construction",D37="Construction & Infrastructure",D37="Engines & Power Systems",D37="Food Processing",D37="Healthcare",D37="Healthcare & Medical Devices",D37="Heavy Equipment",D37="Heavy Industry",D37="Industrial Gases",D37="Industrial Manufacturing",D37="Logistics",D37="Medical Devices",D37="Mining",D37="Mining & Commodities Trading",D37="Oil & Gas",D37="Oilfield Services",D37="Rail Transport",D37="Shipping & Logistics",D37="Steel"),3, OR(D37="Apparel & Footwear",D37="Beverage",D37="Coffeehouse & Retail",D37="Conglomerate",D37="Consumer Goods",D37="Convenience Retail",D37="Electronics",D37="Electronics & Semiconductors",D37="Electronics Retail",D37="Fashion Retail",D37="Food & Beverage",D37="Food Retail & Consumer Goods",D37="Industrial & Technology",D37="Industrial Automation",D37="Industrial Technology",D37="Postal & Financial Services",D37="Postal Services",D37="Scientific Instruments",D37="Technology Hardware",D37="Trading Company",D37="IT Consulting"),1, OR(D37="Cosmetics",D37="E-commerce & Cloud Computing",D37="Electronics & Entertainment",D37="Entertainment & Media",D37="Luxury Goods",D37="Media & Telecommunications",D37="Networking Technology",D37="Real Estate Services",D37="Technology & Consumer Electronics",D37="Telecommunications",D37="Telecommunications & Investment"),1, OR(D37="Asset Management",D37="Banking",D37="Banking & Asset Services",D37="Banking & Financial Services",D37="Banking & Wealth Management",D37="Cloud Software",D37="Enterprise Software",D37="Financial Services",D37="Information Technology Consulting",D37="Investment Banking",D37="Social Media & Technology",D37="Software & Cloud Computing",D37="Technology & Consulting",D37="Technology & Internet Services",D37="Technology & Software"),1, TRUE,"Unmapped" )} -> 2 | H37: =VLOOKUP(B37,'BIS + EDBA Final'!A:K,2,FALSE) -> 1 | I37: =VLOOKUP(B37,'BIS + EDBA Final'!A:F,6,FALSE) -> 0 | J37: =VLOOKUP(B37,'CBG Final'!A:B,2,FALSE) -> 3 | K37: =0.3*F37+0.2*G37+0.2*H37+I37*0.1+J37*0.2 -> 2.1 | L37: 351,093.3 | M37: 0.8% | N37: 12,275.3 | O37: -31.6% | P37: 655,316.8 | Q37: -1 | R37: 31
B38: U.S. Postal Service | C38: United States | D38: Postal & Logistics | E38: 586700 | F38: {=_xlfn.IFS( E38<=$E$245,0, E38<=$E$246,1, E38<=$E$247,2, E38>=$E$247,3)} -> 3 | G38: {=_xlfn.IFS( OR(D38="Aerospace",D38="Aerospace & Defense",D38="Agricultural Equipment",D38="Airlines",D38="Automotive",D38="Automotive & Energy",D38="Automotive Components",D38="Aviation",D38="Building Materials",D38="Chemicals",D38="Commercial Vehicles",D38="Conglomerate & Defense",D38="Conglomerate & Energy",D38="Construction",D38="Construction & Infrastructure",D38="Construction & Real Estate",D38="Construction & Telecom",D38="Discount Retail",D38="Energy Management",D38="Energy Technology",D38="Engines & Power Systems",D38="Environmental Services",D38="Food Distribution",D38="Food Services",D38="Grocery Retail",D38="Healthcare & Pharmacy",D38="Home Improvement Retail",D38="Industrial Engineering & Electronics",D38="Oilfield Services",D38="Pharmaceuticals",D38="Pharmaceuticals & Chemicals",D38="Pharmaceuticals & Healthcare",D38="Pharmacy Retail",D38="Postal & Logistics",D38="Retail",D38="Retail & Distribution",D38="Retail & Grocery",D38="Retail (IKEA)",D38="Tobacco",D38="Trading & Conglomerate",D38="Utilities",D38="Utilities & Energy",D38="Wholesale Retail"),2, OR(D38="Agribusiness",D38="Automotive & Heavy Vehicles",D38="Chemicals",D38="Commercial Vehicles",D38="Construction",D38="Construction & Infrastructure",D38="Engines & Power Systems",D38="Food Processing",D38="Healthcare",D38="Healthcare & Medical Devices",D38="Heavy Equipment",D38="Heavy Industry",D38="Industrial Gases",D38="Industrial Manufacturing",D38="Logistics",D38="Medical Devices",D38="Mining",D38="Mining & Commodities Trading",D38="Oil & Gas",D38="Oilfield Services",D38="Rail Transport",D38="Shipping & Logistics",D38="Steel"),3, OR(D38="Apparel & Footwear",D38="Beverage",D38="Coffeehouse & Retail",D38="Conglomerate",D38="Consumer Goods",D38="Convenience Retail",D38="Electronics",D38="Electronics & Semiconductors",D38="Electronics Retail",D38="Fashion Retail",D38="Food & Beverage",D38="Food Retail & Consumer Goods",D38="Industrial & Technology",D38="Industrial Automation",D38="Industrial Technology",D38="Postal & Financial Services",D38="Postal Services",D38="Scientific Instruments",D38="Technology Hardware",D38="Trading Company",D38="IT Consulting"),1, OR(D38="Cosmetics",D38="E-commerce & Cloud Computing",D38="Electronics & Entertainment",D38="Entertainment & Media",D38="Luxury Goods",D38="Media & Telecommunications",D38="Networking Technology",D38="Real Estate Services",D38="Technology & Consumer Electronics",D38="Telecommunications",D38="Telecommunications & Investment"),1, OR(D38="Asset Management",D38="Banking",D38="Banking & Asset Services",D38="Banking & Financial Services",D38="Banking & Wealth Management",D38="Cloud Software",D38="Enterprise Software",D38="Financial Services",D38="Information Technology Consulting",D38="Investment Banking",D38="Social Media & Technology",D38="Software & Cloud Computing",D38="Technology & Consulting",D38="Technology & Internet Services",D38="Technology & Software"),1, TRUE,"Unmapped" )} -> 2 | H38: 1 | I38: =VLOOKUP(B38,'BIS + EDBA Final'!A:F,6,FALSE) -> 0 | J38: =VLOOKUP(B38,'CBG Final'!A:B,2,FALSE) -> 3 | K38: =0.3*F38+0.2*G38+0.2*H38+I38*0.1+J38*0.2 -> 2.1 | L38: 79,547 | M38: 1.5% | N38: -9,520 | P38: 45,567 | Q38: -1 | R38: 31
B39: Home Depot | C39: United States | D39: Home Improvement Retail | E39: 470100 | F39: {=_xlfn.IFS( E39<=$E$245,0, E39<=$E$246,1, E39<=$E$247,2, E39>=$E$247,3)} -> 3 | G39: {=_xlfn.IFS( OR(D39="Aerospace",D39="Aerospace & Defense",D39="Agricultural Equipment",D39="Airlines",D39="Automotive",D39="Automotive & Energy",D39="Automotive Components",D39="Aviation",D39="Building Materials",D39="Chemicals",D39="Commercial Vehicles",D39="Conglomerate & Defense",D39="Conglomerate & Energy",D39="Construction",D39="Construction & Infrastructure",D39="Construction & Real Estate",D39="Construction & Telecom",D39="Discount Retail",D39="Energy Management",D39="Energy Technology",D39="Engines & Power Systems",D39="Environmental Services",D39="Food Distribution",D39="Food Services",D39="Grocery Retail",D39="Healthcare & Pharmacy",D39="Home Improvement Retail",D39="Industrial Engineering & Electronics",D39="Oilfield Services",D39="Pharmaceuticals",D39="Pharmaceuticals & Chemicals",D39="Pharmaceuticals & Healthcare",D39="Pharmacy Retail",D39="Postal & Logistics",D39="Retail",D39="Retail & Distribution",D39="Retail & Grocery",D39="Retail (IKEA)",D39="Tobacco",D39="Trading & Conglomerate",D39="Utilities",D39="Utilities & Energy",D39="Wholesale Retail"),2, OR(D39="Agribusiness",D39="Automotive & Heavy Vehicles",D39="Chemicals",D39="Commercial Vehicles",D39="Construction",D39="Construction & Infrastructure",D39="Engines & Power Systems",D39="Food Processing",D39="Healthcare",D39="Healthcare & Medical Devices",D39="Heavy Equipment",D39="Heavy Industry",D39="Industrial Gases",D39="Industrial Manufacturing",D39="Logistics",D39="Medical Devices",D39="Mining",D39="Mining & Commodities Trading",D39="Oil & Gas",D39="Oilfield Services",D39="Rail Transport",D39="Shipping & Logistics",D39="Steel"),3, OR(D39="Apparel & Footwear",D39="Beverage",D39="Coffeehouse & Retail",D39="Conglomerate",D39="Consumer Goods",D39="Convenience Retail",D39="Electronics",D39="Electronics & Semiconductors",D39="Electronics Retail",D39="Fashion Retail",D39="Food & Beverage",D39="Food Retail & Consumer Goods",D39="Industrial & Technology",D39="Industrial Automation",D39="Industrial Technology",D39="Postal & Financial Services",D39="Postal Services",D39="Scientific Instruments",D39="Technology Hardware",D39="Trading Company",D39="IT Consulting"),1, OR(D39="Cosmetics",D39="E-commerce & Cloud Computing",D39="Electronics & Entertainment",D39="Entertainment & Media",D39="Luxury Goods",D39="Media & Telecommunications",D39="Networking Technology",D39="Real Estate Services",D39="Technology & Consumer Electronics",D39="Telecommunications",D39="Telecommunications & Investment"),1, OR(D39="Asset Management",D39="Banking",D39="Banking & Asset Services",D39="Banking & Financial Services",D39="Banking & Wealth Management",D39="Cloud Software",D39="Enterprise Software",D39="Financial Services",D39="Information Technology Consulting",D39="Investment Banking",D39="Social Media & Technology",D39="Software & Cloud Computing",D39="Technology & Consulting",D39="Technology & Internet Services",D39="Technology & Software"),1, TRUE,"Unmapped" )} -> 2 | H39: 1 | I39: =VLOOKUP(B39,'BIS + EDBA Final'!A:F,6,FALSE) -> 1 | J39: =VLOOKUP(B39,'CBG Final'!A:B,2,FALSE) -> 2 | K39: =0.3*F39+0.2*G39+0.2*H39+I39*0.1+J39*0.2 -> 2 | L39: 159,514 | M39: 4.5% | N39: 14,806 | O39: -2.2% | P39: 96,119 | Q39: 2 | R39: 31
B40: Starbucks | C40: United States | D40: Coffeehouse & Retail | E40: 361000 | F40: {=_xlfn.IFS( E40<=$E$245,0, E40<=$E$246,1, E40<=$E$247,2, E40>=$E$247,3)} -> 3 | G40: {=_xlfn.IFS( OR(D40="Aerospace",D40="Aerospace & Defense",D40="Agricultural Equipment",D40="Airlines",D40="Automotive",D40="Automotive & Energy",D40="Automotive Components",D40="Aviation",D40="Building Materials",D40="Chemicals",D40="Commercial Vehicles",D40="Conglomerate & Defense",D40="Conglomerate & Energy",D40="Construction",D40="Construction & Infrastructure",D40="Construction & Real Estate",D40="Construction & Telecom",D40="Discount Retail",D40="Energy Management",D40="Energy Technology",D40="Engines & Power Systems",D40="Environmental Services",D40="Food Distribution",D40="Food Services",D40="Grocery Retail",D40="Healthcare & Pharmacy",D40="Home Improvement Retail",D40="Industrial Engineering & Electronics",D40="Oilfield Services",D40="Pharmaceuticals",D40="Pharmaceuticals & Chemicals",D40="Pharmaceuticals & Healthcare",D40="Pharmacy Retail",D40="Postal & Logistics",D40="Retail",D40="Retail & Distribution",D40="Retail & Grocery",D40="Retail (IKEA)",D40="Tobacco",D40="Trading & Conglomerate",D40="Utilities",D40="Utilities & Energy",D40="Wholesale Retail"),2, OR(D40="Agribusiness",D40="Automotive & Heavy Vehicles",D40="Chemicals",D40="Commercial Vehicles",D40="Construction",D40="Construction & Infrastructure",D40="Engines & Power Systems",D40="Food Processing",D40="Healthcare",D40="Healthcare & Medical Devices",D40="Heavy Equipment",D40="Heavy Industry",D40="Industrial Gases",D40="Industrial Manufacturing",D40="Logistics",D40="Medical Devices",D40="Mining",D40="Mining & Commodities Trading",D40="Oil & Gas",D40="Oilfield Services",D40="Rail Transport",D40="Shipping & Logistics",D40="Steel"),3, OR(D40="Apparel & Footwear",D40="Beverage",D40="Coffeehouse & Retail",D40="Conglomerate",D40="Consumer Goods",D40="Convenience Retail",D40="Electronics",D40="Electronics & Semiconductors",D40="Electronics Retail",D40="Fashion Retail",D40="Food & Beverage",D40="Food Retail & Consumer Goods",D40="Industrial & Technology",D40="Industrial Automation",D40="Industrial Technology",D40="Postal & Financial Services",D40="Postal Services",D40="Scientific Instruments",D40="Technology Hardware",D40="Trading Company",D40="IT Consulting"),1, OR(D40="Cosmetics",D40="E-commerce & Cloud Computing",D40="Electronics & Entertainment",D40="Entertainment & Media",D40="Luxury Goods",D40="Media & Telecommunications",D40="Networking Technology",D40="Real Estate Services",D40="Technology & Consumer Electronics",D40="Telecommunications",D40="Telecommunications & Investment"),1, OR(D40="Asset Management",D40="Banking",D40="Banking & Asset Services",D40="Banking & Financial Services",D40="Banking & Wealth Management",D40="Cloud Software",D40="Enterprise Software",D40="Financial Services",D40="Information Technology Consulting",D40="Investment Banking",D40="Social Media & Technology",D40="Software & Cloud Computing",D40="Technology & Consulting",D40="Technology & Internet Services",D40="Technology & Software"),1, TRUE,"Unmapped" )} -> 1 | H40: 2 | I40: =VLOOKUP(B40,'BIS + EDBA Final'!A:F,6,FALSE) -> -1 | J40: =VLOOKUP(B40,'CBG Final'!A:B,2,FALSE) -> 3 | K40: =0.3*F40+0.2*G40+0.2*H40+I40*0.1+J40*0.2 -> 2 | L40: 36,176.2 | M40: 0.6% | N40: 3,760.9 | O40: -8.8% | P40: 31,339.3 | Q40: -17 | R40: 5
B41: Amazon | C41: United States | D41: E-commerce & Cloud Computing | E41: 1556000 | F41: {=_xlfn.IFS( E41<=$E$245,0, E41<=$E$246,1, E41<=$E$247,2, E41>=$E$247,3)} -> 3 | G41: {=_xlfn.IFS( OR(D41="Aerospace",D41="Aerospace & Defense",D41="Agricultural Equipment",D41="Airlines",D41="Automotive",D41="Automotive & Energy",D41="Automotive Components",D41="Aviation",D41="Building Materials",D41="Chemicals",D41="Commercial Vehicles",D41="Conglomerate & Defense",D41="Conglomerate & Energy",D41="Construction",D41="Construction & Infrastructure",D41="Construction & Real Estate",D41="Construction & Telecom",D41="Discount Retail",D41="Energy Management",D41="Energy Technology",D41="Engines & Power Systems",D41="Environmental Services",D41="Food Distribution",D41="Food Services",D41="Grocery Retail",D41="Healthcare & Pharmacy",D41="Home Improvement Retail",D41="Industrial Engineering & Electronics",D41="Oilfield Services",D41="Pharmaceuticals",D41="Pharmaceuticals & Chemicals",D41="Pharmaceuticals & Healthcare",D41="Pharmacy Retail",D41="Postal & Logistics",D41="Retail",D41="Retail & Distribution",D41="Retail & Grocery",D41="Retail (IKEA)",D41="Tobacco",D41="Trading & Conglomerate",D41="Utilities",D41="Utilities & Energy",D41="Wholesale Retail"),2, OR(D41="Agribusiness",D41="Automotive & Heavy Vehicles",D41="Chemicals",D41="Commercial Vehicles",D41="Construction",D41="Construction & Infrastructure",D41="Engines & Power Systems",D41="Food Processing",D41="Healthcare",D41="Healthcare & Medical Devices",D41="Heavy Equipment",D41="Heavy Industry",D41="Industrial Gases",D41="Industrial Manufacturing",D41="Logistics",D41="Medical Devices",D41="Mining",D41="Mining & Commodities Trading",D41="Oil & Gas",D41="Oilfield Services",D41="Rail Transport",D41="Shipping & Logistics",D41="Steel"),3, OR(D41="Apparel & Footwear",D41="Beverage",D41="Coffeehouse & Retail",D41="Conglomerate",D41="Consumer Goods",D41="Convenience Retail",D41="Electronics",D41="Electronics & Semiconductors",D41="Electronics Retail",D41="Fashion Retail",D41="Food & Beverage",D41="Food Retail & Consumer Goods",D41="Industrial & Technology",D41="Industrial Automation",D41="Industrial Technology",D41="Postal & Financial Services",D41="Postal Services",D41="Scientific Instruments",D41="Technology Hardware",D41="Trading Company",D41="IT Consulting"),1, OR(D41="Cosmetics",D41="E-commerce & Cloud Computing",D41="Electronics & Entertainment",D41="Entertainment & Media",D41="Luxury Goods",D41="Media & Telecommunications",D41="Networking Technology",D41="Real Estate Services",D41="Technology & Consumer Electronics",D41="Telecommunications",D41="Telecommunications & Investment"),1, OR(D41="Asset Management",D41="Banking",D41="Banking & Asset Services",D41="Banking & Financial Services",D41="Banking & Wealth Management",D41="Cloud Software",D41="Enterprise Software",D41="Financial Services",D41="Information Technology Consulting",D41="Investment Banking",D41="Social Media & Technology",D41="Software & Cloud Computing",D41="Technology & Consulting",D41="Technology & Internet Services",D41="Technology & Software"),1, TRUE,"Unmapped" )} -> 1 | H41: 2 | I41: =VLOOKUP(B41,'BIS + EDBA Final'!A:F,6,FALSE) -> -1 | J41: =VLOOKUP(B41,'CBG Final'!A:B,2,FALSE) -> 3 | K41: =0.3*F41+0.2*G41+0.2*H41+I41*0.1+J41*0.2 -> 2 | L41: 637,959 | M41: 11% | N41: 59,248 | O41: 94.7% | P41: 624,894 | Q41: - | R41: 17
B42: JPMorgan Chase | C42: United States | D42: Banking & Financial Services | E42: 317233 | F42: {=_xlfn.IFS( E42<=$E$245,0, E42<=$E$246,1, E42<=$E$247,2, E42>=$E$247,3)} -> 3 | G42: {=_xlfn.IFS( OR(D42="Aerospace",D42="Aerospace & Defense",D42="Agricultural Equipment",D42="Airlines",D42="Automotive",D42="Automotive & Energy",D42="Automotive Components",D42="Aviation",D42="Building Materials",D42="Chemicals",D42="Commercial Vehicles",D42="Conglomerate & Defense",D42="Conglomerate & Energy",D42="Construction",D42="Construction & Infrastructure",D42="Construction & Real Estate",D42="Construction & Telecom",D42="Discount Retail",D42="Energy Management",D42="Energy Technology",D42="Engines & Power Systems",D42="Environmental Services",D42="Food Distribution",D42="Food Services",D42="Grocery Retail",D42="Healthcare & Pharmacy",D42="Home Improvement Retail",D42="Industrial Engineering & Electronics",D42="Oilfield Services",D42="Pharmaceuticals",D42="Pharmaceuticals & Chemicals",D42="Pharmaceuticals & Healthcare",D42="Pharmacy Retail",D42="Postal & Logistics",D42="Retail",D42="Retail & Distribution",D42="Retail & Grocery",D42="Retail (IKEA)",D42="Tobacco",D42="Trading & Conglomerate",D42="Utilities",D42="Utilities & Energy",D42="Wholesale Retail"),2, OR(D42="Agribusiness",D42="Automotive & Heavy Vehicles",D42="Chemicals",D42="Commercial Vehicles",D42="Construction",D42="Construction & Infrastructure",D42="Engines & Power Systems",D42="Food Processing",D42="Healthcare",D42="Healthcare & Medical Devices",D42="Heavy Equipment",D42="Heavy Industry",D42="Industrial Gases",D42="Industrial Manufacturing",D42="Logistics",D42="Medical Devices",D42="Mining",D42="Mining & Commodities Trading",D42="Oil & Gas",D42="Oilfield Services",D42="Rail Transport",D42="Shipping & Logistics",D42="Steel"),3, OR(D42="Apparel & Footwear",D42="Beverage",D42="Coffeehouse & Retail",D42="Conglomerate",D42="Consumer Goods",D42="Convenience Retail",D42="Electronics",D42="Electronics & Semiconductors",D42="Electronics Retail",D42="Fashion Retail",D42="Food & Beverage",D42="Food Retail & Consumer Goods",D42="Industrial & Technology",D42="Industrial Automation",D42="Industrial Technology",D42="Postal & Financial Services",D42="Postal Services",D42="Scientific Instruments",D42="Technology Hardware",D42="Trading Company",D42="IT Consulting"),1, OR(D42="Cosmetics",D42="E-commerce & Cloud Computing",D42="Electronics & Entertainment",D42="Entertainment & Media",D42="Luxury Goods",D42="Media & Telecommunications",D42="Networking Technology",D42="Real Estate Services",D42="Technology & Consumer Electronics",D42="Telecommunications",D42="Telecommunications & Investment"),1, OR(D42="Asset Management",D42="Banking",D42="Banking & Asset Services",D42="Banking & Financial Services",D42="Banking & Wealth Management",D42="Cloud Software",D42="Enterprise Software",D42="Financial Services",D42="Information Technology Consulting",D42="Investment Banking",D42="Social Media & Technology",D42="Software & Cloud Computing",D42="Technology & Consulting",D42="Technology & Internet Services",D42="Technology & Software"),1, TRUE,"Unmapped" )} -> 1 | H42: 2 | I42: =VLOOKUP(B42,'BIS + EDBA Final'!A:F,6,FALSE) -> -1 | J42: =VLOOKUP(B42,'CBG Final'!A:B,2,FALSE) -> 3 | K42: =0.3*F42+0.2*G42+0.2*H42+I42*0.1+J42*0.2 -> 2 | L42: 278,906 | M42: 16.5% | N42: 58,471 | O42: 18% | P42: 4,002,814 | Q42: 2 | R42: 31
B43: Banco Santander | C43: Spain | D43: Banking | E43: 206417 | F43: {=_xlfn.IFS( E43<=$E$245,0, E43<=$E$246,1, E43<=$E$247,2, E43>=$E$247,3)} -> 3 | G43: {=_xlfn.IFS( OR(D43="Aerospace",D43="Aerospace & Defense",D43="Agricultural Equipment",D43="Airlines",D43="Automotive",D43="Automotive & Energy",D43="Automotive Components",D43="Aviation",D43="Building Materials",D43="Chemicals",D43="Commercial Vehicles",D43="Conglomerate & Defense",D43="Conglomerate & Energy",D43="Construction",D43="Construction & Infrastructure",D43="Construction & Real Estate",D43="Construction & Telecom",D43="Discount Retail",D43="Energy Management",D43="Energy Technology",D43="Engines & Power Systems",D43="Environmental Services",D43="Food Distribution",D43="Food Services",D43="Grocery Retail",D43="Healthcare & Pharmacy",D43="Home Improvement Retail",D43="Industrial Engineering & Electronics",D43="Oilfield Services",D43="Pharmaceuticals",D43="Pharmaceuticals & Chemicals",D43="Pharmaceuticals & Healthcare",D43="Pharmacy Retail",D43="Postal & Logistics",D43="Retail",D43="Retail & Distribution",D43="Retail & Grocery",D43="Retail (IKEA)",D43="Tobacco",D43="Trading & Conglomerate",D43="Utilities",D43="Utilities & Energy",D43="Wholesale Retail"),2, OR(D43="Agribusiness",D43="Automotive & Heavy Vehicles",D43="Chemicals",D43="Commercial Vehicles",D43="Construction",D43="Construction & Infrastructure",D43="Engines & Power Systems",D43="Food Processing",D43="Healthcare",D43="Healthcare & Medical Devices",D43="Heavy Equipment",D43="Heavy Industry",D43="Industrial Gases",D43="Industrial Manufacturing",D43="Logistics",D43="Medical Devices",D43="Mining",D43="Mining & Commodities Trading",D43="Oil & Gas",D43="Oilfield Services",D43="Rail Transport",D43="Shipping & Logistics",D43="Steel"),3, OR(D43="Apparel & Footwear",D43="Beverage",D43="Coffeehouse & Retail",D43="Conglomerate",D43="Consumer Goods",D43="Convenience Retail",D43="Electronics",D43="Electronics & Semiconductors",D43="Electronics Retail",D43="Fashion Retail",D43="Food & Beverage",D43="Food Retail & Consumer Goods",D43="Industrial & Technology",D43="Industrial Automation",D43="Industrial Technology",D43="Postal & Financial Services",D43="Postal Services",D43="Scientific Instruments",D43="Technology Hardware",D43="Trading Company",D43="IT Consulting"),1, OR(D43="Cosmetics",D43="E-commerce & Cloud Computing",D43="Electronics & Entertainment",D43="Entertainment & Media",D43="Luxury Goods",D43="Media & Telecommunications",D43="Networking Technology",D43="Real Estate Services",D43="Technology & Consumer Electronics",D43="Telecommunications",D43="Telecommunications & Investment"),1, OR(D43="Asset Management",D43="Banking",D43="Banking & Asset Services",D43="Banking & Financial Services",D43="Banking & Wealth Management",D43="Cloud Software",D43="Enterprise Software",D43="Financial Services",D43="Information Technology Consulting",D43="Investment Banking",D43="Social Media & Technology",D43="Software & Cloud Computing",D43="Technology & Consulting",D43="Technology & Internet Services",D43="Technology & Software"),1, TRUE,"Unmapped" )} -> 1 | H43: 2 | I43: =VLOOKUP(B43,'BIS + EDBA Final'!A:F,6,FALSE) -> 1 | J43: =VLOOKUP(B43,'CBG Final'!A:B,2,FALSE) -> 2 | K43: =0.3*F43+0.2*G43+0.2*H43+I43*0.1+J43*0.2 -> 2 | L43: 146,326.4 | M43: 6.6% | N43: 13,597.9 | O43: 13.6% | P43: 1,902,134 | Q43: 7 | R43: 31
B44: HSBC Holdings | C44: United Kingdom | D44: Banking | E44: 211304 | F44: {=_xlfn.IFS( E44<=$E$245,0, E44<=$E$246,1, E44<=$E$247,2, E44>=$E$247,3)} -> 3 | G44: {=_xlfn.IFS( OR(D44="Aerospace",D44="Aerospace & Defense",D44="Agricultural Equipment",D44="Airlines",D44="Automotive",D44="Automotive & Energy",D44="Automotive Components",D44="Aviation",D44="Building Materials",D44="Chemicals",D44="Commercial Vehicles",D44="Conglomerate & Defense",D44="Conglomerate & Energy",D44="Construction",D44="Construction & Infrastructure",D44="Construction & Real Estate",D44="Construction & Telecom",D44="Discount Retail",D44="Energy Management",D44="Energy Technology",D44="Engines & Power Systems",D44="Environmental Services",D44="Food Distribution",D44="Food Services",D44="Grocery Retail",D44="Healthcare & Pharmacy",D44="Home Improvement Retail",D44="Industrial Engineering & Electronics",D44="Oilfield Services",D44="Pharmaceuticals",D44="Pharmaceuticals & Chemicals",D44="Pharmaceuticals & Healthcare",D44="Pharmacy Retail",D44="Postal & Logistics",D44="Retail",D44="Retail & Distribution",D44="Retail & Grocery",D44="Retail (IKEA)",D44="Tobacco",D44="Trading & Conglomerate",D44="Utilities",D44="Utilities & Energy",D44="Wholesale Retail"),2, OR(D44="Agribusiness",D44="Automotive & Heavy Vehicles",D44="Chemicals",D44="Commercial Vehicles",D44="Construction",D44="Construction & Infrastructure",D44="Engines & Power Systems",D44="Food Processing",D44="Healthcare",D44="Healthcare & Medical Devices",D44="Heavy Equipment",D44="Heavy Industry",D44="Industrial Gases",D44="Industrial Manufacturing",D44="Logistics",D44="Medical Devices",D44="Mining",D44="Mining & Commodities Trading",D44="Oil & Gas",D44="Oilfield Services",D44="Rail Transport",D44="Shipping & Logistics",D44="Steel"),3, OR(D44="Apparel & Footwear",D44="Beverage",D44="Coffeehouse & Retail",D44="Conglomerate",D44="Consumer Goods",D44="Convenience Retail",D44="Electronics",D44="Electronics & Semiconductors",D44="Electronics Retail",D44="Fashion Retail",D44="Food & Beverage",D44="Food Retail & Consumer Goods",D44="Industrial & Technology",D44="Industrial Automation",D44="Industrial Technology",D44="Postal & Financial Services",D44="Postal Services",D44="Scientific Instruments",D44="Technology Hardware",D44="Trading Company",D44="IT Consulting"),1, OR(D44="Cosmetics",D44="E-commerce & Cloud Computing",D44="Electronics & Entertainment",D44="Entertainment & Media",D44="Luxury Goods",D44="Media & Telecommunications",D44="Networking Technology",D44="Real Estate Services",D44="Technology & Consumer Electronics",D44="Telecommunications",D44="Telecommunications & Investment"),1, OR(D44="Asset Management",D44="Banking",D44="Banking & Asset Services",D44="Banking & Financial Services",D44="Banking & Wealth Management",D44="Cloud Software",D44="Enterprise Software",D44="Financial Services",D44="Information Technology Consulting",D44="Investment Banking",D44="Social Media & Technology",D44="Software & Cloud Computing",D44="Technology & Consulting",D44="Technology & Internet Services",D44="Technology & Software"),1, TRUE,"Unmapped" )} -> 1 | H44: 1 | I44: =VLOOKUP(B44,'BIS + EDBA Final'!A:F,6,FALSE) -> 1 | J44: =VLOOKUP(B44,'CBG Final'!A:B,2,FALSE) -> 3 | K44: =0.3*F44+0.2*G44+0.2*H44+I44*0.1+J44*0.2 -> 2 | L44: 145,717 | M44: 8% | N44: 23,979 | O44: 1.9% | P44: 3,017,048 | Q44: 11 | R44: 31
B45: Wells Fargo | C45: United States | D45: Banking | E45: 217502 | F45: {=_xlfn.IFS( E45<=$E$245,0, E45<=$E$246,1, E45<=$E$247,2, E45>=$E$247,3)} -> 3 | G45: {=_xlfn.IFS( OR(D45="Aerospace",D45="Aerospace & Defense",D45="Agricultural Equipment",D45="Airlines",D45="Automotive",D45="Automotive & Energy",D45="Automotive Components",D45="Aviation",D45="Building Materials",D45="Chemicals",D45="Commercial Vehicles",D45="Conglomerate & Defense",D45="Conglomerate & Energy",D45="Construction",D45="Construction & Infrastructure",D45="Construction & Real Estate",D45="Construction & Telecom",D45="Discount Retail",D45="Energy Management",D45="Energy Technology",D45="Engines & Power Systems",D45="Environmental Services",D45="Food Distribution",D45="Food Services",D45="Grocery Retail",D45="Healthcare & Pharmacy",D45="Home Improvement Retail",D45="Industrial Engineering & Electronics",D45="Oilfield Services",D45="Pharmaceuticals",D45="Pharmaceuticals & Chemicals",D45="Pharmaceuticals & Healthcare",D45="Pharmacy Retail",D45="Postal & Logistics",D45="Retail",D45="Retail & Distribution",D45="Retail & Grocery",D45="Retail (IKEA)",D45="Tobacco",D45="Trading & Conglomerate",D45="Utilities",D45="Utilities & Energy",D45="Wholesale Retail"),2, OR(D45="Agribusiness",D45="Automotive & Heavy Vehicles",D45="Chemicals",D45="Commercial Vehicles",D45="Construction",D45="Construction & Infrastructure",D45="Engines & Power Systems",D45="Food Processing",D45="Healthcare",D45="Healthcare & Medical Devices",D45="Heavy Equipment",D45="Heavy Industry",D45="Industrial Gases",D45="Industrial Manufacturing",D45="Logistics",D45="Medical Devices",D45="Mining",D45="Mining & Commodities Trading",D45="Oil & Gas",D45="Oilfield Services",D45="Rail Transport",D45="Shipping & Logistics",D45="Steel"),3, OR(D45="Apparel & Footwear",D45="Beverage",D45="Coffeehouse & Retail",D45="Conglomerate",D45="Consumer Goods",D45="Convenience Retail",D45="Electronics",D45="Electronics & Semiconductors",D45="Electronics Retail",D45="Fashion Retail",D45="Food & Beverage",D45="Food Retail & Consumer Goods",D45="Industrial & Technology",D45="Industrial Automation",D45="Industrial Technology",D45="Postal & Financial Services",D45="Postal Services",D45="Scientific Instruments",D45="Technology Hardware",D45="Trading Company",D45="IT Consulting"),1, OR(D45="Cosmetics",D45="E-commerce & Cloud Computing",D45="Electronics & Entertainment",D45="Entertainment & Media",D45="Luxury Goods",D45="Media & Telecommunications",D45="Networking Technology",D45="Real Estate Services",D45="Technology & Consumer Electronics",D45="Telecommunications",D45="Telecommunications & Investment"),1, OR(D45="Asset Management",D45="Banking",D45="Banking & Asset Services",D45="Banking & Financial Services",D45="Banking & Wealth Management",D45="Cloud Software",D45="Enterprise Software",D45="Financial Services",D45="Information Technology Consulting",D45="Investment Banking",D45="Social Media & Technology",D45="Software & Cloud Computing",D45="Technology & Consulting",D45="Technology & Internet Services",D45="Technology & Software"),1, TRUE,"Unmapped" )} -> 1 | H45: 1 | I45: =VLOOKUP(B45,'BIS + EDBA Final'!A:F,6,FALSE) -> 1 | J45: =VLOOKUP(B45,'CBG Final'!A:B,2,FALSE) -> 3 | K45: =0.3*F45+0.2*G45+0.2*H45+I45*0.1+J45*0.2 -> 2 | L45: 125,397 | M45: 8.7% | N45: 19,722 | O45: 3% | P45: 1,929,845 | Q45: 9 | R45: 28
B46: Emirates Group | C46: United Arab Emirates | D46: Aviation | E46: 121223 | F46: {=_xlfn.IFS( E46<=$E$245,0, E46<=$E$246,1, E46<=$E$247,2, E46>=$E$247,3)} -> 2 | G46: {=_xlfn.IFS( OR(D46="Aerospace",D46="Aerospace & Defense",D46="Agricultural Equipment",D46="Airlines",D46="Automotive",D46="Automotive & Energy",D46="Automotive Components",D46="Aviation",D46="Building Materials",D46="Chemicals",D46="Commercial Vehicles",D46="Conglomerate & Defense",D46="Conglomerate & Energy",D46="Construction",D46="Construction & Infrastructure",D46="Construction & Real Estate",D46="Construction & Telecom",D46="Discount Retail",D46="Energy Management",D46="Energy Technology",D46="Engines & Power Systems",D46="Environmental Services",D46="Food Distribution",D46="Food Services",D46="Grocery Retail",D46="Healthcare & Pharmacy",D46="Home Improvement Retail",D46="Industrial Engineering & Electronics",D46="Oilfield Services",D46="Pharmaceuticals",D46="Pharmaceuticals & Chemicals",D46="Pharmaceuticals & Healthcare",D46="Pharmacy Retail",D46="Postal & Logistics",D46="Retail",D46="Retail & Distribution",D46="Retail & Grocery",D46="Retail (IKEA)",D46="Tobacco",D46="Trading & Conglomerate",D46="Utilities",D46="Utilities & Energy",D46="Wholesale Retail"),2, OR(D46="Agribusiness",D46="Automotive & Heavy Vehicles",D46="Chemicals",D46="Commercial Vehicles",D46="Construction",D46="Construction & Infrastructure",D46="Engines & Power Systems",D46="Food Processing",D46="Healthcare",D46="Healthcare & Medical Devices",D46="Heavy Equipment",D46="Heavy Industry",D46="Industrial Gases",D46="Industrial Manufacturing",D46="Logistics",D46="Medical Devices",D46="Mining",D46="Mining & Commodities Trading",D46="Oil & Gas",D46="Oilfield Services",D46="Rail Transport",D46="Shipping & Logistics",D46="Steel"),3, OR(D46="Apparel & Footwear",D46="Beverage",D46="Coffeehouse & Retail",D46="Conglomerate",D46="Consumer Goods",D46="Convenience Retail",D46="Electronics",D46="Electronics & Semiconductors",D46="Electronics Retail",D46="Fashion Retail",D46="Food & Beverage",D46="Food Retail & Consumer Goods",D46="Industrial & Technology",D46="Industrial Automation",D46="Industrial Technology",D46="Postal & Financial Services",D46="Postal Services",D46="Scientific Instruments",D46="Technology Hardware",D46="Trading Company",D46="IT Consulting"),1, OR(D46="Cosmetics",D46="E-commerce & Cloud Computing",D46="Electronics & Entertainment",D46="Entertainment & Media",D46="Luxury Goods",D46="Media & Telecommunications",D46="Networking Technology",D46="Real Estate Services",D46="Technology & Consumer Electronics",D46="Telecommunications",D46="Telecommunications & Investment"),1, OR(D46="Asset Management",D46="Banking",D46="Banking & Asset Services",D46="Banking & Financial Services",D46="Banking & Wealth Management",D46="Cloud Software",D46="Enterprise Software",D46="Financial Services",D46="Information Technology Consulting",D46="Investment Banking",D46="Social Media & Technology",D46="Software & Cloud Computing",D46="Technology & Consulting",D46="Technology & Internet Services",D46="Technology & Software"),1, TRUE,"Unmapped" )} -> 2 | H46: 2 | I46: =VLOOKUP(B46,'BIS + EDBA Final'!A:F,6,FALSE) -> 0 | J46: =VLOOKUP(B46,'CBG Final'!A:B,2,FALSE) -> 3 | K46: =0.3*F46+0.2*G46+0.2*H46+I46*0.1+J46*0.2 -> 2 | L46: 34,257.9 | M46: 5% | N46: 5,191.2 | O46: 10.6% | P46: 45,739.7 | Q46: 22 | R46: 6
B47: IBM | C47: United States | D47: Technology & Consulting | E47: 284500 | F47: {=_xlfn.IFS( E47<=$E$245,0, E47<=$E$246,1, E47<=$E$247,2, E47>=$E$247,3)} -> 3 | G47: {=_xlfn.IFS( OR(D47="Aerospace",D47="Aerospace & Defense",D47="Agricultural Equipment",D47="Airlines",D47="Automotive",D47="Automotive & Energy",D47="Automotive Components",D47="Aviation",D47="Building Materials",D47="Chemicals",D47="Commercial Vehicles",D47="Conglomerate & Defense",D47="Conglomerate & Energy",D47="Construction",D47="Construction & Infrastructure",D47="Construction & Real Estate",D47="Construction & Telecom",D47="Discount Retail",D47="Energy Management",D47="Energy Technology",D47="Engines & Power Systems",D47="Environmental Services",D47="Food Distribution",D47="Food Services",D47="Grocery Retail",D47="Healthcare & Pharmacy",D47="Home Improvement Retail",D47="Industrial Engineering & Electronics",D47="Oilfield Services",D47="Pharmaceuticals",D47="Pharmaceuticals & Chemicals",D47="Pharmaceuticals & Healthcare",D47="Pharmacy Retail",D47="Postal & Logistics",D47="Retail",D47="Retail & Distribution",D47="Retail & Grocery",D47="Retail (IKEA)",D47="Tobacco",D47="Trading & Conglomerate",D47="Utilities",D47="Utilities & Energy",D47="Wholesale Retail"),2, OR(D47="Agribusiness",D47="Automotive & Heavy Vehicles",D47="Chemicals",D47="Commercial Vehicles",D47="Construction",D47="Construction & Infrastructure",D47="Engines & Power Systems",D47="Food Processing",D47="Healthcare",D47="Healthcare & Medical Devices",D47="Heavy Equipment",D47="Heavy Industry",D47="Industrial Gases",D47="Industrial Manufacturing",D47="Logistics",D47="Medical Devices",D47="Mining",D47="Mining & Commodities Trading",D47="Oil & Gas",D47="Oilfield Services",D47="Rail Transport",D47="Shipping & Logistics",D47="Steel"),3, OR(D47="Apparel & Footwear",D47="Beverage",D47="Coffeehouse & Retail",D47="Conglomerate",D47="Consumer Goods",D47="Convenience Retail",D47="Electronics",D47="Electronics & Semiconductors",D47="Electronics Retail",D47="Fashion Retail",D47="Food & Beverage",D47="Food Retail & Consumer Goods",D47="Industrial & Technology",D47="Industrial Automation",D47="Industrial Technology",D47="Postal & Financial Services",D47="Postal Services",D47="Scientific Instruments",D47="Technology Hardware",D47="Trading Company",D47="IT Consulting"),1, OR(D47="Cosmetics",D47="E-commerce & Cloud Computing",D47="Electronics & Entertainment",D47="Entertainment & Media",D47="Luxury Goods",D47="Media & Telecommunications",D47="Networking Technology",D47="Real Estate Services",D47="Technology & Consumer Electronics",D47="Telecommunications",D47="Telecommunications & Investment"),1, OR(D47="Asset Management",D47="Banking",D47="Banking & Asset Services",D47="Banking & Financial Services",D47="Banking & Wealth Management",D47="Cloud Software",D47="Enterprise Software",D47="Financial Services",D47="Information Technology Consulting",D47="Investment Banking",D47="Social Media & Technology",D47="Software & Cloud Computing",D47="Technology & Consulting",D47="Technology & Internet Services",D47="Technology & Software"),1, TRUE,"Unmapped" )} -> 1 | H47: 2 | I47: =VLOOKUP(B47,'BIS + EDBA Final'!A:F,6,FALSE) -> -1 | J47: =VLOOKUP(B47,'CBG Final'!A:B,2,FALSE) -> 3 | K47: =0.3*F47+0.2*G47+0.2*H47+I47*0.1+J47*0.2 -> 2 | L47: 62,753 | M47: 1.4% | N47: 6,023 | O47: -19.7% | P47: 137,175 | Q47: -2 | R47: 31
B48: Edeka Zentrale | C48: Germany | D48: Grocery Retail | E48: 413000 | F48: {=_xlfn.IFS( E48<=$E$245,0, E48<=$E$246,1, E48<=$E$247,2, E48>=$E$247,3)} -> 3 | G48: {=_xlfn.IFS( OR(D48="Aerospace",D48="Aerospace & Defense",D48="Agricultural Equipment",D48="Airlines",D48="Automotive",D48="Automotive & Energy",D48="Automotive Components",D48="Aviation",D48="Building Materials",D48="Chemicals",D48="Commercial Vehicles",D48="Conglomerate & Defense",D48="Conglomerate & Energy",D48="Construction",D48="Construction & Infrastructure",D48="Construction & Real Estate",D48="Construction & Telecom",D48="Discount Retail",D48="Energy Management",D48="Energy Technology",D48="Engines & Power Systems",D48="Environmental Services",D48="Food Distribution",D48="Food Services",D48="Grocery Retail",D48="Healthcare & Pharmacy",D48="Home Improvement Retail",D48="Industrial Engineering & Electronics",D48="Oilfield Services",D48="Pharmaceuticals",D48="Pharmaceuticals & Chemicals",D48="Pharmaceuticals & Healthcare",D48="Pharmacy Retail",D48="Postal & Logistics",D48="Retail",D48="Retail & Distribution",D48="Retail & Grocery",D48="Retail (IKEA)",D48="Tobacco",D48="Trading & Conglomerate",D48="Utilities",D48="Utilities & Energy",D48="Wholesale Retail"),2, OR(D48="Agribusiness",D48="Automotive & Heavy Vehicles",D48="Chemicals",D48="Commercial Vehicles",D48="Construction",D48="Construction & Infrastructure",D48="Engines & Power Systems",D48="Food Processing",D48="Healthcare",D48="Healthcare & Medical Devices",D48="Heavy Equipment",D48="Heavy Industry",D48="Industrial Gases",D48="Industrial Manufacturing",D48="Logistics",D48="Medical Devices",D48="Mining",D48="Mining & Commodities Trading",D48="Oil & Gas",D48="Oilfield Services",D48="Rail Transport",D48="Shipping & Logistics",D48="Steel"),3, OR(D48="Apparel & Footwear",D48="Beverage",D48="Coffeehouse & Retail",D48="Conglomerate",D48="Consumer Goods",D48="Convenience Retail",D48="Electronics",D48="Electronics & Semiconductors",D48="Electronics Retail",D48="Fashion Retail",D48="Food & Beverage",D48="Food Retail & Consumer Goods",D48="Industrial & Technology",D48="Industrial Automation",D48="Industrial Technology",D48="Postal & Financial Services",D48="Postal Services",D48="Scientific Instruments",D48="Technology Hardware",D48="Trading Company",D48="IT Consulting"),1, OR(D48="Cosmetics",D48="E-commerce & Cloud Computing",D48="Electronics & Entertainment",D48="Entertainment & Media",D48="Luxury Goods",D48="Media & Telecommunications",D48="Networking Technology",D48="Real Estate Services",D48="Technology & Consumer Electronics",D48="Telecommunications",D48="Telecommunications & Investment"),1, OR(D48="Asset Management",D48="Banking",D48="Banking & Asset Services",D48="Banking & Financial Services",D48="Banking & Wealth Management",D48="Cloud Software",D48="Enterprise Software",D48="Financial Services",D48="Information Technology Consulting",D48="Investment Banking",D48="Social Media & Technology",D48="Software & Cloud Computing",D48="Technology & Consulting",D48="Technology & Internet Services",D48="Technology & Software"),1, TRUE,"Unmapped" )} -> 2 | H48: 2 | I48: =VLOOKUP(B48,'BIS + EDBA Final'!A:F,6,FALSE) -> 1 | J48: =VLOOKUP(B48,'CBG Final'!A:B,2,FALSE) -> 1 | K48: =0.3*F48+0.2*G48+0.2*H48+I48*0.1+J48*0.2 -> 2 | L48: 58,493.6 | M48: 7.4% | N48: 379.8 | O48: -3.7% | P48: 11,845.1 | Q48: 20 | R48: 27
B49: Shell | C49: United Kingdom | D49: Oil & Gas | E49: 96000 | F49: {=_xlfn.IFS( E49<=$E$245,0, E49<=$E$246,1, E49<=$E$247,2, E49>=$E$247,3)} -> 1 | G49: {=_xlfn.IFS( OR(D49="Aerospace",D49="Aerospace & Defense",D49="Agricultural Equipment",D49="Airlines",D49="Automotive",D49="Automotive & Energy",D49="Automotive Components",D49="Aviation",D49="Building Materials",D49="Chemicals",D49="Commercial Vehicles",D49="Conglomerate & Defense",D49="Conglomerate & Energy",D49="Construction",D49="Construction & Infrastructure",D49="Construction & Real Estate",D49="Construction & Telecom",D49="Discount Retail",D49="Energy Management",D49="Energy Technology",D49="Engines & Power Systems",D49="Environmental Services",D49="Food Distribution",D49="Food Services",D49="Grocery Retail",D49="Healthcare & Pharmacy",D49="Home Improvement Retail",D49="Industrial Engineering & Electronics",D49="Oilfield Services",D49="Pharmaceuticals",D49="Pharmaceuticals & Chemicals",D49="Pharmaceuticals & Healthcare",D49="Pharmacy Retail",D49="Postal & Logistics",D49="Retail",D49="Retail & Distribution",D49="Retail & Grocery",D49="Retail (IKEA)",D49="Tobacco",D49="Trading & Conglomerate",D49="Utilities",D49="Utilities & Energy",D49="Wholesale Retail"),2, OR(D49="Agribusiness",D49="Automotive & Heavy Vehicles",D49="Chemicals",D49="Commercial Vehicles",D49="Construction",D49="Construction & Infrastructure",D49="Engines & Power Systems",D49="Food Processing",D49="Healthcare",D49="Healthcare & Medical Devices",D49="Heavy Equipment",D49="Heavy Industry",D49="Industrial Gases",D49="Industrial Manufacturing",D49="Logistics",D49="Medical Devices",D49="Mining",D49="Mining & Commodities Trading",D49="Oil & Gas",D49="Oilfield Services",D49="Rail Transport",D49="Shipping & Logistics",D49="Steel"),3, OR(D49="Apparel & Footwear",D49="Beverage",D49="Coffeehouse & Retail",D49="Conglomerate",D49="Consumer Goods",D49="Convenience Retail",D49="Electronics",D49="Electronics & Semiconductors",D49="Electronics Retail",D49="Fashion Retail",D49="Food & Beverage",D49="Food Retail & Consumer Goods",D49="Industrial & Technology",D49="Industrial Automation",D49="Industrial Technology",D49="Postal & Financial Services",D49="Postal Services",D49="Scientific Instruments",D49="Technology Hardware",D49="Trading Company",D49="IT Consulting"),1, OR(D49="Cosmetics",D49="E-commerce & Cloud Computing",D49="Electronics & Entertainment",D49="Entertainment & Media",D49="Luxury Goods",D49="Media & Telecommunications",D49="Networking Technology",D49="Real Estate Services",D49="Technology & Consumer Electronics",D49="Telecommunications",D49="Telecommunications & Investment"),1, OR(D49="Asset Management",D49="Banking",D49="Banking & Asset Services",D49="Banking & Financial Services",D49="Banking & Wealth Management",D49="Cloud Software",D49="Enterprise Software",D49="Financial Services",D49="Information Technology Consulting",D49="Investment Banking",D49="Social Media & Technology",D49="Software & Cloud Computing",D49="Technology & Consulting",D49="Technology & Internet Services",D49="Technology & Software"),1, TRUE,"Unmapped" )} -> 3 | H49: =VLOOKUP(B49,'BIS + EDBA Final'!A:K,2,FALSE) -> 2 | I49: =VLOOKUP(B49,'BIS + EDBA Final'!A:F,6,FALSE) -> 0 | J49: =VLOOKUP(B49,'CBG Final'!A:B,2,FALSE) -> 3 | K49: =0.3*F49+0.2*G49+0.2*H49+I49*0.1+J49*0.2 -> 1.9 | L49: 289,029 | M49: -10.6% | N49: 16,094 | O49: -16.9% | P49: 387,609 | Q49: -5 | R49: 31
B50: Comcast | C50: United States | D50: Media & Telecommunications | E50: 182000 | F50: {=_xlfn.IFS( E50<=$E$245,0, E50<=$E$246,1, E50<=$E$247,2, E50>=$E$247,3)} -> 2 | G50: {=_xlfn.IFS( OR(D50="Aerospace",D50="Aerospace & Defense",D50="Agricultural Equipment",D50="Airlines",D50="Automotive",D50="Automotive & Energy",D50="Automotive Components",D50="Aviation",D50="Building Materials",D50="Chemicals",D50="Commercial Vehicles",D50="Conglomerate & Defense",D50="Conglomerate & Energy",D50="Construction",D50="Construction & Infrastructure",D50="Construction & Real Estate",D50="Construction & Telecom",D50="Discount Retail",D50="Energy Management",D50="Energy Technology",D50="Engines & Power Systems",D50="Environmental Services",D50="Food Distribution",D50="Food Services",D50="Grocery Retail",D50="Healthcare & Pharmacy",D50="Home Improvement Retail",D50="Industrial Engineering & Electronics",D50="Oilfield Services",D50="Pharmaceuticals",D50="Pharmaceuticals & Chemicals",D50="Pharmaceuticals & Healthcare",D50="Pharmacy Retail",D50="Postal & Logistics",D50="Retail",D50="Retail & Distribution",D50="Retail & Grocery",D50="Retail (IKEA)",D50="Tobacco",D50="Trading & Conglomerate",D50="Utilities",D50="Utilities & Energy",D50="Wholesale Retail"),2, OR(D50="Agribusiness",D50="Automotive & Heavy Vehicles",D50="Chemicals",D50="Commercial Vehicles",D50="Construction",D50="Construction & Infrastructure",D50="Engines & Power Systems",D50="Food Processing",D50="Healthcare",D50="Healthcare & Medical Devices",D50="Heavy Equipment",D50="Heavy Industry",D50="Industrial Gases",D50="Industrial Manufacturing",D50="Logistics",D50="Medical Devices",D50="Mining",D50="Mining & Commodities Trading",D50="Oil & Gas",D50="Oilfield Services",D50="Rail Transport",D50="Shipping & Logistics",D50="Steel"),3, OR(D50="Apparel & Footwear",D50="Beverage",D50="Coffeehouse & Retail",D50="Conglomerate",D50="Consumer Goods",D50="Convenience Retail",D50="Electronics",D50="Electronics & Semiconductors",D50="Electronics Retail",D50="Fashion Retail",D50="Food & Beverage",D50="Food Retail & Consumer Goods",D50="Industrial & Technology",D50="Industrial Automation",D50="Industrial Technology",D50="Postal & Financial Services",D50="Postal Services",D50="Scientific Instruments",D50="Technology Hardware",D50="Trading Company",D50="IT Consulting"),1, OR(D50="Cosmetics",D50="E-commerce & Cloud Computing",D50="Electronics & Entertainment",D50="Entertainment & Media",D50="Luxury Goods",D50="Media & Telecommunications",D50="Networking Technology",D50="Real Estate Services",D50="Technology & Consumer Electronics",D50="Telecommunications",D50="Telecommunications & Investment"),1, OR(D50="Asset Management",D50="Banking",D50="Banking & Asset Services",D50="Banking & Financial Services",D50="Banking & Wealth Management",D50="Cloud Software",D50="Enterprise Software",D50="Financial Services",D50="Information Technology Consulting",D50="Investment Banking",D50="Social Media & Technology",D50="Software & Cloud Computing",D50="Technology & Consulting",D50="Technology & Internet Services",D50="Technology & Software"),1, TRUE,"Unmapped" )} -> 1 | H50: 2 | I50: =VLOOKUP(B50,'BIS + EDBA Final'!A:F,6,FALSE) -> 1 | J50: =VLOOKUP(B50,'CBG Final'!A:B,2,FALSE) -> 3 | K50: =0.3*F50+0.2*G50+0.2*H50+I50*0.1+J50*0.2 -> 1.9 | L50: 123,731 | M50: 1.8% | N50: 16,192 | O50: 5.2% | P50: 266,211 | Q50: 1 | R50: 23
B51: Société Générale | C51: France | D51: Banking | E51: 114139 | F51: {=_xlfn.IFS( E51<=$E$245,0, E51<=$E$246,1, E51<=$E$247,2, E51>=$E$247,3)} -> 2 | G51: {=_xlfn.IFS( OR(D51="Aerospace",D51="Aerospace & Defense",D51="Agricultural Equipment",D51="Airlines",D51="Automotive",D51="Automotive & Energy",D51="Automotive Components",D51="Aviation",D51="Building Materials",D51="Chemicals",D51="Commercial Vehicles",D51="Conglomerate & Defense",D51="Conglomerate & Energy",D51="Construction",D51="Construction & Infrastructure",D51="Construction & Real Estate",D51="Construction & Telecom",D51="Discount Retail",D51="Energy Management",D51="Energy Technology",D51="Engines & Power Systems",D51="Environmental Services",D51="Food Distribution",D51="Food Services",D51="Grocery Retail",D51="Healthcare & Pharmacy",D51="Home Improvement Retail",D51="Industrial Engineering & Electronics",D51="Oilfield Services",D51="Pharmaceuticals",D51="Pharmaceuticals & Chemicals",D51="Pharmaceuticals & Healthcare",D51="Pharmacy Retail",D51="Postal & Logistics",D51="Retail",D51="Retail & Distribution",D51="Retail & Grocery",D51="Retail (IKEA)",D51="Tobacco",D51="Trading & Conglomerate",D51="Utilities",D51="Utilities & Energy",D51="Wholesale Retail"),2, OR(D51="Agribusiness",D51="Automotive & Heavy Vehicles",D51="Chemicals",D51="Commercial Vehicles",D51="Construction",D51="Construction & Infrastructure",D51="Engines & Power Systems",D51="Food Processing",D51="Healthcare",D51="Healthcare & Medical Devices",D51="Heavy Equipment",D51="Heavy Industry",D51="Industrial Gases",D51="Industrial Manufacturing",D51="Logistics",D51="Medical Devices",D51="Mining",D51="Mining & Commodities Trading",D51="Oil & Gas",D51="Oilfield Services",D51="Rail Transport",D51="Shipping & Logistics",D51="Steel"),3, OR(D51="Apparel & Footwear",D51="Beverage",D51="Coffeehouse & Retail",D51="Conglomerate",D51="Consumer Goods",D51="Convenience Retail",D51="Electronics",D51="Electronics & Semiconductors",D51="Electronics Retail",D51="Fashion Retail",D51="Food & Beverage",D51="Food Retail & Consumer Goods",D51="Industrial & Technology",D51="Industrial Automation",D51="Industrial Technology",D51="Postal & Financial Services",D51="Postal Services",D51="Scientific Instruments",D51="Technology Hardware",D51="Trading Company",D51="IT Consulting"),1, OR(D51="Cosmetics",D51="E-commerce & Cloud Computing",D51="Electronics & Entertainment",D51="Entertainment & Media",D51="Luxury Goods",D51="Media & Telecommunications",D51="Networking Technology",D51="Real Estate Services",D51="Technology & Consumer Electronics",D51="Telecommunications",D51="Telecommunications & Investment"),1, OR(D51="Asset Management",D51="Banking",D51="Banking & Asset Services",D51="Banking & Financial Services",D51="Banking & Wealth Management",D51="Cloud Software",D51="Enterprise Software",D51="Financial Services",D51="Information Technology Consulting",D51="Investment Banking",D51="Social Media & Technology",D51="Software & Cloud Computing",D51="Technology & Consulting",D51="Technology & Internet Services",D51="Technology & Software"),1, TRUE,"Unmapped" )} -> 1 | H51: 2 | I51: =VLOOKUP(B51,'BIS + EDBA Final'!A:F,6,FALSE) -> 1 | J51: =VLOOKUP(B51,'CBG Final'!A:B,2,FALSE) -> 3 | K51: =0.3*F51+0.2*G51+0.2*H51+I51*0.1+J51*0.2 -> 1.9 | L51: 110,647.8 | M51: 11.6% | N51: 4,542 | O51: 68.5% | P51: 1,629,265.9 | Q51: 15 | R51: 29
B52: TotalEnergies | C52: France | D52: Oil & Gas | E52: 102887 | F52: {=_xlfn.IFS( E52<=$E$245,0, E52<=$E$246,1, E52<=$E$247,2, E52>=$E$247,3)} -> 1 | G52: {=_xlfn.IFS( OR(D52="Aerospace",D52="Aerospace & Defense",D52="Agricultural Equipment",D52="Airlines",D52="Automotive",D52="Automotive & Energy",D52="Automotive Components",D52="Aviation",D52="Building Materials",D52="Chemicals",D52="Commercial Vehicles",D52="Conglomerate & Defense",D52="Conglomerate & Energy",D52="Construction",D52="Construction & Infrastructure",D52="Construction & Real Estate",D52="Construction & Telecom",D52="Discount Retail",D52="Energy Management",D52="Energy Technology",D52="Engines & Power Systems",D52="Environmental Services",D52="Food Distribution",D52="Food Services",D52="Grocery Retail",D52="Healthcare & Pharmacy",D52="Home Improvement Retail",D52="Industrial Engineering & Electronics",D52="Oilfield Services",D52="Pharmaceuticals",D52="Pharmaceuticals & Chemicals",D52="Pharmaceuticals & Healthcare",D52="Pharmacy Retail",D52="Postal & Logistics",D52="Retail",D52="Retail & Distribution",D52="Retail & Grocery",D52="Retail (IKEA)",D52="Tobacco",D52="Trading & Conglomerate",D52="Utilities",D52="Utilities & Energy",D52="Wholesale Retail"),2, OR(D52="Agribusiness",D52="Automotive & Heavy Vehicles",D52="Chemicals",D52="Commercial Vehicles",D52="Construction",D52="Construction & Infrastructure",D52="Engines & Power Systems",D52="Food Processing",D52="Healthcare",D52="Healthcare & Medical Devices",D52="Heavy Equipment",D52="Heavy Industry",D52="Industrial Gases",D52="Industrial Manufacturing",D52="Logistics",D52="Medical Devices",D52="Mining",D52="Mining & Commodities Trading",D52="Oil & Gas",D52="Oilfield Services",D52="Rail Transport",D52="Shipping & Logistics",D52="Steel"),3, OR(D52="Apparel & Footwear",D52="Beverage",D52="Coffeehouse & Retail",D52="Conglomerate",D52="Consumer Goods",D52="Convenience Retail",D52="Electronics",D52="Electronics & Semiconductors",D52="Electronics Retail",D52="Fashion Retail",D52="Food & Beverage",D52="Food Retail & Consumer Goods",D52="Industrial & Technology",D52="Industrial Automation",D52="Industrial Technology",D52="Postal & Financial Services",D52="Postal Services",D52="Scientific Instruments",D52="Technology Hardware",D52="Trading Company",D52="IT Consulting"),1, OR(D52="Cosmetics",D52="E-commerce & Cloud Computing",D52="Electronics & Entertainment",D52="Entertainment & Media",D52="Luxury Goods",D52="Media & Telecommunications",D52="Networking Technology",D52="Real Estate Services",D52="Technology & Consumer Electronics",D52="Telecommunications",D52="Telecommunications & Investment"),1, OR(D52="Asset Management",D52="Banking",D52="Banking & Asset Services",D52="Banking & Financial Services",D52="Banking & Wealth Management",D52="Cloud Software",D52="Enterprise Software",D52="Financial Services",D52="Information Technology Consulting",D52="Investment Banking",D52="Social Media & Technology",D52="Software & Cloud Computing",D52="Technology & Consulting",D52="Technology & Internet Services",D52="Technology & Software"),1, TRUE,"Unmapped" )} -> 3 | H52: =VLOOKUP(B52,'BIS + EDBA Final'!A:K,2,FALSE) -> 2 | I52: =VLOOKUP(B52,'BIS + EDBA Final'!A:F,6,FALSE) -> 0 | J52: =VLOOKUP(B52,'CBG Final'!A:B,2,FALSE) -> 3 | K52: =0.3*F52+0.2*G52+0.2*H52+I52*0.1+J52*0.2 -> 1.9 | L52: 195,610 | M52: -10.7% | N52: 15,758 | O52: -26.3% | P52: 285,487 | Q52: -9 | R52: 31
B53: Anheuser-Busch InBev | C53: Belgium | D53: Beverage | E53: 143885 | F53: {=_xlfn.IFS( E53<=$E$245,0, E53<=$E$246,1, E53<=$E$247,2, E53>=$E$247,3)} -> 2 | G53: {=_xlfn.IFS( OR(D53="Aerospace",D53="Aerospace & Defense",D53="Agricultural Equipment",D53="Airlines",D53="Automotive",D53="Automotive & Energy",D53="Automotive Components",D53="Aviation",D53="Building Materials",D53="Chemicals",D53="Commercial Vehicles",D53="Conglomerate & Defense",D53="Conglomerate & Energy",D53="Construction",D53="Construction & Infrastructure",D53="Construction & Real Estate",D53="Construction & Telecom",D53="Discount Retail",D53="Energy Management",D53="Energy Technology",D53="Engines & Power Systems",D53="Environmental Services",D53="Food Distribution",D53="Food Services",D53="Grocery Retail",D53="Healthcare & Pharmacy",D53="Home Improvement Retail",D53="Industrial Engineering & Electronics",D53="Oilfield Services",D53="Pharmaceuticals",D53="Pharmaceuticals & Chemicals",D53="Pharmaceuticals & Healthcare",D53="Pharmacy Retail",D53="Postal & Logistics",D53="Retail",D53="Retail & Distribution",D53="Retail & Grocery",D53="Retail (IKEA)",D53="Tobacco",D53="Trading & Conglomerate",D53="Utilities",D53="Utilities & Energy",D53="Wholesale Retail"),2, OR(D53="Agribusiness",D53="Automotive & Heavy Vehicles",D53="Chemicals",D53="Commercial Vehicles",D53="Construction",D53="Construction & Infrastructure",D53="Engines & Power Systems",D53="Food Processing",D53="Healthcare",D53="Healthcare & Medical Devices",D53="Heavy Equipment",D53="Heavy Industry",D53="Industrial Gases",D53="Industrial Manufacturing",D53="Logistics",D53="Medical Devices",D53="Mining",D53="Mining & Commodities Trading",D53="Oil & Gas",D53="Oilfield Services",D53="Rail Transport",D53="Shipping & Logistics",D53="Steel"),3, OR(D53="Apparel & Footwear",D53="Beverage",D53="Coffeehouse & Retail",D53="Conglomerate",D53="Consumer Goods",D53="Convenience Retail",D53="Electronics",D53="Electronics & Semiconductors",D53="Electronics Retail",D53="Fashion Retail",D53="Food & Beverage",D53="Food Retail & Consumer Goods",D53="Industrial & Technology",D53="Industrial Automation",D53="Industrial Technology",D53="Postal & Financial Services",D53="Postal Services",D53="Scientific Instruments",D53="Technology Hardware",D53="Trading Company",D53="IT Consulting"),1, OR(D53="Cosmetics",D53="E-commerce & Cloud Computing",D53="Electronics & Entertainment",D53="Entertainment & Media",D53="Luxury Goods",D53="Media & Telecommunications",D53="Networking Technology",D53="Real Estate Services",D53="Technology & Consumer Electronics",D53="Telecommunications",D53="Telecommunications & Investment"),1, OR(D53="Asset Management",D53="Banking",D53="Banking & Asset Services",D53="Banking & Financial Services",D53="Banking & Wealth Management",D53="Cloud Software",D53="Enterprise Software",D53="Financial Services",D53="Information Technology Consulting",D53="Investment Banking",D53="Social Media & Technology",D53="Software & Cloud Computing",D53="Technology & Consulting",D53="Technology & Internet Services",D53="Technology & Software"),1, TRUE,"Unmapped" )} -> 1 | H53: 2 | I53: =VLOOKUP(B53,'BIS + EDBA Final'!A:F,6,FALSE) -> 1 | J53: =VLOOKUP(B53,'CBG Final'!A:B,2,FALSE) -> 3 | K53: =0.3*F53+0.2*G53+0.2*H53+I53*0.1+J53*0.2 -> 1.9 | L53: 59,768 | M53: 0.7% | N53: 5,855 | O53: 9.6% | P53: 206,637 | Q53: -1 | R53: 20
B54: Volvo | C54: Sweden | D54: Automotive & Heavy Vehicles | E54: 92690 | F54: {=_xlfn.IFS( E54<=$E$245,0, E54<=$E$246,1, E54<=$E$247,2, E54>=$E$247,3)} -> 1 | G54: {=_xlfn.IFS( OR(D54="Aerospace",D54="Aerospace & Defense",D54="Agricultural Equipment",D54="Airlines",D54="Automotive",D54="Automotive & Energy",D54="Automotive Components",D54="Aviation",D54="Building Materials",D54="Chemicals",D54="Commercial Vehicles",D54="Conglomerate & Defense",D54="Conglomerate & Energy",D54="Construction",D54="Construction & Infrastructure",D54="Construction & Real Estate",D54="Construction & Telecom",D54="Discount Retail",D54="Energy Management",D54="Energy Technology",D54="Engines & Power Systems",D54="Environmental Services",D54="Food Distribution",D54="Food Services",D54="Grocery Retail",D54="Healthcare & Pharmacy",D54="Home Improvement Retail",D54="Industrial Engineering & Electronics",D54="Oilfield Services",D54="Pharmaceuticals",D54="Pharmaceuticals & Chemicals",D54="Pharmaceuticals & Healthcare",D54="Pharmacy Retail",D54="Postal & Logistics",D54="Retail",D54="Retail & Distribution",D54="Retail & Grocery",D54="Retail (IKEA)",D54="Tobacco",D54="Trading & Conglomerate",D54="Utilities",D54="Utilities & Energy",D54="Wholesale Retail"),2, OR(D54="Agribusiness",D54="Automotive & Heavy Vehicles",D54="Chemicals",D54="Commercial Vehicles",D54="Construction",D54="Construction & Infrastructure",D54="Engines & Power Systems",D54="Food Processing",D54="Healthcare",D54="Healthcare & Medical Devices",D54="Heavy Equipment",D54="Heavy Industry",D54="Industrial Gases",D54="Industrial Manufacturing",D54="Logistics",D54="Medical Devices",D54="Mining",D54="Mining & Commodities Trading",D54="Oil & Gas",D54="Oilfield Services",D54="Rail Transport",D54="Shipping & Logistics",D54="Steel"),3, OR(D54="Apparel & Footwear",D54="Beverage",D54="Coffeehouse & Retail",D54="Conglomerate",D54="Consumer Goods",D54="Convenience Retail",D54="Electronics",D54="Electronics & Semiconductors",D54="Electronics Retail",D54="Fashion Retail",D54="Food & Beverage",D54="Food Retail & Consumer Goods",D54="Industrial & Technology",D54="Industrial Automation",D54="Industrial Technology",D54="Postal & Financial Services",D54="Postal Services",D54="Scientific Instruments",D54="Technology Hardware",D54="Trading Company",D54="IT Consulting"),1, OR(D54="Cosmetics",D54="E-commerce & Cloud Computing",D54="Electronics & Entertainment",D54="Entertainment & Media",D54="Luxury Goods",D54="Media & Telecommunications",D54="Networking Technology",D54="Real Estate Services",D54="Technology & Consumer Electronics",D54="Telecommunications",D54="Telecommunications & Investment"),1, OR(D54="Asset Management",D54="Banking",D54="Banking & Asset Services",D54="Banking & Financial Services",D54="Banking & Wealth Management",D54="Cloud Software",D54="Enterprise Software",D54="Financial Services",D54="Information Technology Consulting",D54="Investment Banking",D54="Social Media & Technology",D54="Software & Cloud Computing",D54="Technology & Consulting",D54="Technology & Internet Services",D54="Technology & Software"),1, TRUE,"Unmapped" )} -> 3 | H54: 2 | I54: =VLOOKUP(B54,'BIS + EDBA Final'!A:F,6,FALSE) -> 0 | J54: =VLOOKUP(B54,'CBG Final'!A:B,2,FALSE) -> 3 | K54: =0.3*F54+0.2*G54+0.2*H54+I54*0.1+J54*0.2 -> 1.9 | L54: 49,826.5 | M54: -4.4% | N54: 4,765.8 | O54: 1.5% | P54: 64,681.6 | Q54: -25 | R54: 31
B55: American Airlines Group | C55: United States | D55: Airlines | E55: 133300 | F55: {=_xlfn.IFS( E55<=$E$245,0, E55<=$E$246,1, E55<=$E$247,2, E55>=$E$247,3)} -> 2 | G55: {=_xlfn.IFS( OR(D55="Aerospace",D55="Aerospace & Defense",D55="Agricultural Equipment",D55="Airlines",D55="Automotive",D55="Automotive & Energy",D55="Automotive Components",D55="Aviation",D55="Building Materials",D55="Chemicals",D55="Commercial Vehicles",D55="Conglomerate & Defense",D55="Conglomerate & Energy",D55="Construction",D55="Construction & Infrastructure",D55="Construction & Real Estate",D55="Construction & Telecom",D55="Discount Retail",D55="Energy Management",D55="Energy Technology",D55="Engines & Power Systems",D55="Environmental Services",D55="Food Distribution",D55="Food Services",D55="Grocery Retail",D55="Healthcare & Pharmacy",D55="Home Improvement Retail",D55="Industrial Engineering & Electronics",D55="Oilfield Services",D55="Pharmaceuticals",D55="Pharmaceuticals & Chemicals",D55="Pharmaceuticals & Healthcare",D55="Pharmacy Retail",D55="Postal & Logistics",D55="Retail",D55="Retail & Distribution",D55="Retail & Grocery",D55="Retail (IKEA)",D55="Tobacco",D55="Trading & Conglomerate",D55="Utilities",D55="Utilities & Energy",D55="Wholesale Retail"),2, OR(D55="Agribusiness",D55="Automotive & Heavy Vehicles",D55="Chemicals",D55="Commercial Vehicles",D55="Construction",D55="Construction & Infrastructure",D55="Engines & Power Systems",D55="Food Processing",D55="Healthcare",D55="Healthcare & Medical Devices",D55="Heavy Equipment",D55="Heavy Industry",D55="Industrial Gases",D55="Industrial Manufacturing",D55="Logistics",D55="Medical Devices",D55="Mining",D55="Mining & Commodities Trading",D55="Oil & Gas",D55="Oilfield Services",D55="Rail Transport",D55="Shipping & Logistics",D55="Steel"),3, OR(D55="Apparel & Footwear",D55="Beverage",D55="Coffeehouse & Retail",D55="Conglomerate",D55="Consumer Goods",D55="Convenience Retail",D55="Electronics",D55="Electronics & Semiconductors",D55="Electronics Retail",D55="Fashion Retail",D55="Food & Beverage",D55="Food Retail & Consumer Goods",D55="Industrial & Technology",D55="Industrial Automation",D55="Industrial Technology",D55="Postal & Financial Services",D55="Postal Services",D55="Scientific Instruments",D55="Technology Hardware",D55="Trading Company",D55="IT Consulting"),1, OR(D55="Cosmetics",D55="E-commerce & Cloud Computing",D55="Electronics & Entertainment",D55="Entertainment & Media",D55="Luxury Goods",D55="Media & Telecommunications",D55="Networking Technology",D55="Real Estate Services",D55="Technology & Consumer Electronics",D55="Telecommunications",D55="Telecommunications & Investment"),1, OR(D55="Asset Management",D55="Banking",D55="Banking & Asset Services",D55="Banking & Financial Services",D55="Banking & Wealth Management",D55="Cloud Software",D55="Enterprise Software",D55="Financial Services",D55="Information Technology Consulting",D55="Investment Banking",D55="Social Media & Technology",D55="Software & Cloud Computing",D55="Technology & Consulting",D55="Technology & Internet Services",D55="Technology & Software"),1, TRUE,"Unmapped" )} -> 2 | H55: 1 | I55: =VLOOKUP(B55,'BIS + EDBA Final'!A:F,6,FALSE) -> 1 | J55: =VLOOKUP(B55,'CBG Final'!A:B,2,FALSE) -> 3 | K55: =0.3*F55+0.2*G55+0.2*H55+I55*0.1+J55*0.2 -> 1.9 | L55: 54,211 | M55: 2.7% | N55: 846 | O55: 2.9% | P55: 61,783 | Q55: 10 | R55: 30
B56: Tesla | C56: United States | D56: Automotive & Energy | E56: 125665 | F56: {=_xlfn.IFS( E56<=$E$245,0, E56<=$E$246,1, E56<=$E$247,2, E56>=$E$247,3)} -> 2 | G56: {=_xlfn.IFS( OR(D56="Aerospace",D56="Aerospace & Defense",D56="Agricultural Equipment",D56="Airlines",D56="Automotive",D56="Automotive & Energy",D56="Automotive Components",D56="Aviation",D56="Building Materials",D56="Chemicals",D56="Commercial Vehicles",D56="Conglomerate & Defense",D56="Conglomerate & Energy",D56="Construction",D56="Construction & Infrastructure",D56="Construction & Real Estate",D56="Construction & Telecom",D56="Discount Retail",D56="Energy Management",D56="Energy Technology",D56="Engines & Power Systems",D56="Environmental Services",D56="Food Distribution",D56="Food Services",D56="Grocery Retail",D56="Healthcare & Pharmacy",D56="Home Improvement Retail",D56="Industrial Engineering & Electronics",D56="Oilfield Services",D56="Pharmaceuticals",D56="Pharmaceuticals & Chemicals",D56="Pharmaceuticals & Healthcare",D56="Pharmacy Retail",D56="Postal & Logistics",D56="Retail",D56="Retail & Distribution",D56="Retail & Grocery",D56="Retail (IKEA)",D56="Tobacco",D56="Trading & Conglomerate",D56="Utilities",D56="Utilities & Energy",D56="Wholesale Retail"),2, OR(D56="Agribusiness",D56="Automotive & Heavy Vehicles",D56="Chemicals",D56="Commercial Vehicles",D56="Construction",D56="Construction & Infrastructure",D56="Engines & Power Systems",D56="Food Processing",D56="Healthcare",D56="Healthcare & Medical Devices",D56="Heavy Equipment",D56="Heavy Industry",D56="Industrial Gases",D56="Industrial Manufacturing",D56="Logistics",D56="Medical Devices",D56="Mining",D56="Mining & Commodities Trading",D56="Oil & Gas",D56="Oilfield Services",D56="Rail Transport",D56="Shipping & Logistics",D56="Steel"),3, OR(D56="Apparel & Footwear",D56="Beverage",D56="Coffeehouse & Retail",D56="Conglomerate",D56="Consumer Goods",D56="Convenience Retail",D56="Electronics",D56="Electronics & Semiconductors",D56="Electronics Retail",D56="Fashion Retail",D56="Food & Beverage",D56="Food Retail & Consumer Goods",D56="Industrial & Technology",D56="Industrial Automation",D56="Industrial Technology",D56="Postal & Financial Services",D56="Postal Services",D56="Scientific Instruments",D56="Technology Hardware",D56="Trading Company",D56="IT Consulting"),1, OR(D56="Cosmetics",D56="E-commerce & Cloud Computing",D56="Electronics & Entertainment",D56="Entertainment & Media",D56="Luxury Goods",D56="Media & Telecommunications",D56="Networking Technology",D56="Real Estate Services",D56="Technology & Consumer Electronics",D56="Telecommunications",D56="Telecommunications & Investment"),1, OR(D56="Asset Management",D56="Banking",D56="Banking & Asset Services",D56="Banking & Financial Services",D56="Banking & Wealth Management",D56="Cloud Software",D56="Enterprise Software",D56="Financial Services",D56="Information Technology Consulting",D56="Investment Banking",D56="Social Media & Technology",D56="Software & Cloud Computing",D56="Technology & Consulting",D56="Technology & Internet Services",D56="Technology & Software"),1, TRUE,"Unmapped" )} -> 2 | H56: 1 | I56: =VLOOKUP(B56,'BIS + EDBA Final'!A:F,6,FALSE) -> 1 | J56: =VLOOKUP(B56,'CBG Final'!A:B,2,FALSE) -> 3 | K56: =0.3*F56+0.2*G56+0.2*H56+I56*0.1+J56*0.2 -> 1.9 | L56: 97,690 | M56: 1% | N56: 7,091 | O56: -52.7% | P56: 122,070 | Q56: 4 | R56: 5
B57: JBS | C57: Brazil | D57: Food Processing | E57: 281974 | F57: {=_xlfn.IFS( E57<=$E$245,0, E57<=$E$246,1, E57<=$E$247,2, E57>=$E$247,3)} -> 3 | G57: {=_xlfn.IFS( OR(D57="Aerospace",D57="Aerospace & Defense",D57="Agricultural Equipment",D57="Airlines",D57="Automotive",D57="Automotive & Energy",D57="Automotive Components",D57="Aviation",D57="Building Materials",D57="Chemicals",D57="Commercial Vehicles",D57="Conglomerate & Defense",D57="Conglomerate & Energy",D57="Construction",D57="Construction & Infrastructure",D57="Construction & Real Estate",D57="Construction & Telecom",D57="Discount Retail",D57="Energy Management",D57="Energy Technology",D57="Engines & Power Systems",D57="Environmental Services",D57="Food Distribution",D57="Food Services",D57="Grocery Retail",D57="Healthcare & Pharmacy",D57="Home Improvement Retail",D57="Industrial Engineering & Electronics",D57="Oilfield Services",D57="Pharmaceuticals",D57="Pharmaceuticals & Chemicals",D57="Pharmaceuticals & Healthcare",D57="Pharmacy Retail",D57="Postal & Logistics",D57="Retail",D57="Retail & Distribution",D57="Retail & Grocery",D57="Retail (IKEA)",D57="Tobacco",D57="Trading & Conglomerate",D57="Utilities",D57="Utilities & Energy",D57="Wholesale Retail"),2, OR(D57="Agribusiness",D57="Automotive & Heavy Vehicles",D57="Chemicals",D57="Commercial Vehicles",D57="Construction",D57="Construction & Infrastructure",D57="Engines & Power Systems",D57="Food Processing",D57="Healthcare",D57="Healthcare & Medical Devices",D57="Heavy Equipment",D57="Heavy Industry",D57="Industrial Gases",D57="Industrial Manufacturing",D57="Logistics",D57="Medical Devices",D57="Mining",D57="Mining & Commodities Trading",D57="Oil & Gas",D57="Oilfield Services",D57="Rail Transport",D57="Shipping & Logistics",D57="Steel"),3, OR(D57="Apparel & Footwear",D57="Beverage",D57="Coffeehouse & Retail",D57="Conglomerate",D57="Consumer Goods",D57="Convenience Retail",D57="Electronics",D57="Electronics & Semiconductors",D57="Electronics Retail",D57="Fashion Retail",D57="Food & Beverage",D57="Food Retail & Consumer Goods",D57="Industrial & Technology",D57="Industrial Automation",D57="Industrial Technology",D57="Postal & Financial Services",D57="Postal Services",D57="Scientific Instruments",D57="Technology Hardware",D57="Trading Company",D57="IT Consulting"),1, OR(D57="Cosmetics",D57="E-commerce & Cloud Computing",D57="Electronics & Entertainment",D57="Entertainment & Media",D57="Luxury Goods",D57="Media & Telecommunications",D57="Networking Technology",D57="Real Estate Services",D57="Technology & Consumer Electronics",D57="Telecommunications",D57="Telecommunications & Investment"),1, OR(D57="Asset Management",D57="Banking",D57="Banking & Asset Services",D57="Banking & Financial Services",D57="Banking & Wealth Management",D57="Cloud Software",D57="Enterprise Software",D57="Financial Services",D57="Information Technology Consulting",D57="Investment Banking",D57="Social Media & Technology",D57="Software & Cloud Computing",D57="Technology & Consulting",D57="Technology & Internet Services",D57="Technology & Software"),1, TRUE,"Unmapped" )} -> 3 | H57: =VLOOKUP(B57,'BIS + EDBA Final'!A:K,2,FALSE) -> 1 | I57: =VLOOKUP(B57,'BIS + EDBA Final'!A:F,6,FALSE) -> 0 | J57: =VLOOKUP(B57,'CBG Final'!A:B,2,FALSE) -> 1 | K57: =0.3*F57+0.2*G57+0.2*H57+I57*0.1+J57*0.2 -> 1.9 | L57: 77,182.6 | M57: 5.9% | N57: 1,766.9 | P57: 40,685.4 | Q57: 9 | R57: 16
B58: SNCF Group | C58: France | D58: Rail Transport | E58: 289500 | F58: {=_xlfn.IFS( E58<=$E$245,0, E58<=$E$246,1, E58<=$E$247,2, E58>=$E$247,3)} -> 3 | G58: {=_xlfn.IFS( OR(D58="Aerospace",D58="Aerospace & Defense",D58="Agricultural Equipment",D58="Airlines",D58="Automotive",D58="Automotive & Energy",D58="Automotive Components",D58="Aviation",D58="Building Materials",D58="Chemicals",D58="Commercial Vehicles",D58="Conglomerate & Defense",D58="Conglomerate & Energy",D58="Construction",D58="Construction & Infrastructure",D58="Construction & Real Estate",D58="Construction & Telecom",D58="Discount Retail",D58="Energy Management",D58="Energy Technology",D58="Engines & Power Systems",D58="Environmental Services",D58="Food Distribution",D58="Food Services",D58="Grocery Retail",D58="Healthcare & Pharmacy",D58="Home Improvement Retail",D58="Industrial Engineering & Electronics",D58="Oilfield Services",D58="Pharmaceuticals",D58="Pharmaceuticals & Chemicals",D58="Pharmaceuticals & Healthcare",D58="Pharmacy Retail",D58="Postal & Logistics",D58="Retail",D58="Retail & Distribution",D58="Retail & Grocery",D58="Retail (IKEA)",D58="Tobacco",D58="Trading & Conglomerate",D58="Utilities",D58="Utilities & Energy",D58="Wholesale Retail"),2, OR(D58="Agribusiness",D58="Automotive & Heavy Vehicles",D58="Chemicals",D58="Commercial Vehicles",D58="Construction",D58="Construction & Infrastructure",D58="Engines & Power Systems",D58="Food Processing",D58="Healthcare",D58="Healthcare & Medical Devices",D58="Heavy Equipment",D58="Heavy Industry",D58="Industrial Gases",D58="Industrial Manufacturing",D58="Logistics",D58="Medical Devices",D58="Mining",D58="Mining & Commodities Trading",D58="Oil & Gas",D58="Oilfield Services",D58="Rail Transport",D58="Shipping & Logistics",D58="Steel"),3, OR(D58="Apparel & Footwear",D58="Beverage",D58="Coffeehouse & Retail",D58="Conglomerate",D58="Consumer Goods",D58="Convenience Retail",D58="Electronics",D58="Electronics & Semiconductors",D58="Electronics Retail",D58="Fashion Retail",D58="Food & Beverage",D58="Food Retail & Consumer Goods",D58="Industrial & Technology",D58="Industrial Automation",D58="Industrial Technology",D58="Postal & Financial Services",D58="Postal Services",D58="Scientific Instruments",D58="Technology Hardware",D58="Trading Company",D58="IT Consulting"),1, OR(D58="Cosmetics",D58="E-commerce & Cloud Computing",D58="Electronics & Entertainment",D58="Entertainment & Media",D58="Luxury Goods",D58="Media & Telecommunications",D58="Networking Technology",D58="Real Estate Services",D58="Technology & Consumer Electronics",D58="Telecommunications",D58="Telecommunications & Investment"),1, OR(D58="Asset Management",D58="Banking",D58="Banking & Asset Services",D58="Banking & Financial Services",D58="Banking & Wealth Management",D58="Cloud Software",D58="Enterprise Software",D58="Financial Services",D58="Information Technology Consulting",D58="Investment Banking",D58="Social Media & Technology",D58="Software & Cloud Computing",D58="Technology & Consulting",D58="Technology & Internet Services",D58="Technology & Software"),1, TRUE,"Unmapped" )} -> 3 | H58: =VLOOKUP(B58,'BIS + EDBA Final'!A:K,2,FALSE) -> 1 | I58: =VLOOKUP(B58,'BIS + EDBA Final'!A:F,6,FALSE) -> 0 | J58: =VLOOKUP(B58,'CBG Final'!A:B,2,FALSE) -> 1 | K58: =0.3*F58+0.2*G58+0.2*H58+I58*0.1+J58*0.2 -> 1.9 | L58: 46,884.4 | M58: 3.9% | N58: 1,683.8 | O58: 18.9% | P58: 130,079.7 | Q58: 13 | R58: 31
B59: Saint-Gobain | C59: France | D59: Building Materials | E59: 158413 | F59: {=_xlfn.IFS( E59<=$E$245,0, E59<=$E$246,1, E59<=$E$247,2, E59>=$E$247,3)} -> 2 | G59: {=_xlfn.IFS( OR(D59="Aerospace",D59="Aerospace & Defense",D59="Agricultural Equipment",D59="Airlines",D59="Automotive",D59="Automotive & Energy",D59="Automotive Components",D59="Aviation",D59="Building Materials",D59="Chemicals",D59="Commercial Vehicles",D59="Conglomerate & Defense",D59="Conglomerate & Energy",D59="Construction",D59="Construction & Infrastructure",D59="Construction & Real Estate",D59="Construction & Telecom",D59="Discount Retail",D59="Energy Management",D59="Energy Technology",D59="Engines & Power Systems",D59="Environmental Services",D59="Food Distribution",D59="Food Services",D59="Grocery Retail",D59="Healthcare & Pharmacy",D59="Home Improvement Retail",D59="Industrial Engineering & Electronics",D59="Oilfield Services",D59="Pharmaceuticals",D59="Pharmaceuticals & Chemicals",D59="Pharmaceuticals & Healthcare",D59="Pharmacy Retail",D59="Postal & Logistics",D59="Retail",D59="Retail & Distribution",D59="Retail & Grocery",D59="Retail (IKEA)",D59="Tobacco",D59="Trading & Conglomerate",D59="Utilities",D59="Utilities & Energy",D59="Wholesale Retail"),2, OR(D59="Agribusiness",D59="Automotive & Heavy Vehicles",D59="Chemicals",D59="Commercial Vehicles",D59="Construction",D59="Construction & Infrastructure",D59="Engines & Power Systems",D59="Food Processing",D59="Healthcare",D59="Healthcare & Medical Devices",D59="Heavy Equipment",D59="Heavy Industry",D59="Industrial Gases",D59="Industrial Manufacturing",D59="Logistics",D59="Medical Devices",D59="Mining",D59="Mining & Commodities Trading",D59="Oil & Gas",D59="Oilfield Services",D59="Rail Transport",D59="Shipping & Logistics",D59="Steel"),3, OR(D59="Apparel & Footwear",D59="Beverage",D59="Coffeehouse & Retail",D59="Conglomerate",D59="Consumer Goods",D59="Convenience Retail",D59="Electronics",D59="Electronics & Semiconductors",D59="Electronics Retail",D59="Fashion Retail",D59="Food & Beverage",D59="Food Retail & Consumer Goods",D59="Industrial & Technology",D59="Industrial Automation",D59="Industrial Technology",D59="Postal & Financial Services",D59="Postal Services",D59="Scientific Instruments",D59="Technology Hardware",D59="Trading Company",D59="IT Consulting"),1, OR(D59="Cosmetics",D59="E-commerce & Cloud Computing",D59="Electronics & Entertainment",D59="Entertainment & Media",D59="Luxury Goods",D59="Media & Telecommunications",D59="Networking Technology",D59="Real Estate Services",D59="Technology & Consumer Electronics",D59="Telecommunications",D59="Telecommunications & Investment"),1, OR(D59="Asset Management",D59="Banking",D59="Banking & Asset Services",D59="Banking & Financial Services",D59="Banking & Wealth Management",D59="Cloud Software",D59="Enterprise Software",D59="Financial Services",D59="Information Technology Consulting",D59="Investment Banking",D59="Social Media & Technology",D59="Software & Cloud Computing",D59="Technology & Consulting",D59="Technology & Internet Services",D59="Technology & Software"),1, TRUE,"Unmapped" )} -> 2 | H59: 2 | I59: =VLOOKUP(B59,'BIS + EDBA Final'!A:F,6,FALSE) -> 1 | J59: =VLOOKUP(B59,'CBG Final'!A:B,2,FALSE) -> 2 | K59: =0.3*F59+0.2*G59+0.2*H59+I59*0.1+J59*0.2 -> 1.9 | L59: 50,363.4 | M59: -2.8% | N59: 3,075.6 | O59: 5.4% | P59: 63,903.5 | Q59: -18 | R59: 31
B60: Royal Ahold Delhaize | C60: Netherlands | D60: Grocery Retail | E60: 222000 | F60: {=_xlfn.IFS( E60<=$E$245,0, E60<=$E$246,1, E60<=$E$247,2, E60>=$E$247,3)} -> 3 | G60: {=_xlfn.IFS( OR(D60="Aerospace",D60="Aerospace & Defense",D60="Agricultural Equipment",D60="Airlines",D60="Automotive",D60="Automotive & Energy",D60="Automotive Components",D60="Aviation",D60="Building Materials",D60="Chemicals",D60="Commercial Vehicles",D60="Conglomerate & Defense",D60="Conglomerate & Energy",D60="Construction",D60="Construction & Infrastructure",D60="Construction & Real Estate",D60="Construction & Telecom",D60="Discount Retail",D60="Energy Management",D60="Energy Technology",D60="Engines & Power Systems",D60="Environmental Services",D60="Food Distribution",D60="Food Services",D60="Grocery Retail",D60="Healthcare & Pharmacy",D60="Home Improvement Retail",D60="Industrial Engineering & Electronics",D60="Oilfield Services",D60="Pharmaceuticals",D60="Pharmaceuticals & Chemicals",D60="Pharmaceuticals & Healthcare",D60="Pharmacy Retail",D60="Postal & Logistics",D60="Retail",D60="Retail & Distribution",D60="Retail & Grocery",D60="Retail (IKEA)",D60="Tobacco",D60="Trading & Conglomerate",D60="Utilities",D60="Utilities & Energy",D60="Wholesale Retail"),2, OR(D60="Agribusiness",D60="Automotive & Heavy Vehicles",D60="Chemicals",D60="Commercial Vehicles",D60="Construction",D60="Construction & Infrastructure",D60="Engines & Power Systems",D60="Food Processing",D60="Healthcare",D60="Healthcare & Medical Devices",D60="Heavy Equipment",D60="Heavy Industry",D60="Industrial Gases",D60="Industrial Manufacturing",D60="Logistics",D60="Medical Devices",D60="Mining",D60="Mining & Commodities Trading",D60="Oil & Gas",D60="Oilfield Services",D60="Rail Transport",D60="Shipping & Logistics",D60="Steel"),3, OR(D60="Apparel & Footwear",D60="Beverage",D60="Coffeehouse & Retail",D60="Conglomerate",D60="Consumer Goods",D60="Convenience Retail",D60="Electronics",D60="Electronics & Semiconductors",D60="Electronics Retail",D60="Fashion Retail",D60="Food & Beverage",D60="Food Retail & Consumer Goods",D60="Industrial & Technology",D60="Industrial Automation",D60="Industrial Technology",D60="Postal & Financial Services",D60="Postal Services",D60="Scientific Instruments",D60="Technology Hardware",D60="Trading Company",D60="IT Consulting"),1, OR(D60="Cosmetics",D60="E-commerce & Cloud Computing",D60="Electronics & Entertainment",D60="Entertainment & Media",D60="Luxury Goods",D60="Media & Telecommunications",D60="Networking Technology",D60="Real Estate Services",D60="Technology & Consumer Electronics",D60="Telecommunications",D60="Telecommunications & Investment"),1, OR(D60="Asset Management",D60="Banking",D60="Banking & Asset Services",D60="Banking & Financial Services",D60="Banking & Wealth Management",D60="Cloud Software",D60="Enterprise Software",D60="Financial Services",D60="Information Technology Consulting",D60="Investment Banking",D60="Social Media & Technology",D60="Software & Cloud Computing",D60="Technology & Consulting",D60="Technology & Internet Services",D60="Technology & Software"),1, TRUE,"Unmapped" )} -> 2 | H60: =VLOOKUP(B60,'BIS + EDBA Final'!A:K,2,FALSE) -> 1 | I60: =VLOOKUP(B60,'BIS + EDBA Final'!A:F,6,FALSE) -> 0 | J60: =VLOOKUP(B60,'CBG Final'!A:B,2,FALSE) -> 2 | K60: =0.3*F60+0.2*G60+0.2*H60+I60*0.1+J60*0.2 -> 1.9 | L60: 96,632.4 | M60: 0.8% | N60: 1,907.7 | O60: -5.8% | P60: 53,677.8 | Q60: 6 | R60: 31
